Workbook

Sheet ПФ2026
C1: -1
B3: Статьи Затрат | C3: 1 квартал 2026г. | I3: 2 квартал 2026г. | O3: 3 квартал 2026г. | U3: 4 квартал 2026г. | AA3: Общий Итог
C4: Январь | E4: Февраль | G4: Март | I4: Апрель | K4: Май | M4: Июнь | O4: Июль | Q4: Август | S4: Сентябрь | U4: Октябрь | W4: Ноябрь | Y4: Декабрь
C5: План | D5: Факт | E5: План | F5: Факт | G5: План | H5: Факт | I5: План | J5: Факт | K5: План | L5: Факт | M5: План | N5: Факт | O5: План | P5: Факт | Q5: План | R5: Факт | S5: План | T5: Факт | U5: План | V5: Факт | W5: План | X5: Факт | Y5: План | Z5: Факт | AA5: План | AB5: Факт | AC5: Откл %
B6: Маржинальная прибыль | C6: =C7+C13 -> 1.3314047e+08 | D6: =D7+D13 -> 1.6298824e+08 | E6: =E7+E13 -> 1.4464568e+08 | F6: =F7+F13 -> 1.7509059e+08 | G6: =G7+G13 -> 2.2596815e+08 | H6: =H7+H13 -> 2.3707425e+08 | I6: =I7+I13 -> 3.5249091e+08 | J6: =J7+J13 -> 3.5113252e+08 | ... Z6: =Z7+Z13 -> 0 | AA6: =C6+E6+G6+I6+K6+M6+O6+Q6+S6+U6+W6+Y6 -> 3.4235606e+09 | AB6: =D6+F6+H6+J6+L6+N6+P6+R6+T6+V6+X6+Z6 -> 1.8698216e+09 | AC6: =IFERROR(AB6/AA6,0) -> 0.54616284
B7: Доходы | C7: =SUM(C8,C10) -> 2.237922e+08 | D7: =SUM(D8,D10) -> 2.8666775e+08 | E7: =SUM(E8,E10) -> 2.3967435e+08 | F7: =SUM(F8,F10) -> 3.0542055e+08 | G7: =SUM(G8,G10) -> 3.52725e+08 | H7: =SUM(H8,H10) -> 3.8098314e+08 | I7: =SUM(I8,I10) -> 5.2254876e+08 | J7: =SUM(J8,J10) -> 5.2521408e+08 | ... Z7: =SUM(Z8,Z10) -> 0 | AA7: =C7+E7+G7+I7+K7+M7+O7+Q7+S7+U7+W7+Y7 -> 5.2187376e+09 | AB7: =D7+F7+H7+J7+L7+N7+P7+R7+T7+V7+X7+Z7 -> 2.8635376e+09 | AC7: =IFERROR(AB7/AA7,0) -> 0.54870312
B8: Доход от основной деятельности | C8: =SUM(C9) -> 2.237922e+08 | D8: =SUM(D9) -> 2.8664104e+08 | E8: =SUM(E9) -> 2.3967435e+08 | F8: =SUM(F9) -> 3.0539731e+08 | G8: =SUM(G9) -> 3.52725e+08 | H8: =SUM(H9) -> 3.8095762e+08 | I8: =SUM(I9) -> 5.2254876e+08 | J8: =SUM(J9) -> 5.2520057e+08 | ... Z8: =SUM(Z9) -> 0 | AA8: =SUM(C8,E8,G8,I8,K8,M8,O68,O8,Q8,S8,Y8,W8,U8) -> 5.2187366e+09 | AB8: =D8+F8+H8+J8+L8+N8+P8+R8+T8+V8+X8+Z8 -> 2.8634187e+09 | AC8: =IFERROR(AB8/AA8,0) -> 0.54868045
B9: Доход от основной деятельности | C9: =SUMIFS(data!$G:$G,data!$A:$A,$B$6,data!$B:$B,$B$7,data!$C:$C,$B$8,data!$F:$F,C$4,data!$E:$E,$B9,data!$H:$H,ПФ2026!C$5) -> 2.237922e+08 | D9: =SUMIFS(data!$G:$G,data!$A:$A,$B$6,data!$B:$B,$B$7,data!$C:$C,$B$8,data!$F:$F,C$4,data!$E:$E,$B9,data!$H:$H,ПФ2026!D$5) -> 2.8664104e+08 | E9: =SUMIFS(data!$G:$G,data!$A:$A,$B$6,data!$B:$B,$B$7,data!$C:$C,$B$8,data!$F:$F,E$4,data!$E:$E,$B9,data!$H:$H,ПФ2026!E$5) -> 2.3967435e+08 | F9: =SUMIFS(data!$G:$G,data!$A:$A,$B$6,data!$B:$B,$B$7,data!$C:$C,$B$8,data!$F:$F,E$4,data!$E:$E,$B9,data!$H:$H,ПФ2026!F$5) -> 3.0539731e+08 | G9: =SUMIFS(data!$G:$G,data!$A:$A,$B$6,data!$B:$B,$B$7,data!$C:$C,$B$8,data!$F:$F,G$4,data!$E:$E,$B9,data!$H:$H,ПФ2026!G$5) -> 3.52725e+08 | H9: =SUMIFS(data!$G:$G,data!$A:$A,$B$6,data!$B:$B,$B$7,data!$C:$C,$B$8,data!$F:$F,G$4,data!$E:$E,$B9,data!$H:$H,ПФ2026!H$5) -> 3.8095762e+08 | I9: =SUMIFS(data!$G:$G,data!$A:$A,$B$6,data!$B:$B,$B$7,data!$C:$C,$B$8,data!$F:$F,I$4,data!$E:$E,$B9,data!$H:$H,ПФ2026!I$5) -> 5.2254876e+08 | J9: =SUMIFS(data!$G:$G,data!$A:$A,$B$6,data!$B:$B,$B$7,data!$C:$C,$B$8,data!$F:$F,I$4,data!$E:$E,$B9,data!$H:$H,ПФ2026!J$5) -> 5.2520057e+08 | K9: =SUMIFS(data!$G:$G,data!$A:$A,$B$6,data!$B:$B,$B$7,data!$C:$C,$B$8,data!$F:$F,K$4,data!$E:$E,$B9,data!$H:$H,ПФ2026!K$5) -> 6.219339e+08 | L9: =SUMIFS(data!$G:$G,data!$A:$A,$B$6,data!$B:$B,$B$7,data!$C:$C,$B$8,data!$F:$F,K$4,data!$E:$E,$B9,data!$H:$H,ПФ2026!L$5) -> 5.8823019e+08 | M9: =SUMIFS(data!$G:$G,data!$A:$A,$B$6,data!$B:$B,$B$7,data!$C:$C,$B$8,data!$F:$F,M$4,data!$E:$E,$B9,data!$H:$H,ПФ2026!M$5) -> 6.4493543e+08 | N9: =SUMIFS(data!$G:$G,data!$A:$A,$B$6,data!$B:$B,$B$7,data!$C:$C,$B$8,data!$F:$F,M$4,data!$E:$E,$B9,data!$H:$H,ПФ2026!N$5) -> 7.76992e+08 | O9: =SUMIFS(data!$G:$G,data!$A:$A,$B$6,data!$B:$B,$B$7,data!$C:$C,$B$8,data!$F:$F,O$4,data!$E:$E,$B9,data!$H:$H,ПФ2026!O$5) -> 7.6191424e+08 | P9: =SUMIFS(data!$G:$G,data!$A:$A,$B$6,data!$B:$B,$B$7,data!$C:$C,$B$8,data!$F:$F,O$4,data!$E:$E,$B9,data!$H:$H,ПФ2026!P$5) -> 0 | Q9: =SUMIFS(data!$G:$G,data!$A:$A,$B$6,data!$B:$B,$B$7,data!$C:$C,$B$8,data!$F:$F,Q$4,data!$E:$E,$B9,data!$H:$H,ПФ2026!Q$5) -> 6.6416884e+08 | R9: =SUMIFS(data!$G:$G,data!$A:$A,$B$6,data!$B:$B,$B$7,data!$C:$C,$B$8,data!$F:$F,Q$4,data!$E:$E,$B9,data!$H:$H,ПФ2026!R$5) -> 0 | S9: =SUMIFS(data!$G:$G,data!$A:$A,$B$6,data!$B:$B,$B$7,data!$C:$C,$B$8,data!$F:$F,S$4,data!$E:$E,$B9,data!$H:$H,ПФ2026!S$5) -> 4.4556039e+08 | T9: =SUMIFS(data!$G:$G,data!$A:$A,$B$6,data!$B:$B,$B$7,data!$C:$C,$B$8,data!$F:$F,S$4,data!$E:$E,$B9,data!$H:$H,ПФ2026!T$5) -> 0 | U9: =SUMIFS(data!$G:$G,data!$A:$A,$B$6,data!$B:$B,$B$7,data!$C:$C,$B$8,data!$F:$F,U$4,data!$E:$E,$B9,data!$H:$H,ПФ2026!U$5) -> 2.7591841e+08 | V9: =SUMIFS(data!$G:$G,data!$A:$A,$B$6,data!$B:$B,$B$7,data!$C:$C,$B$8,data!$F:$F,U$4,data!$E:$E,$B9,data!$H:$H,ПФ2026!V$5) -> 0 | W9: =SUMIFS(data!$G:$G,data!$A:$A,$B$6,data!$B:$B,$B$7,data!$C:$C,$B$8,data!$F:$F,W$4,data!$E:$E,$B9,data!$H:$H,ПФ2026!W$5) -> 2.4099837e+08 | X9: =SUMIFS(data!$G:$G,data!$A:$A,$B$6,data!$B:$B,$B$7,data!$C:$C,$B$8,data!$F:$F,W$4,data!$E:$E,$B9,data!$H:$H,ПФ2026!X$5) -> 0 | Y9: =SUMIFS(data!$G:$G,data!$A:$A,$B$6,data!$B:$B,$B$7,data!$C:$C,$B$8,data!$F:$F,Y$4,data!$E:$E,$B9,data!$H:$H,ПФ2026!Y$5) -> 2.2456769e+08 | Z9: =SUMIFS(data!$G:$G,data!$A:$A,$B$6,data!$B:$B,$B$7,data!$C:$C,$B$8,data!$F:$F,Y$4,data!$E:$E,$B9,data!$H:$H,ПФ2026!Z$5) -> 0 | AA9: =SUM(C9,E9,G9,I9,K9,M9,O69,O9,Q9,S9,Y9,W9,U9) -> 5.2187176e+09 | AB9: =D9+F9+H9+J9+L9+N9+P9+R9+T9+V9+X9+Z9 -> 2.8634187e+09 | AC9: =IFERROR(AB9/AA9,0) -> 0.54868245
B10: Доход от неосновной деятельности | C10: =SUM(C11:C12) -> 0 | D10: =SUM(D11:D12) -> 26705 | E10: =SUM(E11:E12) -> 0 | F10: =SUM(F11:F12) -> 23239 | G10: =SUM(G11:G12) -> 0 | H10: =SUM(H11:H12) -> 25523 | I10: =SUM(I11:I12) -> 0 | J10: =SUM(J11:J12) -> 13507.3 | ... Z10: =SUM(Z11:Z12) -> 0 | AA10: =SUM(C10,E10,G10,I10,K10,M10,O70,O10,Q10,S10,Y10,W10,U10) -> -3444440 | AB10: =D10+F10+H10+J10+L10+N10+P10+R10+T10+V10+X10+Z10 -> 118831.6 | AC10: =IFERROR(AB10/AA10,0) -> -0.034499541
B11: Доход от аренды помещений | C11: =SUMIFS(data!$G:$G,data!$A:$A,$B$6,data!$B:$B,$B$7,data!$C:$C,$B$10,data!$F:$F,C$4,data!$E:$E,$B11,data!$H:$H,ПФ2026!C$5) -> 0 | D11: =SUMIFS(data!$G:$G,data!$A:$A,$B$6,data!$B:$B,$B$7,data!$C:$C,$B$10,data!$F:$F,C$4,data!$E:$E,$B11,data!$H:$H,ПФ2026!D$5) -> 1350 | E11: =SUMIFS(data!$G:$G,data!$A:$A,$B$6,data!$B:$B,$B$7,data!$C:$C,$B$10,data!$F:$F,E$4,data!$E:$E,$B11,data!$H:$H,ПФ2026!E$5) -> 0 | F11: =SUMIFS(data!$G:$G,data!$A:$A,$B$6,data!$B:$B,$B$7,data!$C:$C,$B$10,data!$F:$F,E$4,data!$E:$E,$B11,data!$H:$H,ПФ2026!F$5) -> 0 | G11: =SUMIFS(data!$G:$G,data!$A:$A,$B$6,data!$B:$B,$B$7,data!$C:$C,$B$10,data!$F:$F,G$4,data!$E:$E,$B11,data!$H:$H,ПФ2026!G$5) -> 0 | H11: =SUMIFS(data!$G:$G,data!$A:$A,$B$6,data!$B:$B,$B$7,data!$C:$C,$B$10,data!$F:$F,G$4,data!$E:$E,$B11,data!$H:$H,ПФ2026!H$5) -> 3873 | I11: =SUMIFS(data!$G:$G,data!$A:$A,$B$6,data!$B:$B,$B$7,data!$C:$C,$B$10,data!$F:$F,I$4,data!$E:$E,$B11,data!$H:$H,ПФ2026!I$5) -> 0 | J11: =SUMIFS(data!$G:$G,data!$A:$A,$B$6,data!$B:$B,$B$7,data!$C:$C,$B$10,data!$F:$F,I$4,data!$E:$E,$B11,data!$H:$H,ПФ2026!J$5) -> 507.3 | K11: =SUMIFS(data!$G:$G,data!$A:$A,$B$6,data!$B:$B,$B$7,data!$C:$C,$B$10,data!$F:$F,K$4,data!$E:$E,$B11,data!$H:$H,ПФ2026!K$5) -> 0 | L11: =SUMIFS(data!$G:$G,data!$A:$A,$B$6,data!$B:$B,$B$7,data!$C:$C,$B$10,data!$F:$F,K$4,data!$E:$E,$B11,data!$H:$H,ПФ2026!L$5) -> 507.3 | M11: =SUMIFS(data!$G:$G,data!$A:$A,$B$6,data!$B:$B,$B$7,data!$C:$C,$B$10,data!$F:$F,M$4,data!$E:$E,$B11,data!$H:$H,ПФ2026!M$5) -> 0 | N11: =SUMIFS(data!$G:$G,data!$A:$A,$B$6,data!$B:$B,$B$7,data!$C:$C,$B$10,data!$F:$F,M$4,data!$E:$E,$B11,data!$H:$H,ПФ2026!N$5) -> 0 | O11: =SUMIFS(data!$G:$G,data!$A:$A,$B$6,data!$B:$B,$B$7,data!$C:$C,$B$10,data!$F:$F,O$4,data!$E:$E,$B11,data!$H:$H,ПФ2026!O$5) -> 0 | P11: =SUMIFS(data!$G:$G,data!$A:$A,$B$6,data!$B:$B,$B$7,data!$C:$C,$B$10,data!$F:$F,O$4,data!$E:$E,$B11,data!$H:$H,ПФ2026!P$5) -> 0 | Q11: =SUMIFS(data!$G:$G,data!$A:$A,$B$6,data!$B:$B,$B$7,data!$C:$C,$B$10,data!$F:$F,Q$4,data!$E:$E,$B11,data!$H:$H,ПФ2026!Q$5) -> 0 | R11: =SUMIFS(data!$G:$G,data!$A:$A,$B$6,data!$B:$B,$B$7,data!$C:$C,$B$10,data!$F:$F,Q$4,data!$E:$E,$B11,data!$H:$H,ПФ2026!R$5) -> 0 | S11: =SUMIFS(data!$G:$G,data!$A:$A,$B$6,data!$B:$B,$B$7,data!$C:$C,$B$10,data!$F:$F,S$4,data!$E:$E,$B11,data!$H:$H,ПФ2026!S$5) -> 0 | T11: =SUMIFS(data!$G:$G,data!$A:$A,$B$6,data!$B:$B,$B$7,data!$C:$C,$B$10,data!$F:$F,S$4,data!$E:$E,$B11,data!$H:$H,ПФ2026!T$5) -> 0 | U11: =SUMIFS(data!$G:$G,data!$A:$A,$B$6,data!$B:$B,$B$7,data!$C:$C,$B$10,data!$F:$F,U$4,data!$E:$E,$B11,data!$H:$H,ПФ2026!U$5) -> 0 | V11: =SUMIFS(data!$G:$G,data!$A:$A,$B$6,data!$B:$B,$B$7,data!$C:$C,$B$10,data!$F:$F,U$4,data!$E:$E,$B11,data!$H:$H,ПФ2026!V$5) -> 0 | W11: =SUMIFS(data!$G:$G,data!$A:$A,$B$6,data!$B:$B,$B$7,data!$C:$C,$B$10,data!$F:$F,W$4,data!$E:$E,$B11,data!$H:$H,ПФ2026!W$5) -> 0 | X11: =SUMIFS(data!$G:$G,data!$A:$A,$B$6,data!$B:$B,$B$7,data!$C:$C,$B$10,data!$F:$F,W$4,data!$E:$E,$B11,data!$H:$H,ПФ2026!X$5) -> 0 | Y11: =SUMIFS(data!$G:$G,data!$A:$A,$B$6,data!$B:$B,$B$7,data!$C:$C,$B$10,data!$F:$F,Y$4,data!$E:$E,$B11,data!$H:$H,ПФ2026!Y$5) -> 0 | Z11: =SUMIFS(data!$G:$G,data!$A:$A,$B$6,data!$B:$B,$B$7,data!$C:$C,$B$10,data!$F:$F,Y$4,data!$E:$E,$B11,data!$H:$H,ПФ2026!Z$5) -> 0 | AA11: =SUM(C11,E11,G11,I11,K11,M11,O71,O11,Q11,S11) -> -3000000 | AB11: =SUM(D11,F11,H11,J11,L11,N11,P71,P11,R11,T11) -> 6237.6 | AC11: =IFERROR(AB11/AA11,0) -> -0.0020792
B12: Доход от услуг | C12: =SUMIFS(data!$G:$G,data!$A:$A,$B$6,data!$B:$B,$B$7,data!$C:$C,$B$10,data!$F:$F,C$4,data!$E:$E,$B12,data!$H:$H,ПФ2026!C$5) -> 0 | D12: =SUMIFS(data!$G:$G,data!$A:$A,$B$6,data!$B:$B,$B$7,data!$C:$C,$B$10,data!$F:$F,C$4,data!$E:$E,$B12,data!$H:$H,ПФ2026!D$5) -> 25355 | E12: =SUMIFS(data!$G:$G,data!$A:$A,$B$6,data!$B:$B,$B$7,data!$C:$C,$B$10,data!$F:$F,E$4,data!$E:$E,$B12,data!$H:$H,ПФ2026!E$5) -> 0 | F12: =SUMIFS(data!$G:$G,data!$A:$A,$B$6,data!$B:$B,$B$7,data!$C:$C,$B$10,data!$F:$F,E$4,data!$E:$E,$B12,data!$H:$H,ПФ2026!F$5) -> 23239 | G12: =SUMIFS(data!$G:$G,data!$A:$A,$B$6,data!$B:$B,$B$7,data!$C:$C,$B$10,data!$F:$F,G$4,data!$E:$E,$B12,data!$H:$H,ПФ2026!G$5) -> 0 | H12: =SUMIFS(data!$G:$G,data!$A:$A,$B$6,data!$B:$B,$B$7,data!$C:$C,$B$10,data!$F:$F,G$4,data!$E:$E,$B12,data!$H:$H,ПФ2026!H$5) -> 21650 | I12: =SUMIFS(data!$G:$G,data!$A:$A,$B$6,data!$B:$B,$B$7,data!$C:$C,$B$10,data!$F:$F,I$4,data!$E:$E,$B12,data!$H:$H,ПФ2026!I$5) -> 0 | J12: =SUMIFS(data!$G:$G,data!$A:$A,$B$6,data!$B:$B,$B$7,data!$C:$C,$B$10,data!$F:$F,I$4,data!$E:$E,$B12,data!$H:$H,ПФ2026!J$5) -> 13000 | K12: =SUMIFS(data!$G:$G,data!$A:$A,$B$6,data!$B:$B,$B$7,data!$C:$C,$B$10,data!$F:$F,K$4,data!$E:$E,$B12,data!$H:$H,ПФ2026!K$5) -> 0 | L12: =SUMIFS(data!$G:$G,data!$A:$A,$B$6,data!$B:$B,$B$7,data!$C:$C,$B$10,data!$F:$F,K$4,data!$E:$E,$B12,data!$H:$H,ПФ2026!L$5) -> 9850 | M12: =SUMIFS(data!$G:$G,data!$A:$A,$B$6,data!$B:$B,$B$7,data!$C:$C,$B$10,data!$F:$F,M$4,data!$E:$E,$B12,data!$H:$H,ПФ2026!M$5) -> 0 | N12: =SUMIFS(data!$G:$G,data!$A:$A,$B$6,data!$B:$B,$B$7,data!$C:$C,$B$10,data!$F:$F,M$4,data!$E:$E,$B12,data!$H:$H,ПФ2026!N$5) -> 19500 | O12: =SUMIFS(data!$G:$G,data!$A:$A,$B$6,data!$B:$B,$B$7,data!$C:$C,$B$10,data!$F:$F,O$4,data!$E:$E,$B12,data!$H:$H,ПФ2026!O$5) -> 0 | P12: =SUMIFS(data!$G:$G,data!$A:$A,$B$6,data!$B:$B,$B$7,data!$C:$C,$B$10,data!$F:$F,O$4,data!$E:$E,$B12,data!$H:$H,ПФ2026!P$5) -> 0 | Q12: =SUMIFS(data!$G:$G,data!$A:$A,$B$6,data!$B:$B,$B$7,data!$C:$C,$B$10,data!$F:$F,Q$4,data!$E:$E,$B12,data!$H:$H,ПФ2026!Q$5) -> 0 | R12: =SUMIFS(data!$G:$G,data!$A:$A,$B$6,data!$B:$B,$B$7,data!$C:$C,$B$10,data!$F:$F,Q$4,data!$E:$E,$B12,data!$H:$H,ПФ2026!R$5) -> 0 | S12: =SUMIFS(data!$G:$G,data!$A:$A,$B$6,data!$B:$B,$B$7,data!$C:$C,$B$10,data!$F:$F,S$4,data!$E:$E,$B12,data!$H:$H,ПФ2026!S$5) -> 0 | T12: =SUMIFS(data!$G:$G,data!$A:$A,$B$6,data!$B:$B,$B$7,data!$C:$C,$B$10,data!$F:$F,S$4,data!$E:$E,$B12,data!$H:$H,ПФ2026!T$5) -> 0 | U12: =SUMIFS(data!$G:$G,data!$A:$A,$B$6,data!$B:$B,$B$7,data!$C:$C,$B$10,data!$F:$F,U$4,data!$E:$E,$B12,data!$H:$H,ПФ2026!U$5) -> 0 | V12: =SUMIFS(data!$G:$G,data!$A:$A,$B$6,data!$B:$B,$B$7,data!$C:$C,$B$10,data!$F:$F,U$4,data!$E:$E,$B12,data!$H:$H,ПФ2026!V$5) -> 0 | W12: =SUMIFS(data!$G:$G,data!$A:$A,$B$6,data!$B:$B,$B$7,data!$C:$C,$B$10,data!$F:$F,W$4,data!$E:$E,$B12,data!$H:$H,ПФ2026!W$5) -> 0 | X12: =SUMIFS(data!$G:$G,data!$A:$A,$B$6,data!$B:$B,$B$7,data!$C:$C,$B$10,data!$F:$F,W$4,data!$E:$E,$B12,data!$H:$H,ПФ2026!X$5) -> 0 | Y12: =SUMIFS(data!$G:$G,data!$A:$A,$B$6,data!$B:$B,$B$7,data!$C:$C,$B$10,data!$F:$F,Y$4,data!$E:$E,$B12,data!$H:$H,ПФ2026!Y$5) -> 0 | Z12: =SUMIFS(data!$G:$G,data!$A:$A,$B$6,data!$B:$B,$B$7,data!$C:$C,$B$10,data!$F:$F,Y$4,data!$E:$E,$B12,data!$H:$H,ПФ2026!Z$5) -> 0 | AA12: =SUM(C12,E12,G12,I12,K12,M12,O72,O12,Q12,S12) -> -7392 | AB12: =SUM(D12,F12,H12,J12,L12,N12,P72,P12,R12,T12) -> 112594 | AC12: =IFERROR(AB12/AA12,0) -> -15.231872
B13: Расходы по себестоимости | C13: =SUM(C28,C18,C24,C14,C16) -> -90651724 | D13: =SUM(D28,D18,D24,D14,D16) -> -1.2367951e+08 | E13: =SUM(E28,E18,E24,E14,E16) -> -95028669 | F13: =SUM(F28,F18,F24,F14,F16) -> -1.3032997e+08 | G13: =SUM(G28,G18,G24,G14,G16) -> -1.2675685e+08 | H13: =SUM(H28,H18,H24,H14,H16) -> -1.4390889e+08 | I13: =SUM(I28,I18,I24,I14,I16) -> -1.7005785e+08 | J13: =SUM(J28,J18,J24,J14,J16) -> -1.7408157e+08 | ... Z13: =SUM(Z28,Z18,Z24,Z14,Z16) -> 0 | AA13: =C13+E13+G13+I13+K13+M13+O13+Q13+S13+U13+W13+Y13 -> -1.795177e+09 | AB13: =D13+F13+H13+J13+L13+N13+P13+R13+T13+V13+X13+Z13 -> -9.9371601e+08 | AC13: =IFERROR(AB13/AA13,0) -> 0.55354765
B14: Расходы по себестоимости сырья | C14: =SUM(C15) -> -67359643 | D14: =SUM(D15) -> -33676713 | E14: =SUM(E15) -> -70752129 | F14: =SUM(F15) -> -37079022 | G14: =SUM(G15) -> -1.0007111e+08 | H14: =SUM(H15) -> -26397344 | I14: =SUM(I15) -> -1.3897355e+08 | J14: =SUM(J15) -> -1.3601143e+08 | ... Z14: =SUM(Z15) -> 0 | AA14: =SUM(C14,E14,G14,I14,K14,M14,O74,O14,Q14,S14,Y14,W14,U14) -> -1.4102048e+09 | AB14: =D14+F14+H14+J14+L14+N14+P14+R14+T14+V14+X14+Z14 -> -5.023857e+08 | AC14: =IFERROR(AB14/AA14,0) -> 0.35625016
B15: Расходы по себестоимости сырья | C15: =SUMIFS(data!$G:$G,data!$C:$C,$B$13,data!$D:$D,$B$14,data!$F:$F,C$4,data!$E:$E,$B15,data!$H:$H,ПФ2026!C$5) -> -67359643 | D15: =Лист4!C$10 -> -33676713 | E15: =SUMIFS(data!$G:$G,data!$C:$C,$B$13,data!$D:$D,$B$14,data!$F:$F,E$4,data!$E:$E,$B15,data!$H:$H,ПФ2026!E$5) -> -70752129 | F15: =Лист4!D$10 -> -37079022 | G15: =SUMIFS(data!$G:$G,data!$C:$C,$B$13,data!$D:$D,$B$14,data!$F:$F,G$4,data!$E:$E,$B15,data!$H:$H,ПФ2026!G$5) -> -1.0007111e+08 | H15: =Лист4!E$10 -> -26397344 | I15: =SUMIFS(data!$G:$G,data!$C:$C,$B$13,data!$D:$D,$B$14,data!$F:$F,I$4,data!$E:$E,$B15,data!$H:$H,ПФ2026!I$5) -> -1.3897355e+08 | J15: =Лист4!F$10 -> -1.3601143e+08 | K15: =SUMIFS(data!$G:$G,data!$C:$C,$B$13,data!$D:$D,$B$14,data!$F:$F,K$4,data!$E:$E,$B15,data!$H:$H,ПФ2026!K$5) -> -1.5903949e+08 | L15: =Лист4!G$10 -> -82862751 | M15: =SUMIFS(data!$G:$G,data!$C:$C,$B$13,data!$D:$D,$B$14,data!$F:$F,M$4,data!$E:$E,$B15,data!$H:$H,ПФ2026!M$5) -> -1.6343569e+08 | N15: =Лист4!H$10 -> -1.8635845e+08 | O15: =SUMIFS(data!$G:$G,data!$C:$C,$B$13,data!$D:$D,$B$14,data!$F:$F,O$4,data!$E:$E,$B15,data!$H:$H,ПФ2026!O$5) -> -1.9813763e+08 | P15: =Лист4!I10 -> 0 | Q15: =SUMIFS(data!$G:$G,data!$C:$C,$B$13,data!$D:$D,$B$14,data!$F:$F,Q$4,data!$E:$E,$B15,data!$H:$H,ПФ2026!Q$5) -> -1.7099779e+08 | R15: =Лист4!J$10 -> 0 | S15: =SUMIFS(data!$G:$G,data!$C:$C,$B$13,data!$D:$D,$B$14,data!$F:$F,S$4,data!$E:$E,$B15,data!$H:$H,ПФ2026!S$5) -> -1.204398e+08 | T15: =Лист4!K$10 -> 0 | U15: =SUMIFS(data!$G:$G,data!$C:$C,$B$13,data!$D:$D,$B$14,data!$F:$F,U$4,data!$E:$E,$B15,data!$H:$H,ПФ2026!U$5) -> -81391996 | V15: =Лист4!L$10 -> 0 | W15: =SUMIFS(data!$G:$G,data!$C:$C,$B$13,data!$D:$D,$B$14,data!$F:$F,W$4,data!$E:$E,$B15,data!$H:$H,ПФ2026!W$5) -> -71544691 | X15: =Лист4!M10 -> 0 | Y15: =SUMIFS(data!$G:$G,data!$C:$C,$B$13,data!$D:$D,$B$14,data!$F:$F,Y$4,data!$E:$E,$B15,data!$H:$H,ПФ2026!Y$5) -> -68061325 | Z15: =Лист4!N$10 -> 0 | AA15: =SUM(C15,E15,G15,I15,K15,M15,O75,O15,Q15,S15,Y15,W15,U15) -> -1.4102478e+09 | AB15: =D15+F15+H15+J15+L15+N15+P15+R15+T15+V15+X15+Z15 -> -5.023857e+08 | AC15: =IFERROR(AB15/AA15,0) -> 0.35623931
B16: Расходы по себестоимости ФЗП | C16: =SUM(C17) -> -8435387.7 | D16: =SUM(D17) -> -72257022 | E16: =SUM(E17) -> -8863141.7 | F16: =SUM(F17) -> -75683712 | G16: =SUM(G17) -> -11643726 | H16: =SUM(H17) -> -99102968 | I16: =SUM(I17) -> -15237070 | J16: =SUM(J17) -> -19217075 | ... Z16: =SUM(Z17) -> 0 | AA16: =SUM(C16,E16,G16,I16,K16,M16,O76,O16,Q16,S16,Y16,W16,U16) -> -1.5795897e+08 | AB16: =D16+F16+H16+J16+L16+N16+P16+R16+T16+V16+X16+Z16 -> -3.7850048e+08 | AC16: =IFERROR(AB16/AA16,0) -> 2.3961949
B17: Расходы по себестоимости ФЗП | C17: =SUMIFS(data!$G:$G,data!$C:$C,$B$13,data!$D:$D,$B$16,data!$F:$F,C$4,data!$E:$E,$B17,data!$H:$H,ПФ2026!C$5) -> -8435387.7 | D17: =Лист4!$C$6*ПФ2026!$C$1 -> -72257022 | E17: =SUMIFS(data!$G:$G,data!$C:$C,$B$13,data!$D:$D,$B$16,data!$F:$F,E$4,data!$E:$E,$B17,data!$H:$H,ПФ2026!E$5) -> -8863141.7 | F17: =Лист4!$D$6*ПФ2026!$C$1 -> -75683712 | G17: =SUMIFS(data!$G:$G,data!$C:$C,$B$13,data!$D:$D,$B$16,data!$F:$F,G$4,data!$E:$E,$B17,data!$H:$H,ПФ2026!G$5) -> -11643726 | H17: =Лист4!$E$6*ПФ2026!$C$1 -> -99102968 | I17: =SUMIFS(data!$G:$G,data!$C:$C,$B$13,data!$D:$D,$B$16,data!$F:$F,I$4,data!$E:$E,$B17,data!$H:$H,ПФ2026!I$5) -> -15237070 | J17: =Лист4!$F$6*ПФ2026!$C$1 -> -19217075 | K17: =SUMIFS(data!$G:$G,data!$C:$C,$B$13,data!$D:$D,$B$16,data!$F:$F,K$4,data!$E:$E,$B17,data!$H:$H,ПФ2026!K$5) -> -17101214 | L17: =Лист4!$G$6*ПФ2026!$C$1 -> -87639122 | M17: =SUMIFS(data!$G:$G,data!$C:$C,$B$13,data!$D:$D,$B$16,data!$F:$F,M$4,data!$E:$E,$B17,data!$H:$H,ПФ2026!M$5) -> -17299414 | N17: =Лист4!$H$6*ПФ2026!$C$1 -> -24600578 | O17: =SUMIFS(data!$G:$G,data!$C:$C,$B$13,data!$D:$D,$B$16,data!$F:$F,O$4,data!$E:$E,$B17,data!$H:$H,ПФ2026!O$5) -> -19625381 | P17: =Лист4!I6*ПФ2026!C1 -> 0 | Q17: =SUMIFS(data!$G:$G,data!$C:$C,$B$13,data!$D:$D,$B$16,data!$F:$F,Q$4,data!$E:$E,$B17,data!$H:$H,ПФ2026!Q$5) -> -17512321 | R17: =Лист4!J6*ПФ2026!C1 -> 0 | S17: =SUMIFS(data!$G:$G,data!$C:$C,$B$13,data!$D:$D,$B$16,data!$F:$F,S$4,data!$E:$E,$B17,data!$H:$H,ПФ2026!S$5) -> -13455184 | T17: =Лист4!K6*ПФ2026!C1 -> 0 | U17: =SUMIFS(data!$G:$G,data!$C:$C,$B$13,data!$D:$D,$B$16,data!$F:$F,U$4,data!$E:$E,$B17,data!$H:$H,ПФ2026!U$5) -> -10852136 | V17: =Лист4!L6*ПФ2026!C1 -> 0 | W17: =SUMIFS(data!$G:$G,data!$C:$C,$B$13,data!$D:$D,$B$16,data!$F:$F,W$4,data!$E:$E,$B17,data!$H:$H,ПФ2026!W$5) -> -9084947.6 | X17: =Лист4!M6*ПФ2026!$C$1 -> 0 | Y17: =SUMIFS(data!$G:$G,data!$C:$C,$B$13,data!$D:$D,$B$16,data!$F:$F,Y$4,data!$E:$E,$B17,data!$H:$H,ПФ2026!Y$5) -> -8849046.9 | Z17: =Лист4!N6*ПФ2026!$C$1 -> 0 | AA17: =SUM(C17,E17,G17,I17,K17,M17,O77,O17,Q17,S17,Y17,W17,U17) -> -1.5795897e+08 | AB17: =D17+F17+H17+J17+L17+N17+P17+R17+T17+V17+X17+Z17 -> -3.7850048e+08 | AC17: =IFERROR(AB17/AA17,0) -> 2.3961949
B18: Расходы по амортизации | C18: =SUM(C19:C23) -> -12461257 | D18: =SUM(D19:D23) -> -15012436 | E18: =SUM(E19:E23) -> -12378828 | F18: =SUM(F19:F23) -> -14735429 | G18: =SUM(G19:G23) -> -12651670 | H18: =SUM(H19:H23) -> -14783266 | I18: =SUM(I19:I23) -> -12566183 | J18: =SUM(J19:J23) -> -14812631 | ... Z18: =SUM(Z19:Z23) -> 0 | AA18: =SUM(C18,E18,G18,I18,K18,M18,O78,O18,Q18,S18,Y18,W18,U18) -> -1.8242903e+08 | AB18: =D18+F18+H18+J18+L18+N18+P18+R18+T18+V18+X18+Z18 -> -88001062 | AC18: =IFERROR(AB18/AA18,0) -> 0.48238518
B19: 2130/Амортизация - здания | C19: =SUMIFS(data!$G:$G,data!$C:$C,$B$13,data!$D:$D,$B$18,data!$F:$F,C$4,data!$E:$E,$B19,data!$H:$H,ПФ2026!C$5) -> -208621.29 | D19: =SUMIFS(data!$G:$G,data!$C:$C,$B$13,data!$D:$D,$B$18,data!$F:$F,C$4,data!$E:$E,$B19,data!$H:$H,ПФ2026!D$5) -> -705549.66 | E19: =SUMIFS(data!$G:$G,data!$C:$C,$B$13,data!$D:$D,$B$18,data!$F:$F,E$4,data!$E:$E,$B19,data!$H:$H,ПФ2026!E$5) -> -208621.29 | F19: =SUMIFS(data!$G:$G,data!$C:$C,$B$13,data!$D:$D,$B$18,data!$F:$F,E$4,data!$E:$E,$B19,data!$H:$H,ПФ2026!F$5) -> -705549.66 | G19: =SUMIFS(data!$G:$G,data!$C:$C,$B$13,data!$D:$D,$B$18,data!$F:$F,G$4,data!$E:$E,$B19,data!$H:$H,ПФ2026!G$5) -> -209785.24 | H19: =SUMIFS(data!$G:$G,data!$C:$C,$B$13,data!$D:$D,$B$18,data!$F:$F,G$4,data!$E:$E,$B19,data!$H:$H,ПФ2026!H$5) -> -729713.45 | I19: =SUMIFS(data!$G:$G,data!$C:$C,$B$13,data!$D:$D,$B$18,data!$F:$F,I$4,data!$E:$E,$B19,data!$H:$H,ПФ2026!I$5) -> -211606.22 | J19: =SUMIFS(data!$G:$G,data!$C:$C,$B$13,data!$D:$D,$B$18,data!$F:$F,I$4,data!$E:$E,$B19,data!$H:$H,ПФ2026!J$5) -> -738480.85 | K19: =SUMIFS(data!$G:$G,data!$C:$C,$B$13,data!$D:$D,$B$18,data!$F:$F,K$4,data!$E:$E,$B19,data!$H:$H,ПФ2026!K$5) -> -214246.72 | L19: =SUMIFS(data!$G:$G,data!$C:$C,$B$13,data!$D:$D,$B$18,data!$F:$F,K$4,data!$E:$E,$B19,data!$H:$H,ПФ2026!L$5) -> -756590.19 | M19: =SUMIFS(data!$G:$G,data!$C:$C,$B$13,data!$D:$D,$B$18,data!$F:$F,M$4,data!$E:$E,$B19,data!$H:$H,ПФ2026!M$5) -> -214246.72 | N19: =SUMIFS(data!$G:$G,data!$C:$C,$B$13,data!$D:$D,$B$18,data!$F:$F,M$4,data!$E:$E,$B19,data!$H:$H,ПФ2026!N$5) -> -753239.62 | O19: =SUMIFS(data!$G:$G,data!$C:$C,$B$13,data!$D:$D,$B$18,data!$F:$F,O$4,data!$E:$E,$B19,data!$H:$H,ПФ2026!O$5) -> -249829.13 | P19: =SUMIFS(data!$G:$G,data!$C:$C,$B$13,data!$D:$D,$B$18,data!$F:$F,O$4,data!$E:$E,$B19,data!$H:$H,ПФ2026!P$5) -> 0 | Q19: =SUMIFS(data!$G:$G,data!$C:$C,$B$13,data!$D:$D,$B$18,data!$F:$F,Q$4,data!$E:$E,$B19,data!$H:$H,ПФ2026!Q$5) -> -257035.1 | R19: =SUMIFS(data!$G:$G,data!$C:$C,$B$13,data!$D:$D,$B$18,data!$F:$F,Q$4,data!$E:$E,$B19,data!$H:$H,ПФ2026!R$5) -> 0 | S19: =SUMIFS(data!$G:$G,data!$C:$C,$B$13,data!$D:$D,$B$18,data!$F:$F,S$4,data!$E:$E,$B19,data!$H:$H,ПФ2026!S$5) -> -503329.73 | T19: =SUMIFS(data!$G:$G,data!$C:$C,$B$13,data!$D:$D,$B$18,data!$F:$F,S$4,data!$E:$E,$B19,data!$H:$H,ПФ2026!T$5) -> 0 | U19: =SUMIFS(data!$G:$G,data!$C:$C,$B$13,data!$D:$D,$B$18,data!$F:$F,U$4,data!$E:$E,$B19,data!$H:$H,ПФ2026!U$5) -> -776193.55 | V19: =SUMIFS(data!$G:$G,data!$C:$C,$B$13,data!$D:$D,$B$18,data!$F:$F,U$4,data!$E:$E,$B19,data!$H:$H,ПФ2026!V$5) -> 0 | W19: =SUMIFS(data!$G:$G,data!$C:$C,$B$13,data!$D:$D,$B$18,data!$F:$F,W$4,data!$E:$E,$B19,data!$H:$H,ПФ2026!W$5) -> -730718.12 | X19: =SUMIFS(data!$G:$G,data!$C:$C,$B$13,data!$D:$D,$B$18,data!$F:$F,W$4,data!$E:$E,$B19,data!$H:$H,ПФ2026!X$5) -> 0 | Y19: =SUMIFS(data!$G:$G,data!$C:$C,$B$13,data!$D:$D,$B$18,data!$F:$F,Y$4,data!$E:$E,$B19,data!$H:$H,ПФ2026!Y$5) -> -739809.42 | Z19: =SUMIFS(data!$G:$G,data!$C:$C,$B$13,data!$D:$D,$B$18,data!$F:$F,Y$4,data!$E:$E,$B19,data!$H:$H,ПФ2026!Z$5) -> 0 | AA19: =SUM(C19,E19,G19,I19,K19,M19,O79,O19,Q19,S19,Y19,W19,U19) -> -5304442.5 | AB19: =D19+F19+H19+J19+L19+N19+P19+R19+T19+V19+X19+Z19 -> -4389123.4 | AC19: =IFERROR(AB19/AA19,0) -> 0.82744292
B20: 2140/Амортизация - оборудование | C20: =SUMIFS(data!$G:$G,data!$C:$C,$B$13,data!$D:$D,$B$18,data!$F:$F,C$4,data!$E:$E,$B20,data!$H:$H,ПФ2026!C$5) -> -12193821 | D20: =SUMIFS(data!$G:$G,data!$C:$C,$B$13,data!$D:$D,$B$18,data!$F:$F,C$4,data!$E:$E,$B20,data!$H:$H,ПФ2026!D$5) -> -14306887 | E20: =SUMIFS(data!$G:$G,data!$C:$C,$B$13,data!$D:$D,$B$18,data!$F:$F,E$4,data!$E:$E,$B20,data!$H:$H,ПФ2026!E$5) -> -12108590 | F20: =SUMIFS(data!$G:$G,data!$C:$C,$B$13,data!$D:$D,$B$18,data!$F:$F,E$4,data!$E:$E,$B20,data!$H:$H,ПФ2026!F$5) -> -14029880 | G20: =SUMIFS(data!$G:$G,data!$C:$C,$B$13,data!$D:$D,$B$18,data!$F:$F,G$4,data!$E:$E,$B20,data!$H:$H,ПФ2026!G$5) -> -12373983 | H20: =SUMIFS(data!$G:$G,data!$C:$C,$B$13,data!$D:$D,$B$18,data!$F:$F,G$4,data!$E:$E,$B20,data!$H:$H,ПФ2026!H$5) -> -14053552 | I20: =SUMIFS(data!$G:$G,data!$C:$C,$B$13,data!$D:$D,$B$18,data!$F:$F,I$4,data!$E:$E,$B20,data!$H:$H,ПФ2026!I$5) -> -12285981 | J20: =SUMIFS(data!$G:$G,data!$C:$C,$B$13,data!$D:$D,$B$18,data!$F:$F,I$4,data!$E:$E,$B20,data!$H:$H,ПФ2026!J$5) -> -14074150 | K20: =SUMIFS(data!$G:$G,data!$C:$C,$B$13,data!$D:$D,$B$18,data!$F:$F,K$4,data!$E:$E,$B20,data!$H:$H,ПФ2026!K$5) -> -11662422 | L20: =SUMIFS(data!$G:$G,data!$C:$C,$B$13,data!$D:$D,$B$18,data!$F:$F,K$4,data!$E:$E,$B20,data!$H:$H,ПФ2026!L$5) -> -13817271 | M20: =SUMIFS(data!$G:$G,data!$C:$C,$B$13,data!$D:$D,$B$18,data!$F:$F,M$4,data!$E:$E,$B20,data!$H:$H,ПФ2026!M$5) -> -12001174 | N20: =SUMIFS(data!$G:$G,data!$C:$C,$B$13,data!$D:$D,$B$18,data!$F:$F,M$4,data!$E:$E,$B20,data!$H:$H,ПФ2026!N$5) -> -13330199 | O20: =SUMIFS(data!$G:$G,data!$C:$C,$B$13,data!$D:$D,$B$18,data!$F:$F,O$4,data!$E:$E,$B20,data!$H:$H,ПФ2026!O$5) -> -12131877 | P20: =SUMIFS(data!$G:$G,data!$C:$C,$B$13,data!$D:$D,$B$18,data!$F:$F,O$4,data!$E:$E,$B20,data!$H:$H,ПФ2026!P$5) -> 0 | Q20: =SUMIFS(data!$G:$G,data!$C:$C,$B$13,data!$D:$D,$B$18,data!$F:$F,Q$4,data!$E:$E,$B20,data!$H:$H,ПФ2026!Q$5) -> -12237341 | R20: =SUMIFS(data!$G:$G,data!$C:$C,$B$13,data!$D:$D,$B$18,data!$F:$F,Q$4,data!$E:$E,$B20,data!$H:$H,ПФ2026!R$5) -> 0 | S20: =SUMIFS(data!$G:$G,data!$C:$C,$B$13,data!$D:$D,$B$18,data!$F:$F,S$4,data!$E:$E,$B20,data!$H:$H,ПФ2026!S$5) -> -24102184 | T20: =SUMIFS(data!$G:$G,data!$C:$C,$B$13,data!$D:$D,$B$18,data!$F:$F,S$4,data!$E:$E,$B20,data!$H:$H,ПФ2026!T$5) -> 0 | U20: =SUMIFS(data!$G:$G,data!$C:$C,$B$13,data!$D:$D,$B$18,data!$F:$F,U$4,data!$E:$E,$B20,data!$H:$H,ПФ2026!U$5) -> -18274474 | V20: =SUMIFS(data!$G:$G,data!$C:$C,$B$13,data!$D:$D,$B$18,data!$F:$F,U$4,data!$E:$E,$B20,data!$H:$H,ПФ2026!V$5) -> 0 | W20: =SUMIFS(data!$G:$G,data!$C:$C,$B$13,data!$D:$D,$B$18,data!$F:$F,W$4,data!$E:$E,$B20,data!$H:$H,ПФ2026!W$5) -> -18302843 | X20: =SUMIFS(data!$G:$G,data!$C:$C,$B$13,data!$D:$D,$B$18,data!$F:$F,W$4,data!$E:$E,$B20,data!$H:$H,ПФ2026!X$5) -> 0 | Y20: =SUMIFS(data!$G:$G,data!$C:$C,$B$13,data!$D:$D,$B$18,data!$F:$F,Y$4,data!$E:$E,$B20,data!$H:$H,ПФ2026!Y$5) -> -17553918 | Z20: =SUMIFS(data!$G:$G,data!$C:$C,$B$13,data!$D:$D,$B$18,data!$F:$F,Y$4,data!$E:$E,$B20,data!$H:$H,ПФ2026!Z$5) -> 0 | AA20: =SUM(C20,E20,G20,I20,K20,M20,O80,O20,Q20,S20,Y20,W20,U20) -> -1.7523361e+08 | AB20: =D20+F20+H20+J20+L20+N20+P20+R20+T20+V20+X20+Z20 -> -83611938 | AC20: =IFERROR(AB20/AA20,0) -> 0.47714557
B21: 2150/Амортизация - конторское оборудование | C21: =SUMIFS(data!$G:$G,data!$C:$C,$B$13,data!$D:$D,$B$18,data!$F:$F,C$4,data!$E:$E,$B21,data!$H:$H,ПФ2026!C$5) -> -18713.117 | D21: =SUMIFS(data!$G:$G,data!$C:$C,$B$13,data!$D:$D,$B$18,data!$F:$F,C$4,data!$E:$E,$B21,data!$H:$H,ПФ2026!D$5) -> 0 | E21: =SUMIFS(data!$G:$G,data!$C:$C,$B$13,data!$D:$D,$B$18,data!$F:$F,E$4,data!$E:$E,$B21,data!$H:$H,ПФ2026!E$5) -> -20553.907 | F21: =SUMIFS(data!$G:$G,data!$C:$C,$B$13,data!$D:$D,$B$18,data!$F:$F,E$4,data!$E:$E,$B21,data!$H:$H,ПФ2026!F$5) -> 0 | G21: =SUMIFS(data!$G:$G,data!$C:$C,$B$13,data!$D:$D,$B$18,data!$F:$F,G$4,data!$E:$E,$B21,data!$H:$H,ПФ2026!G$5) -> -23668.073 | H21: =SUMIFS(data!$G:$G,data!$C:$C,$B$13,data!$D:$D,$B$18,data!$F:$F,G$4,data!$E:$E,$B21,data!$H:$H,ПФ2026!H$5) -> 0 | I21: =SUMIFS(data!$G:$G,data!$C:$C,$B$13,data!$D:$D,$B$18,data!$F:$F,I$4,data!$E:$E,$B21,data!$H:$H,ПФ2026!I$5) -> -24362.896 | J21: =SUMIFS(data!$G:$G,data!$C:$C,$B$13,data!$D:$D,$B$18,data!$F:$F,I$4,data!$E:$E,$B21,data!$H:$H,ПФ2026!J$5) -> 0 | K21: =SUMIFS(data!$G:$G,data!$C:$C,$B$13,data!$D:$D,$B$18,data!$F:$F,K$4,data!$E:$E,$B21,data!$H:$H,ПФ2026!K$5) -> -22522.106 | L21: =SUMIFS(data!$G:$G,data!$C:$C,$B$13,data!$D:$D,$B$18,data!$F:$F,K$4,data!$E:$E,$B21,data!$H:$H,ПФ2026!L$5) -> 0 | M21: =SUMIFS(data!$G:$G,data!$C:$C,$B$13,data!$D:$D,$B$18,data!$F:$F,M$4,data!$E:$E,$B21,data!$H:$H,ПФ2026!M$5) -> -24362.896 | N21: =SUMIFS(data!$G:$G,data!$C:$C,$B$13,data!$D:$D,$B$18,data!$F:$F,M$4,data!$E:$E,$B21,data!$H:$H,ПФ2026!N$5) -> 0 | O21: =SUMIFS(data!$G:$G,data!$C:$C,$B$13,data!$D:$D,$B$18,data!$F:$F,O$4,data!$E:$E,$B21,data!$H:$H,ПФ2026!O$5) -> -22771.154 | P21: =SUMIFS(data!$G:$G,data!$C:$C,$B$13,data!$D:$D,$B$18,data!$F:$F,O$4,data!$E:$E,$B21,data!$H:$H,ПФ2026!P$5) -> 0 | Q21: =SUMIFS(data!$G:$G,data!$C:$C,$B$13,data!$D:$D,$B$18,data!$F:$F,Q$4,data!$E:$E,$B21,data!$H:$H,ПФ2026!Q$5) -> -21191.321 | R21: =SUMIFS(data!$G:$G,data!$C:$C,$B$13,data!$D:$D,$B$18,data!$F:$F,Q$4,data!$E:$E,$B21,data!$H:$H,ПФ2026!R$5) -> 0 | S21: =SUMIFS(data!$G:$G,data!$C:$C,$B$13,data!$D:$D,$B$18,data!$F:$F,S$4,data!$E:$E,$B21,data!$H:$H,ПФ2026!S$5) -> -39070.931 | T21: =SUMIFS(data!$G:$G,data!$C:$C,$B$13,data!$D:$D,$B$18,data!$F:$F,S$4,data!$E:$E,$B21,data!$H:$H,ПФ2026!T$5) -> 0 | U21: =SUMIFS(data!$G:$G,data!$C:$C,$B$13,data!$D:$D,$B$18,data!$F:$F,U$4,data!$E:$E,$B21,data!$H:$H,ПФ2026!U$5) -> -20154.678 | V21: =SUMIFS(data!$G:$G,data!$C:$C,$B$13,data!$D:$D,$B$18,data!$F:$F,U$4,data!$E:$E,$B21,data!$H:$H,ПФ2026!V$5) -> 0 | W21: =SUMIFS(data!$G:$G,data!$C:$C,$B$13,data!$D:$D,$B$18,data!$F:$F,W$4,data!$E:$E,$B21,data!$H:$H,ПФ2026!W$5) -> -19450.436 | X21: =SUMIFS(data!$G:$G,data!$C:$C,$B$13,data!$D:$D,$B$18,data!$F:$F,W$4,data!$E:$E,$B21,data!$H:$H,ПФ2026!X$5) -> 0 | Y21: =SUMIFS(data!$G:$G,data!$C:$C,$B$13,data!$D:$D,$B$18,data!$F:$F,Y$4,data!$E:$E,$B21,data!$H:$H,ПФ2026!Y$5) -> -15836.782 | Z21: =SUMIFS(data!$G:$G,data!$C:$C,$B$13,data!$D:$D,$B$18,data!$F:$F,Y$4,data!$E:$E,$B21,data!$H:$H,ПФ2026!Z$5) -> 0 | AA21: =SUM(C21,E21,G21,I21,K21,M21,O81,O21,Q21,S21,Y21,W21,U21) -> -272658.3 | AB21: =D21+F21+H21+J21+L21+N21+P21+R21+T21+V21+X21+Z21 -> 0 | AC21: =IFERROR(AB21/AA21,0) -> 0
B22: 2160/Амортизация - мебель и прочие принадлежности | C22: =SUMIFS(data!$G:$G,data!$C:$C,$B$13,data!$D:$D,$B$18,data!$F:$F,C$4,data!$E:$E,$B22,data!$H:$H,ПФ2026!C$5) -> -40101.369 | D22: =SUMIFS(data!$G:$G,data!$C:$C,$B$13,data!$D:$D,$B$18,data!$F:$F,C$4,data!$E:$E,$B22,data!$H:$H,ПФ2026!D$5) -> 0 | E22: =SUMIFS(data!$G:$G,data!$C:$C,$B$13,data!$D:$D,$B$18,data!$F:$F,E$4,data!$E:$E,$B22,data!$H:$H,ПФ2026!E$5) -> -41062.499 | F22: =SUMIFS(data!$G:$G,data!$C:$C,$B$13,data!$D:$D,$B$18,data!$F:$F,E$4,data!$E:$E,$B22,data!$H:$H,ПФ2026!F$5) -> 0 | G22: =SUMIFS(data!$G:$G,data!$C:$C,$B$13,data!$D:$D,$B$18,data!$F:$F,G$4,data!$E:$E,$B22,data!$H:$H,ПФ2026!G$5) -> -44233.643 | H22: =SUMIFS(data!$G:$G,data!$C:$C,$B$13,data!$D:$D,$B$18,data!$F:$F,G$4,data!$E:$E,$B22,data!$H:$H,ПФ2026!H$5) -> 0 | I22: =SUMIFS(data!$G:$G,data!$C:$C,$B$13,data!$D:$D,$B$18,data!$F:$F,I$4,data!$E:$E,$B22,data!$H:$H,ПФ2026!I$5) -> -44233.643 | J22: =SUMIFS(data!$G:$G,data!$C:$C,$B$13,data!$D:$D,$B$18,data!$F:$F,I$4,data!$E:$E,$B22,data!$H:$H,ПФ2026!J$5) -> 0 | K22: =SUMIFS(data!$G:$G,data!$C:$C,$B$13,data!$D:$D,$B$18,data!$F:$F,K$4,data!$E:$E,$B22,data!$H:$H,ПФ2026!K$5) -> -45586.972 | L22: =SUMIFS(data!$G:$G,data!$C:$C,$B$13,data!$D:$D,$B$18,data!$F:$F,K$4,data!$E:$E,$B22,data!$H:$H,ПФ2026!L$5) -> 0 | M22: =SUMIFS(data!$G:$G,data!$C:$C,$B$13,data!$D:$D,$B$18,data!$F:$F,M$4,data!$E:$E,$B22,data!$H:$H,ПФ2026!M$5) -> -44543.602 | N22: =SUMIFS(data!$G:$G,data!$C:$C,$B$13,data!$D:$D,$B$18,data!$F:$F,M$4,data!$E:$E,$B22,data!$H:$H,ПФ2026!N$5) -> 0 | O22: =SUMIFS(data!$G:$G,data!$C:$C,$B$13,data!$D:$D,$B$18,data!$F:$F,O$4,data!$E:$E,$B22,data!$H:$H,ПФ2026!O$5) -> -39113.062 | P22: =SUMIFS(data!$G:$G,data!$C:$C,$B$13,data!$D:$D,$B$18,data!$F:$F,O$4,data!$E:$E,$B22,data!$H:$H,ПФ2026!P$5) -> 0 | Q22: =SUMIFS(data!$G:$G,data!$C:$C,$B$13,data!$D:$D,$B$18,data!$F:$F,Q$4,data!$E:$E,$B22,data!$H:$H,ПФ2026!Q$5) -> -32107.988 | R22: =SUMIFS(data!$G:$G,data!$C:$C,$B$13,data!$D:$D,$B$18,data!$F:$F,Q$4,data!$E:$E,$B22,data!$H:$H,ПФ2026!R$5) -> 0 | S22: =SUMIFS(data!$G:$G,data!$C:$C,$B$13,data!$D:$D,$B$18,data!$F:$F,S$4,data!$E:$E,$B22,data!$H:$H,ПФ2026!S$5) -> -80001.396 | T22: =SUMIFS(data!$G:$G,data!$C:$C,$B$13,data!$D:$D,$B$18,data!$F:$F,S$4,data!$E:$E,$B22,data!$H:$H,ПФ2026!T$5) -> 0 | U22: =SUMIFS(data!$G:$G,data!$C:$C,$B$13,data!$D:$D,$B$18,data!$F:$F,U$4,data!$E:$E,$B22,data!$H:$H,ПФ2026!U$5) -> -30347.269 | V22: =SUMIFS(data!$G:$G,data!$C:$C,$B$13,data!$D:$D,$B$18,data!$F:$F,U$4,data!$E:$E,$B22,data!$H:$H,ПФ2026!V$5) -> 0 | W22: =SUMIFS(data!$G:$G,data!$C:$C,$B$13,data!$D:$D,$B$18,data!$F:$F,W$4,data!$E:$E,$B22,data!$H:$H,ПФ2026!W$5) -> -30346.324 | X22: =SUMIFS(data!$G:$G,data!$C:$C,$B$13,data!$D:$D,$B$18,data!$F:$F,W$4,data!$E:$E,$B22,data!$H:$H,ПФ2026!X$5) -> 0 | Y22: =SUMIFS(data!$G:$G,data!$C:$C,$B$13,data!$D:$D,$B$18,data!$F:$F,Y$4,data!$E:$E,$B22,data!$H:$H,ПФ2026!Y$5) -> -24181.773 | Z22: =SUMIFS(data!$G:$G,data!$C:$C,$B$13,data!$D:$D,$B$18,data!$F:$F,Y$4,data!$E:$E,$B22,data!$H:$H,ПФ2026!Z$5) -> 0 | AA22: =SUM(C22,E22,G22,I22,K22,M22,O82,O22,Q22,S22,Y22,W22,U22) -> -495859.54 | AB22: =D22+F22+H22+J22+L22+N22+P22+R22+T22+V22+X22+Z22 -> 0 | AC22: =IFERROR(AB22/AA22,0) -> 0
B23: 2170/Амортизация - транспортные средства | C23: =SUMIFS(data!$G:$G,data!$C:$C,$B$13,data!$D:$D,$B$18,data!$F:$F,C$4,data!$E:$E,$B23,data!$H:$H,ПФ2026!C$5) -> 0 | D23: =SUMIFS(data!$G:$G,data!$C:$C,$B$13,data!$D:$D,$B$18,data!$F:$F,C$4,data!$E:$E,$B23,data!$H:$H,ПФ2026!D$5) -> 0 | E23: =SUMIFS(data!$G:$G,data!$C:$C,$B$13,data!$D:$D,$B$18,data!$F:$F,E$4,data!$E:$E,$B23,data!$H:$H,ПФ2026!E$5) -> 0 | F23: =SUMIFS(data!$G:$G,data!$C:$C,$B$13,data!$D:$D,$B$18,data!$F:$F,E$4,data!$E:$E,$B23,data!$H:$H,ПФ2026!F$5) -> 0 | G23: =SUMIFS(data!$G:$G,data!$C:$C,$B$13,data!$D:$D,$B$18,data!$F:$F,G$4,data!$E:$E,$B23,data!$H:$H,ПФ2026!G$5) -> 0 | H23: =SUMIFS(data!$G:$G,data!$C:$C,$B$13,data!$D:$D,$B$18,data!$F:$F,G$4,data!$E:$E,$B23,data!$H:$H,ПФ2026!H$5) -> 0 | I23: =SUMIFS(data!$G:$G,data!$C:$C,$B$13,data!$D:$D,$B$18,data!$F:$F,I$4,data!$E:$E,$B23,data!$H:$H,ПФ2026!I$5) -> 0 | J23: =SUMIFS(data!$G:$G,data!$C:$C,$B$13,data!$D:$D,$B$18,data!$F:$F,I$4,data!$E:$E,$B23,data!$H:$H,ПФ2026!J$5) -> 0 | K23: =SUMIFS(data!$G:$G,data!$C:$C,$B$13,data!$D:$D,$B$18,data!$F:$F,K$4,data!$E:$E,$B23,data!$H:$H,ПФ2026!K$5) -> 0 | L23: =SUMIFS(data!$G:$G,data!$C:$C,$B$13,data!$D:$D,$B$18,data!$F:$F,K$4,data!$E:$E,$B23,data!$H:$H,ПФ2026!L$5) -> 0 | M23: =SUMIFS(data!$G:$G,data!$C:$C,$B$13,data!$D:$D,$B$18,data!$F:$F,M$4,data!$E:$E,$B23,data!$H:$H,ПФ2026!M$5) -> 0 | N23: =SUMIFS(data!$G:$G,data!$C:$C,$B$13,data!$D:$D,$B$18,data!$F:$F,M$4,data!$E:$E,$B23,data!$H:$H,ПФ2026!N$5) -> 0 | O23: =SUMIFS(data!$G:$G,data!$C:$C,$B$13,data!$D:$D,$B$18,data!$F:$F,O$4,data!$E:$E,$B23,data!$H:$H,ПФ2026!O$5) -> 0 | P23: =SUMIFS(data!$G:$G,data!$C:$C,$B$13,data!$D:$D,$B$18,data!$F:$F,O$4,data!$E:$E,$B23,data!$H:$H,ПФ2026!P$5) -> 0 | Q23: =SUMIFS(data!$G:$G,data!$C:$C,$B$13,data!$D:$D,$B$18,data!$F:$F,Q$4,data!$E:$E,$B23,data!$H:$H,ПФ2026!Q$5) -> 0 | R23: =SUMIFS(data!$G:$G,data!$C:$C,$B$13,data!$D:$D,$B$18,data!$F:$F,Q$4,data!$E:$E,$B23,data!$H:$H,ПФ2026!R$5) -> 0 | S23: =SUMIFS(data!$G:$G,data!$C:$C,$B$13,data!$D:$D,$B$18,data!$F:$F,S$4,data!$E:$E,$B23,data!$H:$H,ПФ2026!S$5) -> 0 | T23: =SUMIFS(data!$G:$G,data!$C:$C,$B$13,data!$D:$D,$B$18,data!$F:$F,S$4,data!$E:$E,$B23,data!$H:$H,ПФ2026!T$5) -> 0 | U23: =SUMIFS(data!$G:$G,data!$C:$C,$B$13,data!$D:$D,$B$18,data!$F:$F,U$4,data!$E:$E,$B23,data!$H:$H,ПФ2026!U$5) -> 0 | V23: =SUMIFS(data!$G:$G,data!$C:$C,$B$13,data!$D:$D,$B$18,data!$F:$F,U$4,data!$E:$E,$B23,data!$H:$H,ПФ2026!V$5) -> 0 | W23: =SUMIFS(data!$G:$G,data!$C:$C,$B$13,data!$D:$D,$B$18,data!$F:$F,W$4,data!$E:$E,$B23,data!$H:$H,ПФ2026!W$5) -> 0 | X23: =SUMIFS(data!$G:$G,data!$C:$C,$B$13,data!$D:$D,$B$18,data!$F:$F,W$4,data!$E:$E,$B23,data!$H:$H,ПФ2026!X$5) -> 0 | Y23: =SUMIFS(data!$G:$G,data!$C:$C,$B$13,data!$D:$D,$B$18,data!$F:$F,Y$4,data!$E:$E,$B23,data!$H:$H,ПФ2026!Y$5) -> 0 | Z23: =SUMIFS(data!$G:$G,data!$C:$C,$B$13,data!$D:$D,$B$18,data!$F:$F,Y$4,data!$E:$E,$B23,data!$H:$H,ПФ2026!Z$5) -> 0 | AA23: =SUM(C23,E23,G23,I23,K23,M23,O83,O23,Q23,S23,Y23,W23,U23) -> 0 | AB23: =D23+F23+H23+J23+L23+N23+P23+R23+T23+V23+X23+Z23 -> 0 | AC23: =IFERROR(AB23/AA23,0) -> 0
B24: Расходы по ком.услуга | C24: =SUM(C25:C27) -> -1640197.4 | D24: =SUM(D25:D27) -> -1903483.3 | E24: =SUM(E25:E27) -> -2344355.5 | F24: =SUM(F25:F27) -> -2050465.1 | G24: =SUM(G25:G27) -> -1529613.3 | H24: =SUM(H25:H27) -> -2078987.8 | I24: =SUM(I25:I27) -> -2213918 | J24: =SUM(J25:J27) -> -2521758.5 | ... Z24: =SUM(Z25:Z27) -> 0 | AA24: =SUM(C24,E24,G24,I24,K24,M24,O84,O24,Q24,S24,Y24,W24,U24) -> -34831591 | AB24: =D24+F24+H24+J24+L24+N24+P24+R24+T24+V24+X24+Z24 -> -15888135 | AC24: =IFERROR(AB24/AA24,0) -> 0.45614153
B25: Вода, стоки и канализация | C25: =SUMIFS(data!$G:$G,data!$C:$C,$B$13,data!$D:$D,$B$24,data!$F:$F,C$4,data!$E:$E,$B25,data!$H:$H,ПФ2026!C$5) -> 0 | D25: =SUMIFS(data!$G:$G,data!$C:$C,$B$13,data!$D:$D,$B$24,data!$F:$F,C$4,data!$E:$E,$B25,data!$H:$H,ПФ2026!D$5) -> 0 | E25: =SUMIFS(data!$G:$G,data!$C:$C,$B$13,data!$D:$D,$B$24,data!$F:$F,E$4,data!$E:$E,$B25,data!$H:$H,ПФ2026!E$5) -> 0 | F25: =SUMIFS(data!$G:$G,data!$C:$C,$B$13,data!$D:$D,$B$24,data!$F:$F,E$4,data!$E:$E,$B25,data!$H:$H,ПФ2026!F$5) -> 0 | G25: =SUMIFS(data!$G:$G,data!$C:$C,$B$13,data!$D:$D,$B$24,data!$F:$F,G$4,data!$E:$E,$B25,data!$H:$H,ПФ2026!G$5) -> 0 | H25: =SUMIFS(data!$G:$G,data!$C:$C,$B$13,data!$D:$D,$B$24,data!$F:$F,G$4,data!$E:$E,$B25,data!$H:$H,ПФ2026!H$5) -> -6005.45 | I25: =SUMIFS(data!$G:$G,data!$C:$C,$B$13,data!$D:$D,$B$24,data!$F:$F,I$4,data!$E:$E,$B25,data!$H:$H,ПФ2026!I$5) -> 0 | J25: =SUMIFS(data!$G:$G,data!$C:$C,$B$13,data!$D:$D,$B$24,data!$F:$F,I$4,data!$E:$E,$B25,data!$H:$H,ПФ2026!J$5) -> -45562.91 | K25: =SUMIFS(data!$G:$G,data!$C:$C,$B$13,data!$D:$D,$B$24,data!$F:$F,K$4,data!$E:$E,$B25,data!$H:$H,ПФ2026!K$5) -> 0 | L25: =SUMIFS(data!$G:$G,data!$C:$C,$B$13,data!$D:$D,$B$24,data!$F:$F,K$4,data!$E:$E,$B25,data!$H:$H,ПФ2026!L$5) -> -198962.45 | M25: =SUMIFS(data!$G:$G,data!$C:$C,$B$13,data!$D:$D,$B$24,data!$F:$F,M$4,data!$E:$E,$B25,data!$H:$H,ПФ2026!M$5) -> 0 | N25: =SUMIFS(data!$G:$G,data!$C:$C,$B$13,data!$D:$D,$B$24,data!$F:$F,M$4,data!$E:$E,$B25,data!$H:$H,ПФ2026!N$5) -> -193479.25 | O25: =SUMIFS(data!$G:$G,data!$C:$C,$B$13,data!$D:$D,$B$24,data!$F:$F,O$4,data!$E:$E,$B25,data!$H:$H,ПФ2026!O$5) -> 0 | P25: =SUMIFS(data!$G:$G,data!$C:$C,$B$13,data!$D:$D,$B$24,data!$F:$F,O$4,data!$E:$E,$B25,data!$H:$H,ПФ2026!P$5) -> 0 | Q25: =SUMIFS(data!$G:$G,data!$C:$C,$B$13,data!$D:$D,$B$24,data!$F:$F,Q$4,data!$E:$E,$B25,data!$H:$H,ПФ2026!Q$5) -> 0 | R25: =SUMIFS(data!$G:$G,data!$C:$C,$B$13,data!$D:$D,$B$24,data!$F:$F,Q$4,data!$E:$E,$B25,data!$H:$H,ПФ2026!R$5) -> 0 | S25: =SUMIFS(data!$G:$G,data!$C:$C,$B$13,data!$D:$D,$B$24,data!$F:$F,S$4,data!$E:$E,$B25,data!$H:$H,ПФ2026!S$5) -> 0 | T25: =SUMIFS(data!$G:$G,data!$C:$C,$B$13,data!$D:$D,$B$24,data!$F:$F,S$4,data!$E:$E,$B25,data!$H:$H,ПФ2026!T$5) -> 0 | U25: =SUMIFS(data!$G:$G,data!$C:$C,$B$13,data!$D:$D,$B$24,data!$F:$F,U$4,data!$E:$E,$B25,data!$H:$H,ПФ2026!U$5) -> 0 | V25: =SUMIFS(data!$G:$G,data!$C:$C,$B$13,data!$D:$D,$B$24,data!$F:$F,U$4,data!$E:$E,$B25,data!$H:$H,ПФ2026!V$5) -> 0 | W25: =SUMIFS(data!$G:$G,data!$C:$C,$B$13,data!$D:$D,$B$24,data!$F:$F,W$4,data!$E:$E,$B25,data!$H:$H,ПФ2026!W$5) -> 0 | X25: =SUMIFS(data!$G:$G,data!$C:$C,$B$13,data!$D:$D,$B$24,data!$F:$F,W$4,data!$E:$E,$B25,data!$H:$H,ПФ2026!X$5) -> 0 | Y25: =SUMIFS(data!$G:$G,data!$C:$C,$B$13,data!$D:$D,$B$24,data!$F:$F,Y$4,data!$E:$E,$B25,data!$H:$H,ПФ2026!Y$5) -> 0 | Z25: =SUMIFS(data!$G:$G,data!$C:$C,$B$13,data!$D:$D,$B$24,data!$F:$F,Y$4,data!$E:$E,$B25,data!$H:$H,ПФ2026!Z$5) -> 0 | AA25: =SUM(C25,E25,G25,I25,K25,M25,O85,O25,Q25,S25,Y25,W25,U25) -> -515000 | AB25: =D25+F25+H25+J25+L25+N25+P25+R25+T25+V25+X25+Z25 -> -444010.06 | AC25: =IFERROR(AB25/AA25,0) -> 0.86215546
B26: Природный газ | C26: =SUMIFS(data!$G:$G,data!$C:$C,$B$13,data!$D:$D,$B$24,data!$F:$F,C$4,data!$E:$E,$B26,data!$H:$H,ПФ2026!C$5) -> 8869.4441 | D26: =SUMIFS(data!$G:$G,data!$C:$C,$B$13,data!$D:$D,$B$24,data!$F:$F,C$4,data!$E:$E,$B26,data!$H:$H,ПФ2026!D$5) -> -40536.91 | E26: =SUMIFS(data!$G:$G,data!$C:$C,$B$13,data!$D:$D,$B$24,data!$F:$F,E$4,data!$E:$E,$B26,data!$H:$H,ПФ2026!E$5) -> -71501.308 | F26: =SUMIFS(data!$G:$G,data!$C:$C,$B$13,data!$D:$D,$B$24,data!$F:$F,E$4,data!$E:$E,$B26,data!$H:$H,ПФ2026!F$5) -> 0 | G26: =SUMIFS(data!$G:$G,data!$C:$C,$B$13,data!$D:$D,$B$24,data!$F:$F,G$4,data!$E:$E,$B26,data!$H:$H,ПФ2026!G$5) -> -58842.169 | H26: =SUMIFS(data!$G:$G,data!$C:$C,$B$13,data!$D:$D,$B$24,data!$F:$F,G$4,data!$E:$E,$B26,data!$H:$H,ПФ2026!H$5) -> -56712.54 | I26: =SUMIFS(data!$G:$G,data!$C:$C,$B$13,data!$D:$D,$B$24,data!$F:$F,I$4,data!$E:$E,$B26,data!$H:$H,ПФ2026!I$5) -> -97058.97 | J26: =SUMIFS(data!$G:$G,data!$C:$C,$B$13,data!$D:$D,$B$24,data!$F:$F,I$4,data!$E:$E,$B26,data!$H:$H,ПФ2026!J$5) -> -791.52 | K26: =SUMIFS(data!$G:$G,data!$C:$C,$B$13,data!$D:$D,$B$24,data!$F:$F,K$4,data!$E:$E,$B26,data!$H:$H,ПФ2026!K$5) -> -107360.64 | L26: =SUMIFS(data!$G:$G,data!$C:$C,$B$13,data!$D:$D,$B$24,data!$F:$F,K$4,data!$E:$E,$B26,data!$H:$H,ПФ2026!L$5) -> -300800.17 | M26: =SUMIFS(data!$G:$G,data!$C:$C,$B$13,data!$D:$D,$B$24,data!$F:$F,M$4,data!$E:$E,$B26,data!$H:$H,ПФ2026!M$5) -> -121121.4 | N26: =SUMIFS(data!$G:$G,data!$C:$C,$B$13,data!$D:$D,$B$24,data!$F:$F,M$4,data!$E:$E,$B26,data!$H:$H,ПФ2026!N$5) -> -144242.05 | O26: =SUMIFS(data!$G:$G,data!$C:$C,$B$13,data!$D:$D,$B$24,data!$F:$F,O$4,data!$E:$E,$B26,data!$H:$H,ПФ2026!O$5) -> -120654.42 | P26: =SUMIFS(data!$G:$G,data!$C:$C,$B$13,data!$D:$D,$B$24,data!$F:$F,O$4,data!$E:$E,$B26,data!$H:$H,ПФ2026!P$5) -> 0 | Q26: =SUMIFS(data!$G:$G,data!$C:$C,$B$13,data!$D:$D,$B$24,data!$F:$F,Q$4,data!$E:$E,$B26,data!$H:$H,ПФ2026!Q$5) -> -85538.91 | R26: =SUMIFS(data!$G:$G,data!$C:$C,$B$13,data!$D:$D,$B$24,data!$F:$F,Q$4,data!$E:$E,$B26,data!$H:$H,ПФ2026!R$5) -> 0 | S26: =SUMIFS(data!$G:$G,data!$C:$C,$B$13,data!$D:$D,$B$24,data!$F:$F,S$4,data!$E:$E,$B26,data!$H:$H,ПФ2026!S$5) -> -80237.826 | T26: =SUMIFS(data!$G:$G,data!$C:$C,$B$13,data!$D:$D,$B$24,data!$F:$F,S$4,data!$E:$E,$B26,data!$H:$H,ПФ2026!T$5) -> 0 | U26: =SUMIFS(data!$G:$G,data!$C:$C,$B$13,data!$D:$D,$B$24,data!$F:$F,U$4,data!$E:$E,$B26,data!$H:$H,ПФ2026!U$5) -> -68738.536 | V26: =SUMIFS(data!$G:$G,data!$C:$C,$B$13,data!$D:$D,$B$24,data!$F:$F,U$4,data!$E:$E,$B26,data!$H:$H,ПФ2026!V$5) -> 0 | W26: =SUMIFS(data!$G:$G,data!$C:$C,$B$13,data!$D:$D,$B$24,data!$F:$F,W$4,data!$E:$E,$B26,data!$H:$H,ПФ2026!W$5) -> -65741.236 | X26: =SUMIFS(data!$G:$G,data!$C:$C,$B$13,data!$D:$D,$B$24,data!$F:$F,W$4,data!$E:$E,$B26,data!$H:$H,ПФ2026!X$5) -> 0 | Y26: =SUMIFS(data!$G:$G,data!$C:$C,$B$13,data!$D:$D,$B$24,data!$F:$F,Y$4,data!$E:$E,$B26,data!$H:$H,ПФ2026!Y$5) -> -66013.494 | Z26: =SUMIFS(data!$G:$G,data!$C:$C,$B$13,data!$D:$D,$B$24,data!$F:$F,Y$4,data!$E:$E,$B26,data!$H:$H,ПФ2026!Z$5) -> 0 | AA26: =SUM(C26,E26,G26,I26,K26,M26,O86,O26,Q26,S26,Y26,W26,U26) -> -993939.47 | AB26: =D26+F26+H26+J26+L26+N26+P26+R26+T26+V26+X26+Z26 -> -543083.19 | AC26: =IFERROR(AB26/AA26,0) -> 0.54639463
B27: Электроэнергия | C27: =SUMIFS(data!$G:$G,data!$C:$C,$B$13,data!$D:$D,$B$24,data!$F:$F,C$4,data!$E:$E,$B27,data!$H:$H,ПФ2026!C$5) -> -1649066.8 | D27: =SUMIFS(data!$G:$G,data!$C:$C,$B$13,data!$D:$D,$B$24,data!$F:$F,C$4,data!$E:$E,$B27,data!$H:$H,ПФ2026!D$5) -> -1862946.4 | E27: =SUMIFS(data!$G:$G,data!$C:$C,$B$13,data!$D:$D,$B$24,data!$F:$F,E$4,data!$E:$E,$B27,data!$H:$H,ПФ2026!E$5) -> -2272854.2 | F27: =SUMIFS(data!$G:$G,data!$C:$C,$B$13,data!$D:$D,$B$24,data!$F:$F,E$4,data!$E:$E,$B27,data!$H:$H,ПФ2026!F$5) -> -2050465.1 | G27: =SUMIFS(data!$G:$G,data!$C:$C,$B$13,data!$D:$D,$B$24,data!$F:$F,G$4,data!$E:$E,$B27,data!$H:$H,ПФ2026!G$5) -> -1470771.1 | H27: =SUMIFS(data!$G:$G,data!$C:$C,$B$13,data!$D:$D,$B$24,data!$F:$F,G$4,data!$E:$E,$B27,data!$H:$H,ПФ2026!H$5) -> -2016269.8 | I27: =SUMIFS(data!$G:$G,data!$C:$C,$B$13,data!$D:$D,$B$24,data!$F:$F,I$4,data!$E:$E,$B27,data!$H:$H,ПФ2026!I$5) -> -2116859.1 | J27: =SUMIFS(data!$G:$G,data!$C:$C,$B$13,data!$D:$D,$B$24,data!$F:$F,I$4,data!$E:$E,$B27,data!$H:$H,ПФ2026!J$5) -> -2475404 | K27: =SUMIFS(data!$G:$G,data!$C:$C,$B$13,data!$D:$D,$B$24,data!$F:$F,K$4,data!$E:$E,$B27,data!$H:$H,ПФ2026!K$5) -> -2563563.7 | L27: =SUMIFS(data!$G:$G,data!$C:$C,$B$13,data!$D:$D,$B$24,data!$F:$F,K$4,data!$E:$E,$B27,data!$H:$H,ПФ2026!L$5) -> -2906727.6 | M27: =SUMIFS(data!$G:$G,data!$C:$C,$B$13,data!$D:$D,$B$24,data!$F:$F,M$4,data!$E:$E,$B27,data!$H:$H,ПФ2026!M$5) -> -2806475 | N27: =SUMIFS(data!$G:$G,data!$C:$C,$B$13,data!$D:$D,$B$24,data!$F:$F,M$4,data!$E:$E,$B27,data!$H:$H,ПФ2026!N$5) -> -3589229.1 | O27: =SUMIFS(data!$G:$G,data!$C:$C,$B$13,data!$D:$D,$B$24,data!$F:$F,O$4,data!$E:$E,$B27,data!$H:$H,ПФ2026!O$5) -> -2985621.2 | P27: =SUMIFS(data!$G:$G,data!$C:$C,$B$13,data!$D:$D,$B$24,data!$F:$F,O$4,data!$E:$E,$B27,data!$H:$H,ПФ2026!P$5) -> 0 | Q27: =SUMIFS(data!$G:$G,data!$C:$C,$B$13,data!$D:$D,$B$24,data!$F:$F,Q$4,data!$E:$E,$B27,data!$H:$H,ПФ2026!Q$5) -> -3012850.1 | R27: =SUMIFS(data!$G:$G,data!$C:$C,$B$13,data!$D:$D,$B$24,data!$F:$F,Q$4,data!$E:$E,$B27,data!$H:$H,ПФ2026!R$5) -> 0 | S27: =SUMIFS(data!$G:$G,data!$C:$C,$B$13,data!$D:$D,$B$24,data!$F:$F,S$4,data!$E:$E,$B27,data!$H:$H,ПФ2026!S$5) -> -4438331.4 | T27: =SUMIFS(data!$G:$G,data!$C:$C,$B$13,data!$D:$D,$B$24,data!$F:$F,S$4,data!$E:$E,$B27,data!$H:$H,ПФ2026!T$5) -> 0 | U27: =SUMIFS(data!$G:$G,data!$C:$C,$B$13,data!$D:$D,$B$24,data!$F:$F,U$4,data!$E:$E,$B27,data!$H:$H,ПФ2026!U$5) -> -3439263.7 | V27: =SUMIFS(data!$G:$G,data!$C:$C,$B$13,data!$D:$D,$B$24,data!$F:$F,U$4,data!$E:$E,$B27,data!$H:$H,ПФ2026!V$5) -> 0 | W27: =SUMIFS(data!$G:$G,data!$C:$C,$B$13,data!$D:$D,$B$24,data!$F:$F,W$4,data!$E:$E,$B27,data!$H:$H,ПФ2026!W$5) -> -3643003.1 | X27: =SUMIFS(data!$G:$G,data!$C:$C,$B$13,data!$D:$D,$B$24,data!$F:$F,W$4,data!$E:$E,$B27,data!$H:$H,ПФ2026!X$5) -> 0 | Y27: =SUMIFS(data!$G:$G,data!$C:$C,$B$13,data!$D:$D,$B$24,data!$F:$F,Y$4,data!$E:$E,$B27,data!$H:$H,ПФ2026!Y$5) -> -3498992.1 | Z27: =SUMIFS(data!$G:$G,data!$C:$C,$B$13,data!$D:$D,$B$24,data!$F:$F,Y$4,data!$E:$E,$B27,data!$H:$H,ПФ2026!Z$5) -> 0 | AA27: =SUM(C27,E27,G27,I27,K27,M27,O87,O27,Q27,S27,Y27,W27,U27) -> -34052051 | AB27: =D27+F27+H27+J27+L27+N27+P27+R27+T27+V27+X27+Z27 -> -14901042 | AC27: =IFERROR(AB27/AA27,0) -> 0.43759602
B28: Расходы на дезинфицирующие средства | C28: =SUM(C29) -> -755239.2 | D28: =SUM(D29) -> -829855.97 | E28: =SUM(E29) -> -690216 | F28: =SUM(F29) -> -781337.17 | G28: =SUM(G29) -> -860728 | H28: =SUM(H29) -> -1546326.1 | I28: =SUM(I29) -> -1067128 | J28: =SUM(J29) -> -1518675.3 | ... Z28: =SUM(Z29) -> 0 | AA28: =SUM(C28,E28,G28,I28,K28,M28,O88,O28,Q28,S28,Y28,W28,U28) -> -11660431 | AB28: =D28+F28+H28+J28+L28+N28+P28+R28+T28+V28+X28+Z28 -> -8940634.6 | AC28: =IFERROR(AB28/AA28,0) -> 0.76674991
B29: Расходы на дезинфицирующие средства | C29: =SUMIFS(data!$G:$G,data!$C:$C,$B$13,data!$D:$D,$B$28,data!$F:$F,C$4,data!$E:$E,$B29,data!$H:$H,ПФ2026!C$5) -> -755239.2 | D29: =SUMIFS(data!$G:$G,data!$C:$C,$B$13,data!$D:$D,$B$28,data!$F:$F,C$4,data!$E:$E,$B29,data!$H:$H,ПФ2026!D$5) -> -829855.97 | E29: =SUMIFS(data!$G:$G,data!$C:$C,$B$13,data!$D:$D,$B$28,data!$F:$F,E$4,data!$E:$E,$B29,data!$H:$H,ПФ2026!E$5) -> -690216 | F29: =SUMIFS(data!$G:$G,data!$C:$C,$B$13,data!$D:$D,$B$28,data!$F:$F,E$4,data!$E:$E,$B29,data!$H:$H,ПФ2026!F$5) -> -781337.17 | G29: =SUMIFS(data!$G:$G,data!$C:$C,$B$13,data!$D:$D,$B$28,data!$F:$F,G$4,data!$E:$E,$B29,data!$H:$H,ПФ2026!G$5) -> -860728 | H29: =SUMIFS(data!$G:$G,data!$C:$C,$B$13,data!$D:$D,$B$28,data!$F:$F,G$4,data!$E:$E,$B29,data!$H:$H,ПФ2026!H$5) -> -1546326.1 | I29: =SUMIFS(data!$G:$G,data!$C:$C,$B$13,data!$D:$D,$B$28,data!$F:$F,I$4,data!$E:$E,$B29,data!$H:$H,ПФ2026!I$5) -> -1067128 | J29: =SUMIFS(data!$G:$G,data!$C:$C,$B$13,data!$D:$D,$B$28,data!$F:$F,I$4,data!$E:$E,$B29,data!$H:$H,ПФ2026!J$5) -> -1518675.3 | K29: =SUMIFS(data!$G:$G,data!$C:$C,$B$13,data!$D:$D,$B$28,data!$F:$F,K$4,data!$E:$E,$B29,data!$H:$H,ПФ2026!K$5) -> -1065228 | L29: =SUMIFS(data!$G:$G,data!$C:$C,$B$13,data!$D:$D,$B$28,data!$F:$F,K$4,data!$E:$E,$B29,data!$H:$H,ПФ2026!L$5) -> -1815898.4 | M29: =SUMIFS(data!$G:$G,data!$C:$C,$B$13,data!$D:$D,$B$28,data!$F:$F,M$4,data!$E:$E,$B29,data!$H:$H,ПФ2026!M$5) -> -1138748 | N29: =SUMIFS(data!$G:$G,data!$C:$C,$B$13,data!$D:$D,$B$28,data!$F:$F,M$4,data!$E:$E,$B29,data!$H:$H,ПФ2026!N$5) -> -2448541.7 | O29: =SUMIFS(data!$G:$G,data!$C:$C,$B$13,data!$D:$D,$B$28,data!$F:$F,O$4,data!$E:$E,$B29,data!$H:$H,ПФ2026!O$5) -> -1274198.4 | P29: =SUMIFS(data!$G:$G,data!$C:$C,$B$13,data!$D:$D,$B$28,data!$F:$F,O$4,data!$E:$E,$B29,data!$H:$H,ПФ2026!P$5) -> 0 | Q29: =SUMIFS(data!$G:$G,data!$C:$C,$B$13,data!$D:$D,$B$28,data!$F:$F,Q$4,data!$E:$E,$B29,data!$H:$H,ПФ2026!Q$5) -> -1221966.4 | R29: =SUMIFS(data!$G:$G,data!$C:$C,$B$13,data!$D:$D,$B$28,data!$F:$F,Q$4,data!$E:$E,$B29,data!$H:$H,ПФ2026!R$5) -> 0 | S29: =SUMIFS(data!$G:$G,data!$C:$C,$B$13,data!$D:$D,$B$28,data!$F:$F,S$4,data!$E:$E,$B29,data!$H:$H,ПФ2026!S$5) -> -1154674.4 | T29: =SUMIFS(data!$G:$G,data!$C:$C,$B$13,data!$D:$D,$B$28,data!$F:$F,S$4,data!$E:$E,$B29,data!$H:$H,ПФ2026!T$5) -> 0 | U29: =SUMIFS(data!$G:$G,data!$C:$C,$B$13,data!$D:$D,$B$28,data!$F:$F,U$4,data!$E:$E,$B29,data!$H:$H,ПФ2026!U$5) -> -894862.4 | V29: =SUMIFS(data!$G:$G,data!$C:$C,$B$13,data!$D:$D,$B$28,data!$F:$F,U$4,data!$E:$E,$B29,data!$H:$H,ПФ2026!V$5) -> 0 | W29: =SUMIFS(data!$G:$G,data!$C:$C,$B$13,data!$D:$D,$B$28,data!$F:$F,W$4,data!$E:$E,$B29,data!$H:$H,ПФ2026!W$5) -> -771915.2 | X29: =SUMIFS(data!$G:$G,data!$C:$C,$B$13,data!$D:$D,$B$28,data!$F:$F,W$4,data!$E:$E,$B29,data!$H:$H,ПФ2026!X$5) -> 0 | Y29: =SUMIFS(data!$G:$G,data!$C:$C,$B$13,data!$D:$D,$B$28,data!$F:$F,Y$4,data!$E:$E,$B29,data!$H:$H,ПФ2026!Y$5) -> -765527.2 | Z29: =SUMIFS(data!$G:$G,data!$C:$C,$B$13,data!$D:$D,$B$28,data!$F:$F,Y$4,data!$E:$E,$B29,data!$H:$H,ПФ2026!Z$5) -> 0 | AA29: =SUM(C29,E29,G29,I29,K29,M29,O91,O29,Q29,S29) -> -9228126.4 | AB29: =SUM(D29,F29,H29,J29,L29,N29,P91,P29,R29,T29) -> -8940634.6 | AC29: =IFERROR(AB29/AA29,0) -> 0.96884613
B30: Операционные расходы | C30: =SUM(C31,C78,C159,C235,C357,C594,C668,C691,) -> -1.3654275e+08 | D30: =SUM(D31,D78,D159,D235,D357,D594,D668,D691,) -> -1.3009556e+08 | E30: =SUM(E31,E78,E159,E235,E357,E594,E668,E691,) -> -1.4150044e+08 | F30: =SUM(F31,F78,F159,F235,F357,F594,F668,F691,) -> -1.3647242e+08 | G30: =SUM(G31,G78,G159,G235,G357,G594,G668,G691,) -> -1.9463922e+08 | H30: =SUM(H31,H78,H159,H235,H357,H594,H668,H691,) -> -1.6824038e+08 | I30: =SUM(I31,I78,I159,I235,I357,I594,I668,I691,) -> -2.3311898e+08 | J30: =SUM(J31,J78,J159,J235,J357,J594,J668,J691,) -> -2.1604847e+08 | ... Z30: =SUM(Z31,Z78,Z159,Z235,Z357,Z594,Z668,Z691,) -> 0 | AA30: =C30+E30+G30+I30+K30+M30+O30+Q30+S30+U30+W30+Y30 -> -2.5481857e+09 | AB30: =D30+F30+H30+J30+L30+N30+P30+R30+T30+V30+X30+Z30 -> -1.1804129e+09 | AC30: =IFERROR(AB30/AA30,0) -> 0.46323662
B31: Общие расходы | C31: =SUM(C32,C34,C36,C38,C41,C47,C58,C61) -> -49140853 | D31: =SUM(D32,D34,D36,D38,D41,D47,D58,D61) -> -54431423 | E31: =SUM(E32,E34,E36,E38,E41,E47,E58,E61) -> -48052936 | F31: =SUM(F32,F34,F36,F38,F41,F47,F58,F61) -> -58070430 | G31: =SUM(G32,G34,G36,G38,G41,G47,G58,G61) -> -61513948 | H31: =SUM(H32,H34,H36,H38,H41,H47,H58,H61) -> -71693878 | I31: =SUM(I32,I34,I36,I38,I41,I47,I58,I61) -> -80586352 | J31: =SUM(J32,J34,J36,J38,J41,J47,J58,J61) -> -95987840 | ... Z31: =SUM(Z32,Z34,Z36,Z38,Z41,Z47,Z58,Z61) -> 0 | AA31: =SUM(C31,E31,G31,I31,K31,M31,O93,O31,Q31,S31,U31,W31,Y31) -> -8.2417626e+08 | AB31: =SUM(D31,F31,H31,J31,L31,N31,P93,P31,R31,T31,V31,X31,Z31) -> -4.9482277e+08 | AC31: =IFERROR(AB31/AA31,0) -> 0.60038465
B32: Расходы на дезинфицирующие средства | C32: =SUM(C33) -> -19420 | D32: =SUM(D33) -> 0 | E32: =SUM(E33) -> -18280 | F32: =SUM(F33) -> 0 | G32: =SUM(G33) -> -26284 | H32: =SUM(H33) -> 0 | I32: =SUM(I33) -> -19140 | J32: =SUM(J33) -> 0 | ... Z32: =SUM(Z33) -> 0 | AA32: =SUM(C32,E32,G32,I32,K32,M32,O92,O32,Q32,S32,Y32,W32,U32) -> -256596 | AB32: =D32+F32+H32+J32+L32+N32+P32+R32+T32+V32+X32+Z32 -> 0 | AC32: =IFERROR(AB32/AA32,0) -> 0
B33: Расходы на дезинфицирующие средства | C33: =SUMIFS(data!$G:$G,data!$C:$C,$B$31,data!$D:$D,$B$32,data!$F:$F,C$4,data!$E:$E,$B33,data!$H:$H,ПФ2026!C$5) -> -19420 | D33: =SUMIFS(data!$G:$G,data!$C:$C,$B$31,data!$D:$D,$B$32,data!$F:$F,C$4,data!$E:$E,$B33,data!$H:$H,ПФ2026!D$5) -> 0 | E33: =SUMIFS(data!$G:$G,data!$C:$C,$B$31,data!$D:$D,$B$32,data!$F:$F,E$4,data!$E:$E,$B33,data!$H:$H,ПФ2026!E$5) -> -18280 | F33: =SUMIFS(data!$G:$G,data!$C:$C,$B$31,data!$D:$D,$B$32,data!$F:$F,E$4,data!$E:$E,$B33,data!$H:$H,ПФ2026!F$5) -> 0 | G33: =SUMIFS(data!$G:$G,data!$C:$C,$B$31,data!$D:$D,$B$32,data!$F:$F,G$4,data!$E:$E,$B33,data!$H:$H,ПФ2026!G$5) -> -26284 | H33: =SUMIFS(data!$G:$G,data!$C:$C,$B$31,data!$D:$D,$B$32,data!$F:$F,G$4,data!$E:$E,$B33,data!$H:$H,ПФ2026!H$5) -> 0 | I33: =SUMIFS(data!$G:$G,data!$C:$C,$B$31,data!$D:$D,$B$32,data!$F:$F,I$4,data!$E:$E,$B33,data!$H:$H,ПФ2026!I$5) -> -19140 | J33: =SUMIFS(data!$G:$G,data!$C:$C,$B$31,data!$D:$D,$B$32,data!$F:$F,I$4,data!$E:$E,$B33,data!$H:$H,ПФ2026!J$5) -> 0 | K33: =SUMIFS(data!$G:$G,data!$C:$C,$B$31,data!$D:$D,$B$32,data!$F:$F,K$4,data!$E:$E,$B33,data!$H:$H,ПФ2026!K$5) -> -19140 | L33: =SUMIFS(data!$G:$G,data!$C:$C,$B$31,data!$D:$D,$B$32,data!$F:$F,K$4,data!$E:$E,$B33,data!$H:$H,ПФ2026!L$5) -> 0 | M33: =SUMIFS(data!$G:$G,data!$C:$C,$B$31,data!$D:$D,$B$32,data!$F:$F,M$4,data!$E:$E,$B33,data!$H:$H,ПФ2026!M$5) -> -18860 | N33: =SUMIFS(data!$G:$G,data!$C:$C,$B$31,data!$D:$D,$B$32,data!$F:$F,M$4,data!$E:$E,$B33,data!$H:$H,ПФ2026!N$5) -> 0 | O33: =SUMIFS(data!$G:$G,data!$C:$C,$B$31,data!$D:$D,$B$32,data!$F:$F,O$4,data!$E:$E,$B33,data!$H:$H,ПФ2026!O$5) -> -21036 | P33: =SUMIFS(data!$G:$G,data!$C:$C,$B$31,data!$D:$D,$B$32,data!$F:$F,O$4,data!$E:$E,$B33,data!$H:$H,ПФ2026!P$5) -> 0 | Q33: =SUMIFS(data!$G:$G,data!$C:$C,$B$31,data!$D:$D,$B$32,data!$F:$F,Q$4,data!$E:$E,$B33,data!$H:$H,ПФ2026!Q$5) -> -20728 | R33: =SUMIFS(data!$G:$G,data!$C:$C,$B$31,data!$D:$D,$B$32,data!$F:$F,Q$4,data!$E:$E,$B33,data!$H:$H,ПФ2026!R$5) -> 0 | S33: =SUMIFS(data!$G:$G,data!$C:$C,$B$31,data!$D:$D,$B$32,data!$F:$F,S$4,data!$E:$E,$B33,data!$H:$H,ПФ2026!S$5) -> -22456 | T33: =SUMIFS(data!$G:$G,data!$C:$C,$B$31,data!$D:$D,$B$32,data!$F:$F,S$4,data!$E:$E,$B33,data!$H:$H,ПФ2026!T$5) -> 0 | U33: =SUMIFS(data!$G:$G,data!$C:$C,$B$31,data!$D:$D,$B$32,data!$F:$F,U$4,data!$E:$E,$B33,data!$H:$H,ПФ2026!U$5) -> -20416 | V33: =SUMIFS(data!$G:$G,data!$C:$C,$B$31,data!$D:$D,$B$32,data!$F:$F,U$4,data!$E:$E,$B33,data!$H:$H,ПФ2026!V$5) -> 0 | W33: =SUMIFS(data!$G:$G,data!$C:$C,$B$31,data!$D:$D,$B$32,data!$F:$F,W$4,data!$E:$E,$B33,data!$H:$H,ПФ2026!W$5) -> -20728 | X33: =SUMIFS(data!$G:$G,data!$C:$C,$B$31,data!$D:$D,$B$32,data!$F:$F,W$4,data!$E:$E,$B33,data!$H:$H,ПФ2026!X$5) -> 0 | Y33: =SUMIFS(data!$G:$G,data!$C:$C,$B$31,data!$D:$D,$B$32,data!$F:$F,Y$4,data!$E:$E,$B33,data!$H:$H,ПФ2026!Y$5) -> -20108 | Z33: =SUMIFS(data!$G:$G,data!$C:$C,$B$31,data!$D:$D,$B$32,data!$F:$F,Y$4,data!$E:$E,$B33,data!$H:$H,ПФ2026!Z$5) -> 0 | AA33: =SUM(C33,E33,G33,I33,K33,M33,O93,O33,Q33,S33,Y33,W33,U33) -> -246596 | AB33: =D33+F33+H33+J33+L33+N33+P33+R33+T33+V33+X33+Z33 -> 0 | AC33: =IFERROR(AB33/AA33,0) -> 0
B34: Расходы на канц.товары | C34: =SUM(C35) -> -386654.4 | D34: =SUM(D35) -> -298410.7 | E34: =SUM(E35) -> -300055.8 | F34: =SUM(F35) -> -205004.86 | G34: =SUM(G35) -> -272128.8 | H34: =SUM(H35) -> -224047.56 | I34: =SUM(I35) -> -243858 | J34: =SUM(J35) -> -458591.15 | ... Z34: =SUM(Z35) -> 0 | AA34: =SUM(C34,E34,G34,I34,K34,M34,O94,O34,Q34,S34,Y34,W34,U34) -> -3208938.5 | AB34: =D34+F34+H34+J34+L34+N34+P34+R34+T34+V34+X34+Z34 -> -2046078 | AC34: =IFERROR(AB34/AA34,0) -> 0.63761833
B35: Расходы на канц.товары | C35: =SUMIFS(data!$G:$G,data!$C:$C,$B$31,data!$D:$D,$B$34,data!$F:$F,C$4,data!$E:$E,$B35,data!$H:$H,ПФ2026!C$5) -> -386654.4 | D35: =SUMIFS(data!$G:$G,data!$C:$C,$B$31,data!$D:$D,$B$34,data!$F:$F,C$4,data!$E:$E,$B35,data!$H:$H,ПФ2026!D$5) -> -298410.7 | E35: =SUMIFS(data!$G:$G,data!$C:$C,$B$31,data!$D:$D,$B$34,data!$F:$F,E$4,data!$E:$E,$B35,data!$H:$H,ПФ2026!E$5) -> -300055.8 | F35: =SUMIFS(data!$G:$G,data!$C:$C,$B$31,data!$D:$D,$B$34,data!$F:$F,E$4,data!$E:$E,$B35,data!$H:$H,ПФ2026!F$5) -> -205004.86 | G35: =SUMIFS(data!$G:$G,data!$C:$C,$B$31,data!$D:$D,$B$34,data!$F:$F,G$4,data!$E:$E,$B35,data!$H:$H,ПФ2026!G$5) -> -272128.8 | H35: =SUMIFS(data!$G:$G,data!$C:$C,$B$31,data!$D:$D,$B$34,data!$F:$F,G$4,data!$E:$E,$B35,data!$H:$H,ПФ2026!H$5) -> -224047.56 | I35: =SUMIFS(data!$G:$G,data!$C:$C,$B$31,data!$D:$D,$B$34,data!$F:$F,I$4,data!$E:$E,$B35,data!$H:$H,ПФ2026!I$5) -> -243858 | J35: =SUMIFS(data!$G:$G,data!$C:$C,$B$31,data!$D:$D,$B$34,data!$F:$F,I$4,data!$E:$E,$B35,data!$H:$H,ПФ2026!J$5) -> -458591.15 | K35: =SUMIFS(data!$G:$G,data!$C:$C,$B$31,data!$D:$D,$B$34,data!$F:$F,K$4,data!$E:$E,$B35,data!$H:$H,ПФ2026!K$5) -> -265827.6 | L35: =SUMIFS(data!$G:$G,data!$C:$C,$B$31,data!$D:$D,$B$34,data!$F:$F,K$4,data!$E:$E,$B35,data!$H:$H,ПФ2026!L$5) -> -594993.14 | M35: =SUMIFS(data!$G:$G,data!$C:$C,$B$31,data!$D:$D,$B$34,data!$F:$F,M$4,data!$E:$E,$B35,data!$H:$H,ПФ2026!M$5) -> -271251 | N35: =SUMIFS(data!$G:$G,data!$C:$C,$B$31,data!$D:$D,$B$34,data!$F:$F,M$4,data!$E:$E,$B35,data!$H:$H,ПФ2026!N$5) -> -265030.57 | O35: =SUMIFS(data!$G:$G,data!$C:$C,$B$31,data!$D:$D,$B$34,data!$F:$F,O$4,data!$E:$E,$B35,data!$H:$H,ПФ2026!O$5) -> -264525.72 | P35: =SUMIFS(data!$G:$G,data!$C:$C,$B$31,data!$D:$D,$B$34,data!$F:$F,O$4,data!$E:$E,$B35,data!$H:$H,ПФ2026!P$5) -> 0 | Q35: =SUMIFS(data!$G:$G,data!$C:$C,$B$31,data!$D:$D,$B$34,data!$F:$F,Q$4,data!$E:$E,$B35,data!$H:$H,ПФ2026!Q$5) -> -262042.86 | R35: =SUMIFS(data!$G:$G,data!$C:$C,$B$31,data!$D:$D,$B$34,data!$F:$F,Q$4,data!$E:$E,$B35,data!$H:$H,ПФ2026!R$5) -> 0 | S35: =SUMIFS(data!$G:$G,data!$C:$C,$B$31,data!$D:$D,$B$34,data!$F:$F,S$4,data!$E:$E,$B35,data!$H:$H,ПФ2026!S$5) -> -242105.94 | T35: =SUMIFS(data!$G:$G,data!$C:$C,$B$31,data!$D:$D,$B$34,data!$F:$F,S$4,data!$E:$E,$B35,data!$H:$H,ПФ2026!T$5) -> 0 | U35: =SUMIFS(data!$G:$G,data!$C:$C,$B$31,data!$D:$D,$B$34,data!$F:$F,U$4,data!$E:$E,$B35,data!$H:$H,ПФ2026!U$5) -> -240402.78 | V35: =SUMIFS(data!$G:$G,data!$C:$C,$B$31,data!$D:$D,$B$34,data!$F:$F,U$4,data!$E:$E,$B35,data!$H:$H,ПФ2026!V$5) -> 0 | W35: =SUMIFS(data!$G:$G,data!$C:$C,$B$31,data!$D:$D,$B$34,data!$F:$F,W$4,data!$E:$E,$B35,data!$H:$H,ПФ2026!W$5) -> -231930.06 | X35: =SUMIFS(data!$G:$G,data!$C:$C,$B$31,data!$D:$D,$B$34,data!$F:$F,W$4,data!$E:$E,$B35,data!$H:$H,ПФ2026!X$5) -> 0 | Y35: =SUMIFS(data!$G:$G,data!$C:$C,$B$31,data!$D:$D,$B$34,data!$F:$F,Y$4,data!$E:$E,$B35,data!$H:$H,ПФ2026!Y$5) -> -228155.52 | Z35: =SUMIFS(data!$G:$G,data!$C:$C,$B$31,data!$D:$D,$B$34,data!$F:$F,Y$4,data!$E:$E,$B35,data!$H:$H,ПФ2026!Z$5) -> 0 | AA35: =SUM(C35,E35,G35,I35,K35,M35,O95,O35,Q35,S35,Y35,W35,U35) -> -3208938.5 | AB35: =D35+F35+H35+J35+L35+N35+P35+R35+T35+V35+X35+Z35 -> -2046078 | AC35: =IFERROR(AB35/AA35,0) -> 0.63761833
B36: Расходы на мыломоющие средства | C36: =SUM(C37:C37) -> -355301.4 | D36: =SUM(D37:D37) -> -406834.75 | E36: =SUM(E37:E37) -> -367840.2 | F36: =SUM(F37:F37) -> -572940.93 | G36: =SUM(G37:G37) -> -439411.8 | H36: =SUM(H37:H37) -> -274680.9 | I36: =SUM(I37:I37) -> -418035 | J36: =SUM(J37:J37) -> -429215.18 | ... Z36: =SUM(Z37:Z37) -> 0 | AA36: =SUM(C36,E36,G36,I36,K36,M36,O96,O36,Q36,S36,Y36,W36,U36) -> -4960042.8 | AB36: =D36+F36+H36+J36+L36+N36+P36+R36+T36+V36+X36+Z36 -> -2421309.1 | AC36: =IFERROR(AB36/AA36,0) -> 0.48816295
B37: Расходы на мыломоющие средства | C37: =SUMIFS(data!$G:$G,data!$C:$C,$B$31,data!$D:$D,$B$36,data!$F:$F,C$4,data!$E:$E,$B37,data!$H:$H,ПФ2026!C$5) -> -355301.4 | D37: =SUMIFS(data!$G:$G,data!$C:$C,$B$31,data!$D:$D,$B$36,data!$F:$F,C$4,data!$E:$E,$B37,data!$H:$H,ПФ2026!D$5) -> -406834.75 | E37: =SUMIFS(data!$G:$G,data!$C:$C,$B$31,data!$D:$D,$B$36,data!$F:$F,E$4,data!$E:$E,$B37,data!$H:$H,ПФ2026!E$5) -> -367840.2 | F37: =SUMIFS(data!$G:$G,data!$C:$C,$B$31,data!$D:$D,$B$36,data!$F:$F,E$4,data!$E:$E,$B37,data!$H:$H,ПФ2026!F$5) -> -572940.93 | G37: =SUMIFS(data!$G:$G,data!$C:$C,$B$31,data!$D:$D,$B$36,data!$F:$F,G$4,data!$E:$E,$B37,data!$H:$H,ПФ2026!G$5) -> -439411.8 | H37: =SUMIFS(data!$G:$G,data!$C:$C,$B$31,data!$D:$D,$B$36,data!$F:$F,G$4,data!$E:$E,$B37,data!$H:$H,ПФ2026!H$5) -> -274680.9 | I37: =SUMIFS(data!$G:$G,data!$C:$C,$B$31,data!$D:$D,$B$36,data!$F:$F,I$4,data!$E:$E,$B37,data!$H:$H,ПФ2026!I$5) -> -418035 | J37: =SUMIFS(data!$G:$G,data!$C:$C,$B$31,data!$D:$D,$B$36,data!$F:$F,I$4,data!$E:$E,$B37,data!$H:$H,ПФ2026!J$5) -> -429215.18 | K37: =SUMIFS(data!$G:$G,data!$C:$C,$B$31,data!$D:$D,$B$36,data!$F:$F,K$4,data!$E:$E,$B37,data!$H:$H,ПФ2026!K$5) -> -427692 | L37: =SUMIFS(data!$G:$G,data!$C:$C,$B$31,data!$D:$D,$B$36,data!$F:$F,K$4,data!$E:$E,$B37,data!$H:$H,ПФ2026!L$5) -> -517654.48 | M37: =SUMIFS(data!$G:$G,data!$C:$C,$B$31,data!$D:$D,$B$36,data!$F:$F,M$4,data!$E:$E,$B37,data!$H:$H,ПФ2026!M$5) -> -424065.6 | N37: =SUMIFS(data!$G:$G,data!$C:$C,$B$31,data!$D:$D,$B$36,data!$F:$F,M$4,data!$E:$E,$B37,data!$H:$H,ПФ2026!N$5) -> -219982.9 | O37: =SUMIFS(data!$G:$G,data!$C:$C,$B$31,data!$D:$D,$B$36,data!$F:$F,O$4,data!$E:$E,$B37,data!$H:$H,ПФ2026!O$5) -> -487006.08 | P37: =SUMIFS(data!$G:$G,data!$C:$C,$B$31,data!$D:$D,$B$36,data!$F:$F,O$4,data!$E:$E,$B37,data!$H:$H,ПФ2026!P$5) -> 0 | Q37: =SUMIFS(data!$G:$G,data!$C:$C,$B$31,data!$D:$D,$B$36,data!$F:$F,Q$4,data!$E:$E,$B37,data!$H:$H,ПФ2026!Q$5) -> -445406.58 | R37: =SUMIFS(data!$G:$G,data!$C:$C,$B$31,data!$D:$D,$B$36,data!$F:$F,Q$4,data!$E:$E,$B37,data!$H:$H,ПФ2026!R$5) -> 0 | S37: =SUMIFS(data!$G:$G,data!$C:$C,$B$31,data!$D:$D,$B$36,data!$F:$F,S$4,data!$E:$E,$B37,data!$H:$H,ПФ2026!S$5) -> -456546.36 | T37: =SUMIFS(data!$G:$G,data!$C:$C,$B$31,data!$D:$D,$B$36,data!$F:$F,S$4,data!$E:$E,$B37,data!$H:$H,ПФ2026!T$5) -> 0 | U37: =SUMIFS(data!$G:$G,data!$C:$C,$B$31,data!$D:$D,$B$36,data!$F:$F,U$4,data!$E:$E,$B37,data!$H:$H,ПФ2026!U$5) -> -402267.54 | V37: =SUMIFS(data!$G:$G,data!$C:$C,$B$31,data!$D:$D,$B$36,data!$F:$F,U$4,data!$E:$E,$B37,data!$H:$H,ПФ2026!V$5) -> 0 | W37: =SUMIFS(data!$G:$G,data!$C:$C,$B$31,data!$D:$D,$B$36,data!$F:$F,W$4,data!$E:$E,$B37,data!$H:$H,ПФ2026!W$5) -> -379787.64 | X37: =SUMIFS(data!$G:$G,data!$C:$C,$B$31,data!$D:$D,$B$36,data!$F:$F,W$4,data!$E:$E,$B37,data!$H:$H,ПФ2026!X$5) -> 0 | Y37: =SUMIFS(data!$G:$G,data!$C:$C,$B$31,data!$D:$D,$B$36,data!$F:$F,Y$4,data!$E:$E,$B37,data!$H:$H,ПФ2026!Y$5) -> -355682.64 | Z37: =SUMIFS(data!$G:$G,data!$C:$C,$B$31,data!$D:$D,$B$36,data!$F:$F,Y$4,data!$E:$E,$B37,data!$H:$H,ПФ2026!Z$5) -> 0 | AA37: =SUM(C37,E37,G37,I37,K37,M37,O97,O37,Q37,S37,Y37,W37,U37) -> -4959042.8 | AB37: =D37+F37+H37+J37+L37+N37+P37+R37+T37+V37+X37+Z37 -> -2421309.1 | AC37: =IFERROR(AB37/AA37,0) -> 0.48826139
B38: Расходы на спец.одежду | C38: =SUM(C39:C40) -> -570843.78 | D38: =SUM(D39:D40) -> 0 | E38: =SUM(E39:E40) -> -581350.38 | F38: =SUM(F39:F40) -> 0 | G38: =SUM(G39:G40) -> -1504496 | H38: =SUM(H39:H40) -> 0 | I38: =SUM(I39:I40) -> -281380.32 | J38: =SUM(J39:J40) -> -129960 | ... Z38: =SUM(Z39:Z40) -> 0 | AA38: =SUM(C38,E38,G38,I38,K38,M38,O98,O38,Q38,S38,Y38,W38,U38) -> -5505154.2 | AB38: =D38+F38+H38+J38+L38+N38+P38+R38+T38+V38+X38+Z38 -> -129960 | AC38: =IFERROR(AB38/AA38,0) -> 0.023606968
B39: Расходы на спец.одежду | C39: =SUMIFS(data!$G:$G,data!$C:$C,$B$31,data!$D:$D,$B$38,data!$F:$F,C$4,data!$E:$E,$B39,data!$H:$H,ПФ2026!C$5) -> -570843.78 | D39: =SUMIFS(data!$G:$G,data!$C:$C,$B$31,data!$D:$D,$B$38,data!$F:$F,C$4,data!$E:$E,$B39,data!$H:$H,ПФ2026!D$5) -> 0 | E39: =SUMIFS(data!$G:$G,data!$C:$C,$B$31,data!$D:$D,$B$38,data!$F:$F,E$4,data!$E:$E,$B39,data!$H:$H,ПФ2026!E$5) -> -581350.38 | F39: =SUMIFS(data!$G:$G,data!$C:$C,$B$31,data!$D:$D,$B$38,data!$F:$F,E$4,data!$E:$E,$B39,data!$H:$H,ПФ2026!F$5) -> 0 | G39: =SUMIFS(data!$G:$G,data!$C:$C,$B$31,data!$D:$D,$B$38,data!$F:$F,G$4,data!$E:$E,$B39,data!$H:$H,ПФ2026!G$5) -> -1504496 | H39: =SUMIFS(data!$G:$G,data!$C:$C,$B$31,data!$D:$D,$B$38,data!$F:$F,G$4,data!$E:$E,$B39,data!$H:$H,ПФ2026!H$5) -> 0 | I39: =SUMIFS(data!$G:$G,data!$C:$C,$B$31,data!$D:$D,$B$38,data!$F:$F,I$4,data!$E:$E,$B39,data!$H:$H,ПФ2026!I$5) -> -281380.32 | J39: =SUMIFS(data!$G:$G,data!$C:$C,$B$31,data!$D:$D,$B$38,data!$F:$F,I$4,data!$E:$E,$B39,data!$H:$H,ПФ2026!J$5) -> -129960 | K39: =SUMIFS(data!$G:$G,data!$C:$C,$B$31,data!$D:$D,$B$38,data!$F:$F,K$4,data!$E:$E,$B39,data!$H:$H,ПФ2026!K$5) -> -224787.68 | L39: =SUMIFS(data!$G:$G,data!$C:$C,$B$31,data!$D:$D,$B$38,data!$F:$F,K$4,data!$E:$E,$B39,data!$H:$H,ПФ2026!L$5) -> 0 | M39: =SUMIFS(data!$G:$G,data!$C:$C,$B$31,data!$D:$D,$B$38,data!$F:$F,M$4,data!$E:$E,$B39,data!$H:$H,ПФ2026!M$5) -> -307098.48 | N39: =SUMIFS(data!$G:$G,data!$C:$C,$B$31,data!$D:$D,$B$38,data!$F:$F,M$4,data!$E:$E,$B39,data!$H:$H,ПФ2026!N$5) -> 0 | O39: =SUMIFS(data!$G:$G,data!$C:$C,$B$31,data!$D:$D,$B$38,data!$F:$F,O$4,data!$E:$E,$B39,data!$H:$H,ПФ2026!O$5) -> -150487.48 | P39: =SUMIFS(data!$G:$G,data!$C:$C,$B$31,data!$D:$D,$B$38,data!$F:$F,O$4,data!$E:$E,$B39,data!$H:$H,ПФ2026!P$5) -> 0 | Q39: =SUMIFS(data!$G:$G,data!$C:$C,$B$31,data!$D:$D,$B$38,data!$F:$F,Q$4,data!$E:$E,$B39,data!$H:$H,ПФ2026!Q$5) -> -247233.48 | R39: =SUMIFS(data!$G:$G,data!$C:$C,$B$31,data!$D:$D,$B$38,data!$F:$F,Q$4,data!$E:$E,$B39,data!$H:$H,ПФ2026!R$5) -> 0 | S39: =SUMIFS(data!$G:$G,data!$C:$C,$B$31,data!$D:$D,$B$38,data!$F:$F,S$4,data!$E:$E,$B39,data!$H:$H,ПФ2026!S$5) -> -950169.48 | T39: =SUMIFS(data!$G:$G,data!$C:$C,$B$31,data!$D:$D,$B$38,data!$F:$F,S$4,data!$E:$E,$B39,data!$H:$H,ПФ2026!T$5) -> 0 | U39: =SUMIFS(data!$G:$G,data!$C:$C,$B$31,data!$D:$D,$B$38,data!$F:$F,U$4,data!$E:$E,$B39,data!$H:$H,ПФ2026!U$5) -> -449301.58 | V39: =SUMIFS(data!$G:$G,data!$C:$C,$B$31,data!$D:$D,$B$38,data!$F:$F,U$4,data!$E:$E,$B39,data!$H:$H,ПФ2026!V$5) -> 0 | W39: =SUMIFS(data!$G:$G,data!$C:$C,$B$31,data!$D:$D,$B$38,data!$F:$F,W$4,data!$E:$E,$B39,data!$H:$H,ПФ2026!W$5) -> -80871.18 | X39: =SUMIFS(data!$G:$G,data!$C:$C,$B$31,data!$D:$D,$B$38,data!$F:$F,W$4,data!$E:$E,$B39,data!$H:$H,ПФ2026!X$5) -> 0 | Y39: =SUMIFS(data!$G:$G,data!$C:$C,$B$31,data!$D:$D,$B$38,data!$F:$F,Y$4,data!$E:$E,$B39,data!$H:$H,ПФ2026!Y$5) -> -157134.38 | Z39: =SUMIFS(data!$G:$G,data!$C:$C,$B$31,data!$D:$D,$B$38,data!$F:$F,Y$4,data!$E:$E,$B39,data!$H:$H,ПФ2026!Z$5) -> 0 | AA39: =SUM(C39,E39,G39,I39,K39,M39,O99,O39,Q39,S39,Y39,W39,U39) -> -5505154.2 | AB39: =D39+F39+H39+J39+L39+N39+P39+R39+T39+V39+X39+Z39 -> -129960 | AC39: =IFERROR(AB39/AA39,0) -> 0.023606968
B40: Департамент управления человеческими ресурсами | C40: =SUMIFS(data!$G:$G,data!$C:$C,$B$31,data!$D:$D,$B$38,data!$F:$F,C$4,data!$E:$E,$B40,data!$H:$H,ПФ2026!C$5) -> 0 | D40: =SUMIFS(data!$G:$G,data!$C:$C,$B$31,data!$D:$D,$B$38,data!$F:$F,C$4,data!$E:$E,$B40,data!$H:$H,ПФ2026!D$5) -> 0 | E40: =SUMIFS(data!$G:$G,data!$C:$C,$B$31,data!$D:$D,$B$38,data!$F:$F,E$4,data!$E:$E,$B40,data!$H:$H,ПФ2026!E$5) -> 0 | F40: =SUMIFS(data!$G:$G,data!$C:$C,$B$31,data!$D:$D,$B$38,data!$F:$F,E$4,data!$E:$E,$B40,data!$H:$H,ПФ2026!F$5) -> 0 | G40: =SUMIFS(data!$G:$G,data!$C:$C,$B$31,data!$D:$D,$B$38,data!$F:$F,G$4,data!$E:$E,$B40,data!$H:$H,ПФ2026!G$5) -> 0 | H40: =SUMIFS(data!$G:$G,data!$C:$C,$B$31,data!$D:$D,$B$38,data!$F:$F,G$4,data!$E:$E,$B40,data!$H:$H,ПФ2026!H$5) -> 0 | I40: =SUMIFS(data!$G:$G,data!$C:$C,$B$31,data!$D:$D,$B$38,data!$F:$F,I$4,data!$E:$E,$B40,data!$H:$H,ПФ2026!I$5) -> 0 | J40: =SUMIFS(data!$G:$G,data!$C:$C,$B$31,data!$D:$D,$B$38,data!$F:$F,I$4,data!$E:$E,$B40,data!$H:$H,ПФ2026!J$5) -> 0 | K40: =SUMIFS(data!$G:$G,data!$C:$C,$B$31,data!$D:$D,$B$38,data!$F:$F,K$4,data!$E:$E,$B40,data!$H:$H,ПФ2026!K$5) -> 0 | L40: =SUMIFS(data!$G:$G,data!$C:$C,$B$31,data!$D:$D,$B$38,data!$F:$F,K$4,data!$E:$E,$B40,data!$H:$H,ПФ2026!L$5) -> 0 | M40: =SUMIFS(data!$G:$G,data!$C:$C,$B$31,data!$D:$D,$B$38,data!$F:$F,M$4,data!$E:$E,$B40,data!$H:$H,ПФ2026!M$5) -> 0 | N40: =SUMIFS(data!$G:$G,data!$C:$C,$B$31,data!$D:$D,$B$38,data!$F:$F,M$4,data!$E:$E,$B40,data!$H:$H,ПФ2026!N$5) -> 0 | O40: =SUMIFS(data!$G:$G,data!$C:$C,$B$31,data!$D:$D,$B$38,data!$F:$F,O$4,data!$E:$E,$B40,data!$H:$H,ПФ2026!O$5) -> 0 | P40: =SUMIFS(data!$G:$G,data!$C:$C,$B$31,data!$D:$D,$B$38,data!$F:$F,O$4,data!$E:$E,$B40,data!$H:$H,ПФ2026!P$5) -> 0 | Q40: =SUMIFS(data!$G:$G,data!$C:$C,$B$31,data!$D:$D,$B$38,data!$F:$F,Q$4,data!$E:$E,$B40,data!$H:$H,ПФ2026!Q$5) -> 0 | R40: =SUMIFS(data!$G:$G,data!$C:$C,$B$31,data!$D:$D,$B$38,data!$F:$F,Q$4,data!$E:$E,$B40,data!$H:$H,ПФ2026!R$5) -> 0 | S40: =SUMIFS(data!$G:$G,data!$C:$C,$B$31,data!$D:$D,$B$38,data!$F:$F,S$4,data!$E:$E,$B40,data!$H:$H,ПФ2026!S$5) -> 0 | T40: =SUMIFS(data!$G:$G,data!$C:$C,$B$31,data!$D:$D,$B$38,data!$F:$F,S$4,data!$E:$E,$B40,data!$H:$H,ПФ2026!T$5) -> 0 | U40: =SUMIFS(data!$G:$G,data!$C:$C,$B$31,data!$D:$D,$B$38,data!$F:$F,U$4,data!$E:$E,$B40,data!$H:$H,ПФ2026!U$5) -> 0 | V40: =SUMIFS(data!$G:$G,data!$C:$C,$B$31,data!$D:$D,$B$38,data!$F:$F,U$4,data!$E:$E,$B40,data!$H:$H,ПФ2026!V$5) -> 0 | W40: =SUMIFS(data!$G:$G,data!$C:$C,$B$31,data!$D:$D,$B$38,data!$F:$F,W$4,data!$E:$E,$B40,data!$H:$H,ПФ2026!W$5) -> 0 | X40: =SUMIFS(data!$G:$G,data!$C:$C,$B$31,data!$D:$D,$B$38,data!$F:$F,W$4,data!$E:$E,$B40,data!$H:$H,ПФ2026!X$5) -> 0 | Y40: =SUMIFS(data!$G:$G,data!$C:$C,$B$31,data!$D:$D,$B$38,data!$F:$F,Y$4,data!$E:$E,$B40,data!$H:$H,ПФ2026!Y$5) -> 0 | Z40: =SUMIFS(data!$G:$G,data!$C:$C,$B$31,data!$D:$D,$B$38,data!$F:$F,Y$4,data!$E:$E,$B40,data!$H:$H,ПФ2026!Z$5) -> 0 | AA40: =SUM(C40,E40,G40,I40,K40,M40,O100,O40,Q40,S40,Y40,W40,U40) -> 0 | AB40: =D40+F40+H40+J40+L40+N40+P40+R40+T40+V40+X40+Z40 -> 0 | AC40: =IFERROR(AB40/AA40,0) -> 0
B41: Расходы по ком.услуга | C41: =SUM(C42:C46) -> -2030912 | D41: =SUM(D42:D46) -> -2926686.3 | E41: =SUM(E42:E46) -> -997592.08 | F41: =SUM(F42:F46) -> -2693727.1 | G41: =SUM(G42:G46) -> -2234379.7 | H41: =SUM(H42:H46) -> -2950395.5 | I41: =SUM(I42:I46) -> -2036260.4 | J41: =SUM(J42:J46) -> -2626929.8 | ... Z41: =SUM(Z42:Z46) -> 0 | AA41: =SUM(C41,E41,G41,I41,K41,M41,O101,O41,Q41,S41,Y41,W41,U41) -> -37323913 | AB41: =D41+F41+H41+J41+L41+N41+P41+R41+T41+V41+X41+Z41 -> -19097125 | AC41: =IFERROR(AB41/AA41,0) -> 0.51165923
B42: Вода, стоки и канализация | C42: =SUMIFS(data!$G:$G,data!$C:$C,$B$31,data!$D:$D,$B$41,data!$F:$F,C$4,data!$E:$E,$B42,data!$H:$H,ПФ2026!C$5) -> -202637.72 | D42: =SUMIFS(data!$G:$G,data!$C:$C,$B$31,data!$D:$D,$B$41,data!$F:$F,C$4,data!$E:$E,$B42,data!$H:$H,ПФ2026!D$5) -> -551184.3 | E42: =SUMIFS(data!$G:$G,data!$C:$C,$B$31,data!$D:$D,$B$41,data!$F:$F,E$4,data!$E:$E,$B42,data!$H:$H,ПФ2026!E$5) -> -345654.5 | F42: =SUMIFS(data!$G:$G,data!$C:$C,$B$31,data!$D:$D,$B$41,data!$F:$F,E$4,data!$E:$E,$B42,data!$H:$H,ПФ2026!F$5) -> -509327.61 | G42: =SUMIFS(data!$G:$G,data!$C:$C,$B$31,data!$D:$D,$B$41,data!$F:$F,G$4,data!$E:$E,$B42,data!$H:$H,ПФ2026!G$5) -> -160473.48 | H42: =SUMIFS(data!$G:$G,data!$C:$C,$B$31,data!$D:$D,$B$41,data!$F:$F,G$4,data!$E:$E,$B42,data!$H:$H,ПФ2026!H$5) -> -513520.41 | I42: =SUMIFS(data!$G:$G,data!$C:$C,$B$31,data!$D:$D,$B$41,data!$F:$F,I$4,data!$E:$E,$B42,data!$H:$H,ПФ2026!I$5) -> -99803.987 | J42: =SUMIFS(data!$G:$G,data!$C:$C,$B$31,data!$D:$D,$B$41,data!$F:$F,I$4,data!$E:$E,$B42,data!$H:$H,ПФ2026!J$5) -> -584682.06 | K42: =SUMIFS(data!$G:$G,data!$C:$C,$B$31,data!$D:$D,$B$41,data!$F:$F,K$4,data!$E:$E,$B42,data!$H:$H,ПФ2026!K$5) -> -304997.54 | L42: =SUMIFS(data!$G:$G,data!$C:$C,$B$31,data!$D:$D,$B$41,data!$F:$F,K$4,data!$E:$E,$B42,data!$H:$H,ПФ2026!L$5) -> -800103.02 | M42: =SUMIFS(data!$G:$G,data!$C:$C,$B$31,data!$D:$D,$B$41,data!$F:$F,M$4,data!$E:$E,$B42,data!$H:$H,ПФ2026!M$5) -> -1238969.3 | N42: =SUMIFS(data!$G:$G,data!$C:$C,$B$31,data!$D:$D,$B$41,data!$F:$F,M$4,data!$E:$E,$B42,data!$H:$H,ПФ2026!N$5) -> -831269.16 | O42: =SUMIFS(data!$G:$G,data!$C:$C,$B$31,data!$D:$D,$B$41,data!$F:$F,O$4,data!$E:$E,$B42,data!$H:$H,ПФ2026!O$5) -> -836118.98 | P42: =SUMIFS(data!$G:$G,data!$C:$C,$B$31,data!$D:$D,$B$41,data!$F:$F,O$4,data!$E:$E,$B42,data!$H:$H,ПФ2026!P$5) -> 0 | Q42: =SUMIFS(data!$G:$G,data!$C:$C,$B$31,data!$D:$D,$B$41,data!$F:$F,Q$4,data!$E:$E,$B42,data!$H:$H,ПФ2026!Q$5) -> -758413.89 | R42: =SUMIFS(data!$G:$G,data!$C:$C,$B$31,data!$D:$D,$B$41,data!$F:$F,Q$4,data!$E:$E,$B42,data!$H:$H,ПФ2026!R$5) -> 0 | S42: =SUMIFS(data!$G:$G,data!$C:$C,$B$31,data!$D:$D,$B$41,data!$F:$F,S$4,data!$E:$E,$B42,data!$H:$H,ПФ2026!S$5) -> -1350787.7 | T42: =SUMIFS(data!$G:$G,data!$C:$C,$B$31,data!$D:$D,$B$41,data!$F:$F,S$4,data!$E:$E,$B42,data!$H:$H,ПФ2026!T$5) -> 0 | U42: =SUMIFS(data!$G:$G,data!$C:$C,$B$31,data!$D:$D,$B$41,data!$F:$F,U$4,data!$E:$E,$B42,data!$H:$H,ПФ2026!U$5) -> -826806.31 | V42: =SUMIFS(data!$G:$G,data!$C:$C,$B$31,data!$D:$D,$B$41,data!$F:$F,U$4,data!$E:$E,$B42,data!$H:$H,ПФ2026!V$5) -> 0 | W42: =SUMIFS(data!$G:$G,data!$C:$C,$B$31,data!$D:$D,$B$41,data!$F:$F,W$4,data!$E:$E,$B42,data!$H:$H,ПФ2026!W$5) -> -816432.41 | X42: =SUMIFS(data!$G:$G,data!$C:$C,$B$31,data!$D:$D,$B$41,data!$F:$F,W$4,data!$E:$E,$B42,data!$H:$H,ПФ2026!X$5) -> 0 | Y42: =SUMIFS(data!$G:$G,data!$C:$C,$B$31,data!$D:$D,$B$41,data!$F:$F,Y$4,data!$E:$E,$B42,data!$H:$H,ПФ2026!Y$5) -> -561281.61 | Z42: =SUMIFS(data!$G:$G,data!$C:$C,$B$31,data!$D:$D,$B$41,data!$F:$F,Y$4,data!$E:$E,$B42,data!$H:$H,ПФ2026!Z$5) -> 0 | AA42: =SUM(C42,E42,G42,I42,K42,M42,O102,O42,Q42,S42,Y42,W42,U42) -> -7502377.5 | AB42: =D42+F42+H42+J42+L42+N42+P42+R42+T42+V42+X42+Z42 -> -3790086.6 | AC42: =IFERROR(AB42/AA42,0) -> 0.50518473
B43: Вывоз мусора | C43: =SUMIFS(data!$G:$G,data!$C:$C,$B$31,data!$D:$D,$B$41,data!$F:$F,C$4,data!$E:$E,$B43,data!$H:$H,ПФ2026!C$5) -> -208352.4 | D43: =SUMIFS(data!$G:$G,data!$C:$C,$B$31,data!$D:$D,$B$41,data!$F:$F,C$4,data!$E:$E,$B43,data!$H:$H,ПФ2026!D$5) -> -248330.06 | E43: =SUMIFS(data!$G:$G,data!$C:$C,$B$31,data!$D:$D,$B$41,data!$F:$F,E$4,data!$E:$E,$B43,data!$H:$H,ПФ2026!E$5) -> -56877.211 | F43: =SUMIFS(data!$G:$G,data!$C:$C,$B$31,data!$D:$D,$B$41,data!$F:$F,E$4,data!$E:$E,$B43,data!$H:$H,ПФ2026!F$5) -> -314450.06 | G43: =SUMIFS(data!$G:$G,data!$C:$C,$B$31,data!$D:$D,$B$41,data!$F:$F,G$4,data!$E:$E,$B43,data!$H:$H,ПФ2026!G$5) -> -387915.9 | H43: =SUMIFS(data!$G:$G,data!$C:$C,$B$31,data!$D:$D,$B$41,data!$F:$F,G$4,data!$E:$E,$B43,data!$H:$H,ПФ2026!H$5) -> -258320.06 | I43: =SUMIFS(data!$G:$G,data!$C:$C,$B$31,data!$D:$D,$B$41,data!$F:$F,I$4,data!$E:$E,$B43,data!$H:$H,ПФ2026!I$5) -> -274813.62 | J43: =SUMIFS(data!$G:$G,data!$C:$C,$B$31,data!$D:$D,$B$41,data!$F:$F,I$4,data!$E:$E,$B43,data!$H:$H,ПФ2026!J$5) -> -132718.61 | K43: =SUMIFS(data!$G:$G,data!$C:$C,$B$31,data!$D:$D,$B$41,data!$F:$F,K$4,data!$E:$E,$B43,data!$H:$H,ПФ2026!K$5) -> -327546.63 | L43: =SUMIFS(data!$G:$G,data!$C:$C,$B$31,data!$D:$D,$B$41,data!$F:$F,K$4,data!$E:$E,$B43,data!$H:$H,ПФ2026!L$5) -> -394360.61 | M43: =SUMIFS(data!$G:$G,data!$C:$C,$B$31,data!$D:$D,$B$41,data!$F:$F,M$4,data!$E:$E,$B43,data!$H:$H,ПФ2026!M$5) -> -317351.11 | N43: =SUMIFS(data!$G:$G,data!$C:$C,$B$31,data!$D:$D,$B$41,data!$F:$F,M$4,data!$E:$E,$B43,data!$H:$H,ПФ2026!N$5) -> -320208.61 | O43: =SUMIFS(data!$G:$G,data!$C:$C,$B$31,data!$D:$D,$B$41,data!$F:$F,O$4,data!$E:$E,$B43,data!$H:$H,ПФ2026!O$5) -> -291862.3 | P43: =SUMIFS(data!$G:$G,data!$C:$C,$B$31,data!$D:$D,$B$41,data!$F:$F,O$4,data!$E:$E,$B43,data!$H:$H,ПФ2026!P$5) -> 0 | Q43: =SUMIFS(data!$G:$G,data!$C:$C,$B$31,data!$D:$D,$B$41,data!$F:$F,Q$4,data!$E:$E,$B43,data!$H:$H,ПФ2026!Q$5) -> -319899.98 | R43: =SUMIFS(data!$G:$G,data!$C:$C,$B$31,data!$D:$D,$B$41,data!$F:$F,Q$4,data!$E:$E,$B43,data!$H:$H,ПФ2026!R$5) -> 0 | S43: =SUMIFS(data!$G:$G,data!$C:$C,$B$31,data!$D:$D,$B$41,data!$F:$F,S$4,data!$E:$E,$B43,data!$H:$H,ПФ2026!S$5) -> -1298592.7 | T43: =SUMIFS(data!$G:$G,data!$C:$C,$B$31,data!$D:$D,$B$41,data!$F:$F,S$4,data!$E:$E,$B43,data!$H:$H,ПФ2026!T$5) -> 0 | U43: =SUMIFS(data!$G:$G,data!$C:$C,$B$31,data!$D:$D,$B$41,data!$F:$F,U$4,data!$E:$E,$B43,data!$H:$H,ПФ2026!U$5) -> -460996 | V43: =SUMIFS(data!$G:$G,data!$C:$C,$B$31,data!$D:$D,$B$41,data!$F:$F,U$4,data!$E:$E,$B43,data!$H:$H,ПФ2026!V$5) -> 0 | W43: =SUMIFS(data!$G:$G,data!$C:$C,$B$31,data!$D:$D,$B$41,data!$F:$F,W$4,data!$E:$E,$B43,data!$H:$H,ПФ2026!W$5) -> -403248.06 | X43: =SUMIFS(data!$G:$G,data!$C:$C,$B$31,data!$D:$D,$B$41,data!$F:$F,W$4,data!$E:$E,$B43,data!$H:$H,ПФ2026!X$5) -> 0 | Y43: =SUMIFS(data!$G:$G,data!$C:$C,$B$31,data!$D:$D,$B$41,data!$F:$F,Y$4,data!$E:$E,$B43,data!$H:$H,ПФ2026!Y$5) -> -480626.06 | Z43: =SUMIFS(data!$G:$G,data!$C:$C,$B$31,data!$D:$D,$B$41,data!$F:$F,Y$4,data!$E:$E,$B43,data!$H:$H,ПФ2026!Z$5) -> 0 | AA43: =SUM(C43,E43,G43,I43,K43,M43,O103,O43,Q43,S43,Y43,W43,U43) -> -4828082 | AB43: =D43+F43+H43+J43+L43+N43+P43+R43+T43+V43+X43+Z43 -> -1668388 | AC43: =IFERROR(AB43/AA43,0) -> 0.34555917
B44: Информационные услуги (Интернет) | C44: =SUMIFS(data!$G:$G,data!$C:$C,$B$31,data!$D:$D,$B$41,data!$F:$F,C$4,data!$E:$E,$B44,data!$H:$H,ПФ2026!C$5) -> -43602.728 | D44: =SUMIFS(data!$G:$G,data!$C:$C,$B$31,data!$D:$D,$B$41,data!$F:$F,C$4,data!$E:$E,$B44,data!$H:$H,ПФ2026!D$5) -> 0 | E44: =SUMIFS(data!$G:$G,data!$C:$C,$B$31,data!$D:$D,$B$41,data!$F:$F,E$4,data!$E:$E,$B44,data!$H:$H,ПФ2026!E$5) -> -48244.728 | F44: =SUMIFS(data!$G:$G,data!$C:$C,$B$31,data!$D:$D,$B$41,data!$F:$F,E$4,data!$E:$E,$B44,data!$H:$H,ПФ2026!F$5) -> 0 | G44: =SUMIFS(data!$G:$G,data!$C:$C,$B$31,data!$D:$D,$B$41,data!$F:$F,G$4,data!$E:$E,$B44,data!$H:$H,ПФ2026!G$5) -> -45712.728 | H44: =SUMIFS(data!$G:$G,data!$C:$C,$B$31,data!$D:$D,$B$41,data!$F:$F,G$4,data!$E:$E,$B44,data!$H:$H,ПФ2026!H$5) -> 0 | I44: =SUMIFS(data!$G:$G,data!$C:$C,$B$31,data!$D:$D,$B$41,data!$F:$F,I$4,data!$E:$E,$B44,data!$H:$H,ПФ2026!I$5) -> -45712.728 | J44: =SUMIFS(data!$G:$G,data!$C:$C,$B$31,data!$D:$D,$B$41,data!$F:$F,I$4,data!$E:$E,$B44,data!$H:$H,ПФ2026!J$5) -> 0 | K44: =SUMIFS(data!$G:$G,data!$C:$C,$B$31,data!$D:$D,$B$41,data!$F:$F,K$4,data!$E:$E,$B44,data!$H:$H,ПФ2026!K$5) -> -56684.728 | L44: =SUMIFS(data!$G:$G,data!$C:$C,$B$31,data!$D:$D,$B$41,data!$F:$F,K$4,data!$E:$E,$B44,data!$H:$H,ПФ2026!L$5) -> 0 | M44: =SUMIFS(data!$G:$G,data!$C:$C,$B$31,data!$D:$D,$B$41,data!$F:$F,M$4,data!$E:$E,$B44,data!$H:$H,ПФ2026!M$5) -> -66306.328 | N44: =SUMIFS(data!$G:$G,data!$C:$C,$B$31,data!$D:$D,$B$41,data!$F:$F,M$4,data!$E:$E,$B44,data!$H:$H,ПФ2026!N$5) -> 0 | O44: =SUMIFS(data!$G:$G,data!$C:$C,$B$31,data!$D:$D,$B$41,data!$F:$F,O$4,data!$E:$E,$B44,data!$H:$H,ПФ2026!O$5) -> -66306.328 | P44: =SUMIFS(data!$G:$G,data!$C:$C,$B$31,data!$D:$D,$B$41,data!$F:$F,O$4,data!$E:$E,$B44,data!$H:$H,ПФ2026!P$5) -> 0 | Q44: =SUMIFS(data!$G:$G,data!$C:$C,$B$31,data!$D:$D,$B$41,data!$F:$F,Q$4,data!$E:$E,$B44,data!$H:$H,ПФ2026!Q$5) -> -66306.328 | R44: =SUMIFS(data!$G:$G,data!$C:$C,$B$31,data!$D:$D,$B$41,data!$F:$F,Q$4,data!$E:$E,$B44,data!$H:$H,ПФ2026!R$5) -> 0 | S44: =SUMIFS(data!$G:$G,data!$C:$C,$B$31,data!$D:$D,$B$41,data!$F:$F,S$4,data!$E:$E,$B44,data!$H:$H,ПФ2026!S$5) -> -164769.06 | T44: =SUMIFS(data!$G:$G,data!$C:$C,$B$31,data!$D:$D,$B$41,data!$F:$F,S$4,data!$E:$E,$B44,data!$H:$H,ПФ2026!T$5) -> 0 | U44: =SUMIFS(data!$G:$G,data!$C:$C,$B$31,data!$D:$D,$B$41,data!$F:$F,U$4,data!$E:$E,$B44,data!$H:$H,ПФ2026!U$5) -> -118019.3 | V44: =SUMIFS(data!$G:$G,data!$C:$C,$B$31,data!$D:$D,$B$41,data!$F:$F,U$4,data!$E:$E,$B44,data!$H:$H,ПФ2026!V$5) -> 0 | W44: =SUMIFS(data!$G:$G,data!$C:$C,$B$31,data!$D:$D,$B$41,data!$F:$F,W$4,data!$E:$E,$B44,data!$H:$H,ПФ2026!W$5) -> -117982.93 | X44: =SUMIFS(data!$G:$G,data!$C:$C,$B$31,data!$D:$D,$B$41,data!$F:$F,W$4,data!$E:$E,$B44,data!$H:$H,ПФ2026!X$5) -> 0 | Y44: =SUMIFS(data!$G:$G,data!$C:$C,$B$31,data!$D:$D,$B$41,data!$F:$F,Y$4,data!$E:$E,$B44,data!$H:$H,ПФ2026!Y$5) -> -117982.93 | Z44: =SUMIFS(data!$G:$G,data!$C:$C,$B$31,data!$D:$D,$B$41,data!$F:$F,Y$4,data!$E:$E,$B44,data!$H:$H,ПФ2026!Z$5) -> 0 | AA44: =SUM(C44,E44,G44,I44,K44,M44,O105,O44,Q44,S44,Y44,W44,U44) -> -957630.84 | AB44: =D44+F44+H44+J44+L44+N44+P44+R44+T44+V44+X44+Z44 -> 0 | AC44: =IFERROR(AB44/AA44,0) -> 0
B45: Услуги телефонной связи | C45: =SUMIFS(data!$G:$G,data!$C:$C,$B$31,data!$D:$D,$B$41,data!$F:$F,C$4,data!$E:$E,$B45,data!$H:$H,ПФ2026!C$5) -> -15924.457 | D45: =SUMIFS(data!$G:$G,data!$C:$C,$B$31,data!$D:$D,$B$41,data!$F:$F,C$4,data!$E:$E,$B45,data!$H:$H,ПФ2026!D$5) -> -45274.76 | E45: =SUMIFS(data!$G:$G,data!$C:$C,$B$31,data!$D:$D,$B$41,data!$F:$F,E$4,data!$E:$E,$B45,data!$H:$H,ПФ2026!E$5) -> -15870.998 | F45: =SUMIFS(data!$G:$G,data!$C:$C,$B$31,data!$D:$D,$B$41,data!$F:$F,E$4,data!$E:$E,$B45,data!$H:$H,ПФ2026!F$5) -> -19054.76 | G45: =SUMIFS(data!$G:$G,data!$C:$C,$B$31,data!$D:$D,$B$41,data!$F:$F,G$4,data!$E:$E,$B45,data!$H:$H,ПФ2026!G$5) -> -16010.148 | H45: =SUMIFS(data!$G:$G,data!$C:$C,$B$31,data!$D:$D,$B$41,data!$F:$F,G$4,data!$E:$E,$B45,data!$H:$H,ПФ2026!H$5) -> -19639.76 | I45: =SUMIFS(data!$G:$G,data!$C:$C,$B$31,data!$D:$D,$B$41,data!$F:$F,I$4,data!$E:$E,$B45,data!$H:$H,ПФ2026!I$5) -> -16856.056 | J45: =SUMIFS(data!$G:$G,data!$C:$C,$B$31,data!$D:$D,$B$41,data!$F:$F,I$4,data!$E:$E,$B45,data!$H:$H,ПФ2026!J$5) -> -30684.63 | K45: =SUMIFS(data!$G:$G,data!$C:$C,$B$31,data!$D:$D,$B$41,data!$F:$F,K$4,data!$E:$E,$B45,data!$H:$H,ПФ2026!K$5) -> -17214.773 | L45: =SUMIFS(data!$G:$G,data!$C:$C,$B$31,data!$D:$D,$B$41,data!$F:$F,K$4,data!$E:$E,$B45,data!$H:$H,ПФ2026!L$5) -> -31562.14 | M45: =SUMIFS(data!$G:$G,data!$C:$C,$B$31,data!$D:$D,$B$41,data!$F:$F,M$4,data!$E:$E,$B45,data!$H:$H,ПФ2026!M$5) -> -16949.318 | N45: =SUMIFS(data!$G:$G,data!$C:$C,$B$31,data!$D:$D,$B$41,data!$F:$F,M$4,data!$E:$E,$B45,data!$H:$H,ПФ2026!N$5) -> -31929.52 | O45: =SUMIFS(data!$G:$G,data!$C:$C,$B$31,data!$D:$D,$B$41,data!$F:$F,O$4,data!$E:$E,$B45,data!$H:$H,ПФ2026!O$5) -> -17057.763 | P45: =SUMIFS(data!$G:$G,data!$C:$C,$B$31,data!$D:$D,$B$41,data!$F:$F,O$4,data!$E:$E,$B45,data!$H:$H,ПФ2026!P$5) -> 0 | Q45: =SUMIFS(data!$G:$G,data!$C:$C,$B$31,data!$D:$D,$B$41,data!$F:$F,Q$4,data!$E:$E,$B45,data!$H:$H,ПФ2026!Q$5) -> -16824.895 | R45: =SUMIFS(data!$G:$G,data!$C:$C,$B$31,data!$D:$D,$B$41,data!$F:$F,Q$4,data!$E:$E,$B45,data!$H:$H,ПФ2026!R$5) -> 0 | S45: =SUMIFS(data!$G:$G,data!$C:$C,$B$31,data!$D:$D,$B$41,data!$F:$F,S$4,data!$E:$E,$B45,data!$H:$H,ПФ2026!S$5) -> -27072.439 | T45: =SUMIFS(data!$G:$G,data!$C:$C,$B$31,data!$D:$D,$B$41,data!$F:$F,S$4,data!$E:$E,$B45,data!$H:$H,ПФ2026!T$5) -> 0 | U45: =SUMIFS(data!$G:$G,data!$C:$C,$B$31,data!$D:$D,$B$41,data!$F:$F,U$4,data!$E:$E,$B45,data!$H:$H,ПФ2026!U$5) -> -29066.329 | V45: =SUMIFS(data!$G:$G,data!$C:$C,$B$31,data!$D:$D,$B$41,data!$F:$F,U$4,data!$E:$E,$B45,data!$H:$H,ПФ2026!V$5) -> 0 | W45: =SUMIFS(data!$G:$G,data!$C:$C,$B$31,data!$D:$D,$B$41,data!$F:$F,W$4,data!$E:$E,$B45,data!$H:$H,ПФ2026!W$5) -> -28419.318 | X45: =SUMIFS(data!$G:$G,data!$C:$C,$B$31,data!$D:$D,$B$41,data!$F:$F,W$4,data!$E:$E,$B45,data!$H:$H,ПФ2026!X$5) -> 0 | Y45: =SUMIFS(data!$G:$G,data!$C:$C,$B$31,data!$D:$D,$B$41,data!$F:$F,Y$4,data!$E:$E,$B45,data!$H:$H,ПФ2026!Y$5) -> -28588.447 | Z45: =SUMIFS(data!$G:$G,data!$C:$C,$B$31,data!$D:$D,$B$41,data!$F:$F,Y$4,data!$E:$E,$B45,data!$H:$H,ПФ2026!Z$5) -> 0 | AA45: =SUM(C45,E45,G45,I45,K45,M45,O106,O45,Q45,S45,Y45,W45,U45) -> -245854.94 | AB45: =D45+F45+H45+J45+L45+N45+P45+R45+T45+V45+X45+Z45 -> -178145.57 | AC45: =IFERROR(AB45/AA45,0) -> 0.72459626
B46: Электроэнергия | C46: =SUMIFS(data!$G:$G,data!$C:$C,$B$31,data!$D:$D,$B$41,data!$F:$F,C$4,data!$E:$E,$B46,data!$H:$H,ПФ2026!C$5) -> -1560394.7 | D46: =SUMIFS(data!$G:$G,data!$C:$C,$B$31,data!$D:$D,$B$41,data!$F:$F,C$4,data!$E:$E,$B46,data!$H:$H,ПФ2026!D$5) -> -2081897.1 | E46: =SUMIFS(data!$G:$G,data!$C:$C,$B$31,data!$D:$D,$B$41,data!$F:$F,E$4,data!$E:$E,$B46,data!$H:$H,ПФ2026!E$5) -> -530944.64 | F46: =SUMIFS(data!$G:$G,data!$C:$C,$B$31,data!$D:$D,$B$41,data!$F:$F,E$4,data!$E:$E,$B46,data!$H:$H,ПФ2026!F$5) -> -1850894.7 | G46: =SUMIFS(data!$G:$G,data!$C:$C,$B$31,data!$D:$D,$B$41,data!$F:$F,G$4,data!$E:$E,$B46,data!$H:$H,ПФ2026!G$5) -> -1624267.4 | H46: =SUMIFS(data!$G:$G,data!$C:$C,$B$31,data!$D:$D,$B$41,data!$F:$F,G$4,data!$E:$E,$B46,data!$H:$H,ПФ2026!H$5) -> -2158915.3 | I46: =SUMIFS(data!$G:$G,data!$C:$C,$B$31,data!$D:$D,$B$41,data!$F:$F,I$4,data!$E:$E,$B46,data!$H:$H,ПФ2026!I$5) -> -1599074 | J46: =SUMIFS(data!$G:$G,data!$C:$C,$B$31,data!$D:$D,$B$41,data!$F:$F,I$4,data!$E:$E,$B46,data!$H:$H,ПФ2026!J$5) -> -1878844.5 | K46: =SUMIFS(data!$G:$G,data!$C:$C,$B$31,data!$D:$D,$B$41,data!$F:$F,K$4,data!$E:$E,$B46,data!$H:$H,ПФ2026!K$5) -> -2085132.9 | L46: =SUMIFS(data!$G:$G,data!$C:$C,$B$31,data!$D:$D,$B$41,data!$F:$F,K$4,data!$E:$E,$B46,data!$H:$H,ПФ2026!L$5) -> -2553149.1 | M46: =SUMIFS(data!$G:$G,data!$C:$C,$B$31,data!$D:$D,$B$41,data!$F:$F,M$4,data!$E:$E,$B46,data!$H:$H,ПФ2026!M$5) -> -2085932 | N46: =SUMIFS(data!$G:$G,data!$C:$C,$B$31,data!$D:$D,$B$41,data!$F:$F,M$4,data!$E:$E,$B46,data!$H:$H,ПФ2026!N$5) -> -2936803.7 | O46: =SUMIFS(data!$G:$G,data!$C:$C,$B$31,data!$D:$D,$B$41,data!$F:$F,O$4,data!$E:$E,$B46,data!$H:$H,ПФ2026!O$5) -> -2454430.9 | P46: =SUMIFS(data!$G:$G,data!$C:$C,$B$31,data!$D:$D,$B$41,data!$F:$F,O$4,data!$E:$E,$B46,data!$H:$H,ПФ2026!P$5) -> 0 | Q46: =SUMIFS(data!$G:$G,data!$C:$C,$B$31,data!$D:$D,$B$41,data!$F:$F,Q$4,data!$E:$E,$B46,data!$H:$H,ПФ2026!Q$5) -> -2104117.6 | R46: =SUMIFS(data!$G:$G,data!$C:$C,$B$31,data!$D:$D,$B$41,data!$F:$F,Q$4,data!$E:$E,$B46,data!$H:$H,ПФ2026!R$5) -> 0 | S46: =SUMIFS(data!$G:$G,data!$C:$C,$B$31,data!$D:$D,$B$41,data!$F:$F,S$4,data!$E:$E,$B46,data!$H:$H,ПФ2026!S$5) -> -3103044 | T46: =SUMIFS(data!$G:$G,data!$C:$C,$B$31,data!$D:$D,$B$41,data!$F:$F,S$4,data!$E:$E,$B46,data!$H:$H,ПФ2026!T$5) -> 0 | U46: =SUMIFS(data!$G:$G,data!$C:$C,$B$31,data!$D:$D,$B$41,data!$F:$F,U$4,data!$E:$E,$B46,data!$H:$H,ПФ2026!U$5) -> -2291658.7 | V46: =SUMIFS(data!$G:$G,data!$C:$C,$B$31,data!$D:$D,$B$41,data!$F:$F,U$4,data!$E:$E,$B46,data!$H:$H,ПФ2026!V$5) -> 0 | W46: =SUMIFS(data!$G:$G,data!$C:$C,$B$31,data!$D:$D,$B$41,data!$F:$F,W$4,data!$E:$E,$B46,data!$H:$H,ПФ2026!W$5) -> -2180338.2 | X46: =SUMIFS(data!$G:$G,data!$C:$C,$B$31,data!$D:$D,$B$41,data!$F:$F,W$4,data!$E:$E,$B46,data!$H:$H,ПФ2026!X$5) -> 0 | Y46: =SUMIFS(data!$G:$G,data!$C:$C,$B$31,data!$D:$D,$B$41,data!$F:$F,Y$4,data!$E:$E,$B46,data!$H:$H,ПФ2026!Y$5) -> -2170632.4 | Z46: =SUMIFS(data!$G:$G,data!$C:$C,$B$31,data!$D:$D,$B$41,data!$F:$F,Y$4,data!$E:$E,$B46,data!$H:$H,ПФ2026!Z$5) -> 0 | AA46: =SUM(C46,E46,G46,I46,K46,M46,O107,O46,Q46,S46,Y46,W46,U46) -> -23856968 | AB46: =D46+F46+H46+J46+L46+N46+P46+R46+T46+V46+X46+Z46 -> -13460504 | AC46: =IFERROR(AB46/AA46,0) -> 0.56421691
B47: Расходы по оплате труда | C47: =SUM(C48:C57) -> -43321224 | D47: =SUM(D48:D57) -> -49069578 | E47: =SUM(E48:E57) -> -43785291 | F47: =SUM(F48:F57) -> -52917356 | G47: =SUM(G48:G57) -> -52778128 | H47: =SUM(H48:H57) -> -64890230 | I47: =SUM(I48:I57) -> -72569363 | J47: =SUM(J48:J57) -> -87740454 | ... Z47: =SUM(Z48:Z57) -> 0 | AA47: =SUM(C47,E47,G47,I47,K47,M47,O108,O47,Q47,S47,Y47,W47,U47) -> -728757886 | AB47: =D47+F47+H47+J47+L47+N47+P47+R47+T47+V47+X47+Z47 -> -4.4873695e+08 | AC47: =IFERROR(AB47/AA47,0) -> 0.61575587
B48: Департамент логистики и транспорта | C48: =SUMIFS(data!$G:$G,data!$C:$C,$B$31,data!$D:$D,$B$47,data!$F:$F,C$4,data!$E:$E,$B48,data!$H:$H,ПФ2026!C$5) -> -12468727 | D48: =SUMIFS(data!$G:$G,data!$C:$C,$B$31,data!$D:$D,$B$47,data!$F:$F,C$4,data!$E:$E,$B48,data!$H:$H,ПФ2026!D$5) -> -16383321 | E48: =SUMIFS(data!$G:$G,data!$C:$C,$B$31,data!$D:$D,$B$47,data!$F:$F,E$4,data!$E:$E,$B48,data!$H:$H,ПФ2026!E$5) -> -12868070 | F48: =SUMIFS(data!$G:$G,data!$C:$C,$B$31,data!$D:$D,$B$47,data!$F:$F,E$4,data!$E:$E,$B48,data!$H:$H,ПФ2026!F$5) -> -18409546 | G48: =SUMIFS(data!$G:$G,data!$C:$C,$B$31,data!$D:$D,$B$47,data!$F:$F,G$4,data!$E:$E,$B48,data!$H:$H,ПФ2026!G$5) -> -15995056 | H48: =SUMIFS(data!$G:$G,data!$C:$C,$B$31,data!$D:$D,$B$47,data!$F:$F,G$4,data!$E:$E,$B48,data!$H:$H,ПФ2026!H$5) -> -21830179 | I48: =SUMIFS(data!$G:$G,data!$C:$C,$B$31,data!$D:$D,$B$47,data!$F:$F,I$4,data!$E:$E,$B48,data!$H:$H,ПФ2026!I$5) -> -18343080 | J48: =SUMIFS(data!$G:$G,data!$C:$C,$B$31,data!$D:$D,$B$47,data!$F:$F,I$4,data!$E:$E,$B48,data!$H:$H,ПФ2026!J$5) -> -25162851 | K48: =SUMIFS(data!$G:$G,data!$C:$C,$B$31,data!$D:$D,$B$47,data!$F:$F,K$4,data!$E:$E,$B48,data!$H:$H,ПФ2026!K$5) -> -19532454 | L48: =SUMIFS(data!$G:$G,data!$C:$C,$B$31,data!$D:$D,$B$47,data!$F:$F,K$4,data!$E:$E,$B48,data!$H:$H,ПФ2026!L$5) -> -26232325 | M48: =SUMIFS(data!$G:$G,data!$C:$C,$B$31,data!$D:$D,$B$47,data!$F:$F,M$4,data!$E:$E,$B48,data!$H:$H,ПФ2026!M$5) -> -19744667 | N48: =SUMIFS(data!$G:$G,data!$C:$C,$B$31,data!$D:$D,$B$47,data!$F:$F,M$4,data!$E:$E,$B48,data!$H:$H,ПФ2026!N$5) -> -29635697 | O48: =SUMIFS(data!$G:$G,data!$C:$C,$B$31,data!$D:$D,$B$47,data!$F:$F,O$4,data!$E:$E,$B48,data!$H:$H,ПФ2026!O$5) -> -20437695 | P48: =SUMIFS(data!$G:$G,data!$C:$C,$B$31,data!$D:$D,$B$47,data!$F:$F,O$4,data!$E:$E,$B48,data!$H:$H,ПФ2026!P$5) -> 0 | Q48: =SUMIFS(data!$G:$G,data!$C:$C,$B$31,data!$D:$D,$B$47,data!$F:$F,Q$4,data!$E:$E,$B48,data!$H:$H,ПФ2026!Q$5) -> -19859261 | R48: =SUMIFS(data!$G:$G,data!$C:$C,$B$31,data!$D:$D,$B$47,data!$F:$F,Q$4,data!$E:$E,$B48,data!$H:$H,ПФ2026!R$5) -> 0 | S48: =SUMIFS(data!$G:$G,data!$C:$C,$B$31,data!$D:$D,$B$47,data!$F:$F,S$4,data!$E:$E,$B48,data!$H:$H,ПФ2026!S$5) -> -18093222 | T48: =SUMIFS(data!$G:$G,data!$C:$C,$B$31,data!$D:$D,$B$47,data!$F:$F,S$4,data!$E:$E,$B48,data!$H:$H,ПФ2026!T$5) -> 0 | U48: =SUMIFS(data!$G:$G,data!$C:$C,$B$31,data!$D:$D,$B$47,data!$F:$F,U$4,data!$E:$E,$B48,data!$H:$H,ПФ2026!U$5) -> -15047370 | V48: =SUMIFS(data!$G:$G,data!$C:$C,$B$31,data!$D:$D,$B$47,data!$F:$F,U$4,data!$E:$E,$B48,data!$H:$H,ПФ2026!V$5) -> 0 | W48: =SUMIFS(data!$G:$G,data!$C:$C,$B$31,data!$D:$D,$B$47,data!$F:$F,W$4,data!$E:$E,$B48,data!$H:$H,ПФ2026!W$5) -> -13319058 | X48: =SUMIFS(data!$G:$G,data!$C:$C,$B$31,data!$D:$D,$B$47,data!$F:$F,W$4,data!$E:$E,$B48,data!$H:$H,ПФ2026!X$5) -> 0 | Y48: =SUMIFS(data!$G:$G,data!$C:$C,$B$31,data!$D:$D,$B$47,data!$F:$F,Y$4,data!$E:$E,$B48,data!$H:$H,ПФ2026!Y$5) -> -13174506 | Z48: =SUMIFS(data!$G:$G,data!$C:$C,$B$31,data!$D:$D,$B$47,data!$F:$F,Y$4,data!$E:$E,$B48,data!$H:$H,ПФ2026!Z$5) -> 0 | AA48: =SUM(C48,E48,G48,I48,K48,M48,O109,O48,Q48,S48,Y48,W48,U48) -> -198883166 | AB48: =D48+F48+H48+J48+L48+N48+P48+R48+T48+V48+X48+Z48 -> -1.3765392e+08 | AC48: =IFERROR(AB48/AA48,0) -> 0.6921346
B49: Департамент производства | C49: =SUMIFS(data!$G:$G,data!$C:$C,$B$31,data!$D:$D,$B$47,data!$F:$F,C$4,data!$E:$E,$B49,data!$H:$H,ПФ2026!C$5) -> -2729600 | D49: =SUMIFS(data!$G:$G,data!$C:$C,$B$31,data!$D:$D,$B$47,data!$F:$F,C$4,data!$E:$E,$B49,data!$H:$H,ПФ2026!D$5) -> -2979531.9 | E49: =SUMIFS(data!$G:$G,data!$C:$C,$B$31,data!$D:$D,$B$47,data!$F:$F,E$4,data!$E:$E,$B49,data!$H:$H,ПФ2026!E$5) -> -2729600 | F49: =SUMIFS(data!$G:$G,data!$C:$C,$B$31,data!$D:$D,$B$47,data!$F:$F,E$4,data!$E:$E,$B49,data!$H:$H,ПФ2026!F$5) -> -3505220.7 | G49: =SUMIFS(data!$G:$G,data!$C:$C,$B$31,data!$D:$D,$B$47,data!$F:$F,G$4,data!$E:$E,$B49,data!$H:$H,ПФ2026!G$5) -> -2729600 | H49: =SUMIFS(data!$G:$G,data!$C:$C,$B$31,data!$D:$D,$B$47,data!$F:$F,G$4,data!$E:$E,$B49,data!$H:$H,ПФ2026!H$5) -> -3072400.6 | I49: =SUMIFS(data!$G:$G,data!$C:$C,$B$31,data!$D:$D,$B$47,data!$F:$F,I$4,data!$E:$E,$B49,data!$H:$H,ПФ2026!I$5) -> -2976000 | J49: =SUMIFS(data!$G:$G,data!$C:$C,$B$31,data!$D:$D,$B$47,data!$F:$F,I$4,data!$E:$E,$B49,data!$H:$H,ПФ2026!J$5) -> -3481905.7 | K49: =SUMIFS(data!$G:$G,data!$C:$C,$B$31,data!$D:$D,$B$47,data!$F:$F,K$4,data!$E:$E,$B49,data!$H:$H,ПФ2026!K$5) -> -2976000 | L49: =SUMIFS(data!$G:$G,data!$C:$C,$B$31,data!$D:$D,$B$47,data!$F:$F,K$4,data!$E:$E,$B49,data!$H:$H,ПФ2026!L$5) -> -3660851.3 | M49: =SUMIFS(data!$G:$G,data!$C:$C,$B$31,data!$D:$D,$B$47,data!$F:$F,M$4,data!$E:$E,$B49,data!$H:$H,ПФ2026!M$5) -> -2976000 | N49: =SUMIFS(data!$G:$G,data!$C:$C,$B$31,data!$D:$D,$B$47,data!$F:$F,M$4,data!$E:$E,$B49,data!$H:$H,ПФ2026!N$5) -> -3742180.4 | O49: =SUMIFS(data!$G:$G,data!$C:$C,$B$31,data!$D:$D,$B$47,data!$F:$F,O$4,data!$E:$E,$B49,data!$H:$H,ПФ2026!O$5) -> -2976000 | P49: =SUMIFS(data!$G:$G,data!$C:$C,$B$31,data!$D:$D,$B$47,data!$F:$F,O$4,data!$E:$E,$B49,data!$H:$H,ПФ2026!P$5) -> 0 | Q49: =SUMIFS(data!$G:$G,data!$C:$C,$B$31,data!$D:$D,$B$47,data!$F:$F,Q$4,data!$E:$E,$B49,data!$H:$H,ПФ2026!Q$5) -> -2976000 | R49: =SUMIFS(data!$G:$G,data!$C:$C,$B$31,data!$D:$D,$B$47,data!$F:$F,Q$4,data!$E:$E,$B49,data!$H:$H,ПФ2026!R$5) -> 0 | S49: =SUMIFS(data!$G:$G,data!$C:$C,$B$31,data!$D:$D,$B$47,data!$F:$F,S$4,data!$E:$E,$B49,data!$H:$H,ПФ2026!S$5) -> -2976000 | T49: =SUMIFS(data!$G:$G,data!$C:$C,$B$31,data!$D:$D,$B$47,data!$F:$F,S$4,data!$E:$E,$B49,data!$H:$H,ПФ2026!T$5) -> 0 | U49: =SUMIFS(data!$G:$G,data!$C:$C,$B$31,data!$D:$D,$B$47,data!$F:$F,U$4,data!$E:$E,$B49,data!$H:$H,ПФ2026!U$5) -> -2714400 | V49: =SUMIFS(data!$G:$G,data!$C:$C,$B$31,data!$D:$D,$B$47,data!$F:$F,U$4,data!$E:$E,$B49,data!$H:$H,ПФ2026!V$5) -> 0 | W49: =SUMIFS(data!$G:$G,data!$C:$C,$B$31,data!$D:$D,$B$47,data!$F:$F,W$4,data!$E:$E,$B49,data!$H:$H,ПФ2026!W$5) -> -2714400 | X49: =SUMIFS(data!$G:$G,data!$C:$C,$B$31,data!$D:$D,$B$47,data!$F:$F,W$4,data!$E:$E,$B49,data!$H:$H,ПФ2026!X$5) -> 0 | Y49: =SUMIFS(data!$G:$G,data!$C:$C,$B$31,data!$D:$D,$B$47,data!$F:$F,Y$4,data!$E:$E,$B49,data!$H:$H,ПФ2026!Y$5) -> -2714400 | Z49: =SUMIFS(data!$G:$G,data!$C:$C,$B$31,data!$D:$D,$B$47,data!$F:$F,Y$4,data!$E:$E,$B49,data!$H:$H,ПФ2026!Z$5) -> 0 | AA49: =SUM(C49,E49,G49,I49,K49,M49,O110,O49,Q49,S49,Y49,W49,U49) -> -34213000 | AB49: =D49+F49+H49+J49+L49+N49+P49+R49+T49+V49+X49+Z49 -> -20442091 | AC49: =IFERROR(AB49/AA49,0) -> 0.59749483
B50: Департамент управления человеческими ресурсами | C50: =SUMIFS(data!$G:$G,data!$C:$C,$B$31,data!$D:$D,$B$47,data!$F:$F,C$4,data!$E:$E,$B50,data!$H:$H,ПФ2026!C$5) -> -906400 | D50: =SUMIFS(data!$G:$G,data!$C:$C,$B$31,data!$D:$D,$B$47,data!$F:$F,C$4,data!$E:$E,$B50,data!$H:$H,ПФ2026!D$5) -> -1574225.4 | E50: =SUMIFS(data!$G:$G,data!$C:$C,$B$31,data!$D:$D,$B$47,data!$F:$F,E$4,data!$E:$E,$B50,data!$H:$H,ПФ2026!E$5) -> -906400 | F50: =SUMIFS(data!$G:$G,data!$C:$C,$B$31,data!$D:$D,$B$47,data!$F:$F,E$4,data!$E:$E,$B50,data!$H:$H,ПФ2026!F$5) -> -2051843.8 | G50: =SUMIFS(data!$G:$G,data!$C:$C,$B$31,data!$D:$D,$B$47,data!$F:$F,G$4,data!$E:$E,$B50,data!$H:$H,ПФ2026!G$5) -> -906400 | H50: =SUMIFS(data!$G:$G,data!$C:$C,$B$31,data!$D:$D,$B$47,data!$F:$F,G$4,data!$E:$E,$B50,data!$H:$H,ПФ2026!H$5) -> -2139281.7 | I50: =SUMIFS(data!$G:$G,data!$C:$C,$B$31,data!$D:$D,$B$47,data!$F:$F,I$4,data!$E:$E,$B50,data!$H:$H,ПФ2026!I$5) -> -1040800 | J50: =SUMIFS(data!$G:$G,data!$C:$C,$B$31,data!$D:$D,$B$47,data!$F:$F,I$4,data!$E:$E,$B50,data!$H:$H,ПФ2026!J$5) -> -2239315.3 | K50: =SUMIFS(data!$G:$G,data!$C:$C,$B$31,data!$D:$D,$B$47,data!$F:$F,K$4,data!$E:$E,$B50,data!$H:$H,ПФ2026!K$5) -> -1040800 | L50: =SUMIFS(data!$G:$G,data!$C:$C,$B$31,data!$D:$D,$B$47,data!$F:$F,K$4,data!$E:$E,$B50,data!$H:$H,ПФ2026!L$5) -> -2246931.5 | M50: =SUMIFS(data!$G:$G,data!$C:$C,$B$31,data!$D:$D,$B$47,data!$F:$F,M$4,data!$E:$E,$B50,data!$H:$H,ПФ2026!M$5) -> -1040800 | N50: =SUMIFS(data!$G:$G,data!$C:$C,$B$31,data!$D:$D,$B$47,data!$F:$F,M$4,data!$E:$E,$B50,data!$H:$H,ПФ2026!N$5) -> -2658090.8 | O50: =SUMIFS(data!$G:$G,data!$C:$C,$B$31,data!$D:$D,$B$47,data!$F:$F,O$4,data!$E:$E,$B50,data!$H:$H,ПФ2026!O$5) -> -1040800 | P50: =SUMIFS(data!$G:$G,data!$C:$C,$B$31,data!$D:$D,$B$47,data!$F:$F,O$4,data!$E:$E,$B50,data!$H:$H,ПФ2026!P$5) -> 0 | Q50: =SUMIFS(data!$G:$G,data!$C:$C,$B$31,data!$D:$D,$B$47,data!$F:$F,Q$4,data!$E:$E,$B50,data!$H:$H,ПФ2026!Q$5) -> -1040800 | R50: =SUMIFS(data!$G:$G,data!$C:$C,$B$31,data!$D:$D,$B$47,data!$F:$F,Q$4,data!$E:$E,$B50,data!$H:$H,ПФ2026!R$5) -> 0 | S50: =SUMIFS(data!$G:$G,data!$C:$C,$B$31,data!$D:$D,$B$47,data!$F:$F,S$4,data!$E:$E,$B50,data!$H:$H,ПФ2026!S$5) -> -1040800 | T50: =SUMIFS(data!$G:$G,data!$C:$C,$B$31,data!$D:$D,$B$47,data!$F:$F,S$4,data!$E:$E,$B50,data!$H:$H,ПФ2026!T$5) -> 0 | U50: =SUMIFS(data!$G:$G,data!$C:$C,$B$31,data!$D:$D,$B$47,data!$F:$F,U$4,data!$E:$E,$B50,data!$H:$H,ПФ2026!U$5) -> -976800 | V50: =SUMIFS(data!$G:$G,data!$C:$C,$B$31,data!$D:$D,$B$47,data!$F:$F,U$4,data!$E:$E,$B50,data!$H:$H,ПФ2026!V$5) -> 0 | W50: =SUMIFS(data!$G:$G,data!$C:$C,$B$31,data!$D:$D,$B$47,data!$F:$F,W$4,data!$E:$E,$B50,data!$H:$H,ПФ2026!W$5) -> -874400 | X50: =SUMIFS(data!$G:$G,data!$C:$C,$B$31,data!$D:$D,$B$47,data!$F:$F,W$4,data!$E:$E,$B50,data!$H:$H,ПФ2026!X$5) -> 0 | Y50: =SUMIFS(data!$G:$G,data!$C:$C,$B$31,data!$D:$D,$B$47,data!$F:$F,Y$4,data!$E:$E,$B50,data!$H:$H,ПФ2026!Y$5) -> -874400 | Z50: =SUMIFS(data!$G:$G,data!$C:$C,$B$31,data!$D:$D,$B$47,data!$F:$F,Y$4,data!$E:$E,$B50,data!$H:$H,ПФ2026!Z$5) -> 0 | AA50: =SUM(C50,E50,G50,I50,K50,M50,O111,O50,Q50,S50,Y50,W50,U50) -> -11691600 | AB50: =D50+F50+H50+J50+L50+N50+P50+R50+T50+V50+X50+Z50 -> -12909689 | AC50: =IFERROR(AB50/AA50,0) -> 1.1041849
B51: Директорский состав | C51: =SUMIFS(data!$G:$G,data!$C:$C,$B$31,data!$D:$D,$B$47,data!$F:$F,C$4,data!$E:$E,$B51,data!$H:$H,ПФ2026!C$5) -> -2529000 | D51: =SUMIFS(data!$G:$G,data!$C:$C,$B$31,data!$D:$D,$B$47,data!$F:$F,C$4,data!$E:$E,$B51,data!$H:$H,ПФ2026!D$5) -> -3163141.2 | E51: =SUMIFS(data!$G:$G,data!$C:$C,$B$31,data!$D:$D,$B$47,data!$F:$F,E$4,data!$E:$E,$B51,data!$H:$H,ПФ2026!E$5) -> -2529000 | F51: =SUMIFS(data!$G:$G,data!$C:$C,$B$31,data!$D:$D,$B$47,data!$F:$F,E$4,data!$E:$E,$B51,data!$H:$H,ПФ2026!F$5) -> -3271232.5 | G51: =SUMIFS(data!$G:$G,data!$C:$C,$B$31,data!$D:$D,$B$47,data!$F:$F,G$4,data!$E:$E,$B51,data!$H:$H,ПФ2026!G$5) -> -2529000 | H51: =SUMIFS(data!$G:$G,data!$C:$C,$B$31,data!$D:$D,$B$47,data!$F:$F,G$4,data!$E:$E,$B51,data!$H:$H,ПФ2026!H$5) -> -3292550.6 | I51: =SUMIFS(data!$G:$G,data!$C:$C,$B$31,data!$D:$D,$B$47,data!$F:$F,I$4,data!$E:$E,$B51,data!$H:$H,ПФ2026!I$5) -> -2529000 | J51: =SUMIFS(data!$G:$G,data!$C:$C,$B$31,data!$D:$D,$B$47,data!$F:$F,I$4,data!$E:$E,$B51,data!$H:$H,ПФ2026!J$5) -> -4080091.4 | K51: =SUMIFS(data!$G:$G,data!$C:$C,$B$31,data!$D:$D,$B$47,data!$F:$F,K$4,data!$E:$E,$B51,data!$H:$H,ПФ2026!K$5) -> -2529000 | L51: =SUMIFS(data!$G:$G,data!$C:$C,$B$31,data!$D:$D,$B$47,data!$F:$F,K$4,data!$E:$E,$B51,data!$H:$H,ПФ2026!L$5) -> -3326761.8 | M51: =SUMIFS(data!$G:$G,data!$C:$C,$B$31,data!$D:$D,$B$47,data!$F:$F,M$4,data!$E:$E,$B51,data!$H:$H,ПФ2026!M$5) -> -2529000 | N51: =SUMIFS(data!$G:$G,data!$C:$C,$B$31,data!$D:$D,$B$47,data!$F:$F,M$4,data!$E:$E,$B51,data!$H:$H,ПФ2026!N$5) -> -3443379.3 | O51: =SUMIFS(data!$G:$G,data!$C:$C,$B$31,data!$D:$D,$B$47,data!$F:$F,O$4,data!$E:$E,$B51,data!$H:$H,ПФ2026!O$5) -> -2529000 | P51: =SUMIFS(data!$G:$G,data!$C:$C,$B$31,data!$D:$D,$B$47,data!$F:$F,O$4,data!$E:$E,$B51,data!$H:$H,ПФ2026!P$5) -> 0 | Q51: =SUMIFS(data!$G:$G,data!$C:$C,$B$31,data!$D:$D,$B$47,data!$F:$F,Q$4,data!$E:$E,$B51,data!$H:$H,ПФ2026!Q$5) -> -2529000 | R51: =SUMIFS(data!$G:$G,data!$C:$C,$B$31,data!$D:$D,$B$47,data!$F:$F,Q$4,data!$E:$E,$B51,data!$H:$H,ПФ2026!R$5) -> 0 | S51: =SUMIFS(data!$G:$G,data!$C:$C,$B$31,data!$D:$D,$B$47,data!$F:$F,S$4,data!$E:$E,$B51,data!$H:$H,ПФ2026!S$5) -> -2529000 | T51: =SUMIFS(data!$G:$G,data!$C:$C,$B$31,data!$D:$D,$B$47,data!$F:$F,S$4,data!$E:$E,$B51,data!$H:$H,ПФ2026!T$5) -> 0 | U51: =SUMIFS(data!$G:$G,data!$C:$C,$B$31,data!$D:$D,$B$47,data!$F:$F,U$4,data!$E:$E,$B51,data!$H:$H,ПФ2026!U$5) -> -2529000 | V51: =SUMIFS(data!$G:$G,data!$C:$C,$B$31,data!$D:$D,$B$47,data!$F:$F,U$4,data!$E:$E,$B51,data!$H:$H,ПФ2026!V$5) -> 0 | W51: =SUMIFS(data!$G:$G,data!$C:$C,$B$31,data!$D:$D,$B$47,data!$F:$F,W$4,data!$E:$E,$B51,data!$H:$H,ПФ2026!W$5) -> -2529000 | X51: =SUMIFS(data!$G:$G,data!$C:$C,$B$31,data!$D:$D,$B$47,data!$F:$F,W$4,data!$E:$E,$B51,data!$H:$H,ПФ2026!X$5) -> 0 | Y51: =SUMIFS(data!$G:$G,data!$C:$C,$B$31,data!$D:$D,$B$47,data!$F:$F,Y$4,data!$E:$E,$B51,data!$H:$H,ПФ2026!Y$5) -> -2529000 | Z51: =SUMIFS(data!$G:$G,data!$C:$C,$B$31,data!$D:$D,$B$47,data!$F:$F,Y$4,data!$E:$E,$B51,data!$H:$H,ПФ2026!Z$5) -> 0 | AA51: =SUM(C51,E51,G51,I51,K51,M51,O112,O51,Q51,S51,Y51,W51,U51) -> -30348000 | AB51: =D51+F51+H51+J51+L51+N51+P51+R51+T51+V51+X51+Z51 -> -20577157 | AC51: =IFERROR(AB51/AA51,0) -> 0.67803997
B52: Коммерческий департамент | C52: =SUMIFS(data!$G:$G,data!$C:$C,$B$31,data!$D:$D,$B$47,data!$F:$F,C$4,data!$E:$E,$B52,data!$H:$H,ПФ2026!C$5) -> -11628899 | D52: =SUMIFS(data!$G:$G,data!$C:$C,$B$31,data!$D:$D,$B$47,data!$F:$F,C$4,data!$E:$E,$B52,data!$H:$H,ПФ2026!D$5) -> -12638883 | E52: =SUMIFS(data!$G:$G,data!$C:$C,$B$31,data!$D:$D,$B$47,data!$F:$F,E$4,data!$E:$E,$B52,data!$H:$H,ПФ2026!E$5) -> -11651273 | F52: =SUMIFS(data!$G:$G,data!$C:$C,$B$31,data!$D:$D,$B$47,data!$F:$F,E$4,data!$E:$E,$B52,data!$H:$H,ПФ2026!F$5) -> -12914163 | G52: =SUMIFS(data!$G:$G,data!$C:$C,$B$31,data!$D:$D,$B$47,data!$F:$F,G$4,data!$E:$E,$B52,data!$H:$H,ПФ2026!G$5) -> -14782212 | H52: =SUMIFS(data!$G:$G,data!$C:$C,$B$31,data!$D:$D,$B$47,data!$F:$F,G$4,data!$E:$E,$B52,data!$H:$H,ПФ2026!H$5) -> -18903063 | I52: =SUMIFS(data!$G:$G,data!$C:$C,$B$31,data!$D:$D,$B$47,data!$F:$F,I$4,data!$E:$E,$B52,data!$H:$H,ПФ2026!I$5) -> -29495833 | J52: =SUMIFS(data!$G:$G,data!$C:$C,$B$31,data!$D:$D,$B$47,data!$F:$F,I$4,data!$E:$E,$B52,data!$H:$H,ПФ2026!J$5) -> -34721333 | K52: =SUMIFS(data!$G:$G,data!$C:$C,$B$31,data!$D:$D,$B$47,data!$F:$F,K$4,data!$E:$E,$B52,data!$H:$H,ПФ2026!K$5) -> -33909885 | L52: =SUMIFS(data!$G:$G,data!$C:$C,$B$31,data!$D:$D,$B$47,data!$F:$F,K$4,data!$E:$E,$B52,data!$H:$H,ПФ2026!L$5) -> -36346495 | M52: =SUMIFS(data!$G:$G,data!$C:$C,$B$31,data!$D:$D,$B$47,data!$F:$F,M$4,data!$E:$E,$B52,data!$H:$H,ПФ2026!M$5) -> -33452554 | N52: =SUMIFS(data!$G:$G,data!$C:$C,$B$31,data!$D:$D,$B$47,data!$F:$F,M$4,data!$E:$E,$B52,data!$H:$H,ПФ2026!N$5) -> -42993179 | O52: =SUMIFS(data!$G:$G,data!$C:$C,$B$31,data!$D:$D,$B$47,data!$F:$F,O$4,data!$E:$E,$B52,data!$H:$H,ПФ2026!O$5) -> -33182700 | P52: =SUMIFS(data!$G:$G,data!$C:$C,$B$31,data!$D:$D,$B$47,data!$F:$F,O$4,data!$E:$E,$B52,data!$H:$H,ПФ2026!P$5) -> 0 | Q52: =SUMIFS(data!$G:$G,data!$C:$C,$B$31,data!$D:$D,$B$47,data!$F:$F,Q$4,data!$E:$E,$B52,data!$H:$H,ПФ2026!Q$5) -> -31945333 | R52: =SUMIFS(data!$G:$G,data!$C:$C,$B$31,data!$D:$D,$B$47,data!$F:$F,Q$4,data!$E:$E,$B52,data!$H:$H,ПФ2026!R$5) -> 0 | S52: =SUMIFS(data!$G:$G,data!$C:$C,$B$31,data!$D:$D,$B$47,data!$F:$F,S$4,data!$E:$E,$B52,data!$H:$H,ПФ2026!S$5) -> -23308485 | T52: =SUMIFS(data!$G:$G,data!$C:$C,$B$31,data!$D:$D,$B$47,data!$F:$F,S$4,data!$E:$E,$B52,data!$H:$H,ПФ2026!T$5) -> 0 | U52: =SUMIFS(data!$G:$G,data!$C:$C,$B$31,data!$D:$D,$B$47,data!$F:$F,U$4,data!$E:$E,$B52,data!$H:$H,ПФ2026!U$5) -> -12660891 | V52: =SUMIFS(data!$G:$G,data!$C:$C,$B$31,data!$D:$D,$B$47,data!$F:$F,U$4,data!$E:$E,$B52,data!$H:$H,ПФ2026!V$5) -> 0 | W52: =SUMIFS(data!$G:$G,data!$C:$C,$B$31,data!$D:$D,$B$47,data!$F:$F,W$4,data!$E:$E,$B52,data!$H:$H,ПФ2026!W$5) -> -11840097 | X52: =SUMIFS(data!$G:$G,data!$C:$C,$B$31,data!$D:$D,$B$47,data!$F:$F,W$4,data!$E:$E,$B52,data!$H:$H,ПФ2026!X$5) -> 0 | Y52: =SUMIFS(data!$G:$G,data!$C:$C,$B$31,data!$D:$D,$B$47,data!$F:$F,Y$4,data!$E:$E,$B52,data!$H:$H,ПФ2026!Y$5) -> -11819362 | Z52: =SUMIFS(data!$G:$G,data!$C:$C,$B$31,data!$D:$D,$B$47,data!$F:$F,Y$4,data!$E:$E,$B52,data!$H:$H,ПФ2026!Z$5) -> 0 | AA52: =SUM(C52,E52,G52,I52,K52,M52,O113,O52,Q52,S52,Y52,W52,U52) -> -259838524 | AB52: =D52+F52+H52+J52+L52+N52+P52+R52+T52+V52+X52+Z52 -> -1.5851712e+08 | AC52: =IFERROR(AB52/AA52,0) -> 0.61006011
B53: Служба ОТ и ТБ | C53: =SUMIFS(data!$G:$G,data!$C:$C,$B$31,data!$D:$D,$B$47,data!$F:$F,C$4,data!$E:$E,$B53,data!$H:$H,ПФ2026!C$5) -> -210000 | D53: =SUMIFS(data!$G:$G,data!$C:$C,$B$31,data!$D:$D,$B$47,data!$F:$F,C$4,data!$E:$E,$B53,data!$H:$H,ПФ2026!D$5) -> -251571.79 | E53: =SUMIFS(data!$G:$G,data!$C:$C,$B$31,data!$D:$D,$B$47,data!$F:$F,E$4,data!$E:$E,$B53,data!$H:$H,ПФ2026!E$5) -> -210000 | F53: =SUMIFS(data!$G:$G,data!$C:$C,$B$31,data!$D:$D,$B$47,data!$F:$F,E$4,data!$E:$E,$B53,data!$H:$H,ПФ2026!F$5) -> -296404.71 | G53: =SUMIFS(data!$G:$G,data!$C:$C,$B$31,data!$D:$D,$B$47,data!$F:$F,G$4,data!$E:$E,$B53,data!$H:$H,ПФ2026!G$5) -> -210000 | H53: =SUMIFS(data!$G:$G,data!$C:$C,$B$31,data!$D:$D,$B$47,data!$F:$F,G$4,data!$E:$E,$B53,data!$H:$H,ПФ2026!H$5) -> -258098.68 | I53: =SUMIFS(data!$G:$G,data!$C:$C,$B$31,data!$D:$D,$B$47,data!$F:$F,I$4,data!$E:$E,$B53,data!$H:$H,ПФ2026!I$5) -> -210000 | J53: =SUMIFS(data!$G:$G,data!$C:$C,$B$31,data!$D:$D,$B$47,data!$F:$F,I$4,data!$E:$E,$B53,data!$H:$H,ПФ2026!J$5) -> -271075.05 | K53: =SUMIFS(data!$G:$G,data!$C:$C,$B$31,data!$D:$D,$B$47,data!$F:$F,K$4,data!$E:$E,$B53,data!$H:$H,ПФ2026!K$5) -> -210000 | L53: =SUMIFS(data!$G:$G,data!$C:$C,$B$31,data!$D:$D,$B$47,data!$F:$F,K$4,data!$E:$E,$B53,data!$H:$H,ПФ2026!L$5) -> -272302.47 | M53: =SUMIFS(data!$G:$G,data!$C:$C,$B$31,data!$D:$D,$B$47,data!$F:$F,M$4,data!$E:$E,$B53,data!$H:$H,ПФ2026!M$5) -> -210000 | N53: =SUMIFS(data!$G:$G,data!$C:$C,$B$31,data!$D:$D,$B$47,data!$F:$F,M$4,data!$E:$E,$B53,data!$H:$H,ПФ2026!N$5) -> -272302.47 | O53: =SUMIFS(data!$G:$G,data!$C:$C,$B$31,data!$D:$D,$B$47,data!$F:$F,O$4,data!$E:$E,$B53,data!$H:$H,ПФ2026!O$5) -> -210000 | P53: =SUMIFS(data!$G:$G,data!$C:$C,$B$31,data!$D:$D,$B$47,data!$F:$F,O$4,data!$E:$E,$B53,data!$H:$H,ПФ2026!P$5) -> 0 | Q53: =SUMIFS(data!$G:$G,data!$C:$C,$B$31,data!$D:$D,$B$47,data!$F:$F,Q$4,data!$E:$E,$B53,data!$H:$H,ПФ2026!Q$5) -> -210000 | R53: =SUMIFS(data!$G:$G,data!$C:$C,$B$31,data!$D:$D,$B$47,data!$F:$F,Q$4,data!$E:$E,$B53,data!$H:$H,ПФ2026!R$5) -> 0 | S53: =SUMIFS(data!$G:$G,data!$C:$C,$B$31,data!$D:$D,$B$47,data!$F:$F,S$4,data!$E:$E,$B53,data!$H:$H,ПФ2026!S$5) -> -210000 | T53: =SUMIFS(data!$G:$G,data!$C:$C,$B$31,data!$D:$D,$B$47,data!$F:$F,S$4,data!$E:$E,$B53,data!$H:$H,ПФ2026!T$5) -> 0 | U53: =SUMIFS(data!$G:$G,data!$C:$C,$B$31,data!$D:$D,$B$47,data!$F:$F,U$4,data!$E:$E,$B53,data!$H:$H,ПФ2026!U$5) -> -210000 | V53: =SUMIFS(data!$G:$G,data!$C:$C,$B$31,data!$D:$D,$B$47,data!$F:$F,U$4,data!$E:$E,$B53,data!$H:$H,ПФ2026!V$5) -> 0 | W53: =SUMIFS(data!$G:$G,data!$C:$C,$B$31,data!$D:$D,$B$47,data!$F:$F,W$4,data!$E:$E,$B53,data!$H:$H,ПФ2026!W$5) -> -210000 | X53: =SUMIFS(data!$G:$G,data!$C:$C,$B$31,data!$D:$D,$B$47,data!$F:$F,W$4,data!$E:$E,$B53,data!$H:$H,ПФ2026!X$5) -> 0 | Y53: =SUMIFS(data!$G:$G,data!$C:$C,$B$31,data!$D:$D,$B$47,data!$F:$F,Y$4,data!$E:$E,$B53,data!$H:$H,ПФ2026!Y$5) -> -210000 | Z53: =SUMIFS(data!$G:$G,data!$C:$C,$B$31,data!$D:$D,$B$47,data!$F:$F,Y$4,data!$E:$E,$B53,data!$H:$H,ПФ2026!Z$5) -> 0 | AA53: =SUM(C53,E53,G53,I53,K53,M53,O114,O53,Q53,S53,Y53,W53,U53) -> -2520000 | AB53: =D53+F53+H53+J53+L53+N53+P53+R53+T53+V53+X53+Z53 -> -1621755.2 | AC53: =IFERROR(AB53/AA53,0) -> 0.64355364
B54: Технический департамент | C54: =SUMIFS(data!$G:$G,data!$C:$C,$B$31,data!$D:$D,$B$47,data!$F:$F,C$4,data!$E:$E,$B54,data!$H:$H,ПФ2026!C$5) -> -8622570 | D54: =SUMIFS(data!$G:$G,data!$C:$C,$B$31,data!$D:$D,$B$47,data!$F:$F,C$4,data!$E:$E,$B54,data!$H:$H,ПФ2026!D$5) -> -7522286.2 | E54: =SUMIFS(data!$G:$G,data!$C:$C,$B$31,data!$D:$D,$B$47,data!$F:$F,E$4,data!$E:$E,$B54,data!$H:$H,ПФ2026!E$5) -> -8622570 | F54: =SUMIFS(data!$G:$G,data!$C:$C,$B$31,data!$D:$D,$B$47,data!$F:$F,E$4,data!$E:$E,$B54,data!$H:$H,ПФ2026!F$5) -> -7752159.3 | G54: =SUMIFS(data!$G:$G,data!$C:$C,$B$31,data!$D:$D,$B$47,data!$F:$F,G$4,data!$E:$E,$B54,data!$H:$H,ПФ2026!G$5) -> -8665770 | H54: =SUMIFS(data!$G:$G,data!$C:$C,$B$31,data!$D:$D,$B$47,data!$F:$F,G$4,data!$E:$E,$B54,data!$H:$H,ПФ2026!H$5) -> -8889417.3 | I54: =SUMIFS(data!$G:$G,data!$C:$C,$B$31,data!$D:$D,$B$47,data!$F:$F,I$4,data!$E:$E,$B54,data!$H:$H,ПФ2026!I$5) -> -8703210 | J54: =SUMIFS(data!$G:$G,data!$C:$C,$B$31,data!$D:$D,$B$47,data!$F:$F,I$4,data!$E:$E,$B54,data!$H:$H,ПФ2026!J$5) -> -9184768.5 | K54: =SUMIFS(data!$G:$G,data!$C:$C,$B$31,data!$D:$D,$B$47,data!$F:$F,K$4,data!$E:$E,$B54,data!$H:$H,ПФ2026!K$5) -> -8703210 | L54: =SUMIFS(data!$G:$G,data!$C:$C,$B$31,data!$D:$D,$B$47,data!$F:$F,K$4,data!$E:$E,$B54,data!$H:$H,ПФ2026!L$5) -> -9528932.8 | M54: =SUMIFS(data!$G:$G,data!$C:$C,$B$31,data!$D:$D,$B$47,data!$F:$F,M$4,data!$E:$E,$B54,data!$H:$H,ПФ2026!M$5) -> -8703210 | N54: =SUMIFS(data!$G:$G,data!$C:$C,$B$31,data!$D:$D,$B$47,data!$F:$F,M$4,data!$E:$E,$B54,data!$H:$H,ПФ2026!N$5) -> -9841938.1 | O54: =SUMIFS(data!$G:$G,data!$C:$C,$B$31,data!$D:$D,$B$47,data!$F:$F,O$4,data!$E:$E,$B54,data!$H:$H,ПФ2026!O$5) -> -8703210 | P54: =SUMIFS(data!$G:$G,data!$C:$C,$B$31,data!$D:$D,$B$47,data!$F:$F,O$4,data!$E:$E,$B54,data!$H:$H,ПФ2026!P$5) -> 0 | Q54: =SUMIFS(data!$G:$G,data!$C:$C,$B$31,data!$D:$D,$B$47,data!$F:$F,Q$4,data!$E:$E,$B54,data!$H:$H,ПФ2026!Q$5) -> -8703210 | R54: =SUMIFS(data!$G:$G,data!$C:$C,$B$31,data!$D:$D,$B$47,data!$F:$F,Q$4,data!$E:$E,$B54,data!$H:$H,ПФ2026!R$5) -> 0 | S54: =SUMIFS(data!$G:$G,data!$C:$C,$B$31,data!$D:$D,$B$47,data!$F:$F,S$4,data!$E:$E,$B54,data!$H:$H,ПФ2026!S$5) -> -8703210 | T54: =SUMIFS(data!$G:$G,data!$C:$C,$B$31,data!$D:$D,$B$47,data!$F:$F,S$4,data!$E:$E,$B54,data!$H:$H,ПФ2026!T$5) -> 0 | U54: =SUMIFS(data!$G:$G,data!$C:$C,$B$31,data!$D:$D,$B$47,data!$F:$F,U$4,data!$E:$E,$B54,data!$H:$H,ПФ2026!U$5) -> -8665770 | V54: =SUMIFS(data!$G:$G,data!$C:$C,$B$31,data!$D:$D,$B$47,data!$F:$F,U$4,data!$E:$E,$B54,data!$H:$H,ПФ2026!V$5) -> 0 | W54: =SUMIFS(data!$G:$G,data!$C:$C,$B$31,data!$D:$D,$B$47,data!$F:$F,W$4,data!$E:$E,$B54,data!$H:$H,ПФ2026!W$5) -> -8665770 | X54: =SUMIFS(data!$G:$G,data!$C:$C,$B$31,data!$D:$D,$B$47,data!$F:$F,W$4,data!$E:$E,$B54,data!$H:$H,ПФ2026!X$5) -> 0 | Y54: =SUMIFS(data!$G:$G,data!$C:$C,$B$31,data!$D:$D,$B$47,data!$F:$F,Y$4,data!$E:$E,$B54,data!$H:$H,ПФ2026!Y$5) -> -8665770 | Z54: =SUMIFS(data!$G:$G,data!$C:$C,$B$31,data!$D:$D,$B$47,data!$F:$F,Y$4,data!$E:$E,$B54,data!$H:$H,ПФ2026!Z$5) -> 0 | AA54: =SUM(C54,E54,G54,I54,K54,M54,O115,O54,Q54,S54,Y54,W54,U54) -> -104127480 | AB54: =D54+F54+H54+J54+L54+N54+P54+R54+T54+V54+X54+Z54 -> -52719502 | AC54: =IFERROR(AB54/AA54,0) -> 0.50629769
B55: Финансовый департамент | C55: =SUMIFS(data!$G:$G,data!$C:$C,$B$31,data!$D:$D,$B$47,data!$F:$F,C$4,data!$E:$E,$B55,data!$H:$H,ПФ2026!C$5) -> -3425500 | D55: =SUMIFS(data!$G:$G,data!$C:$C,$B$31,data!$D:$D,$B$47,data!$F:$F,C$4,data!$E:$E,$B55,data!$H:$H,ПФ2026!D$5) -> -3979624.9 | E55: =SUMIFS(data!$G:$G,data!$C:$C,$B$31,data!$D:$D,$B$47,data!$F:$F,E$4,data!$E:$E,$B55,data!$H:$H,ПФ2026!E$5) -> -3425500 | F55: =SUMIFS(data!$G:$G,data!$C:$C,$B$31,data!$D:$D,$B$47,data!$F:$F,E$4,data!$E:$E,$B55,data!$H:$H,ПФ2026!F$5) -> -4062214.3 | G55: =SUMIFS(data!$G:$G,data!$C:$C,$B$31,data!$D:$D,$B$47,data!$F:$F,G$4,data!$E:$E,$B55,data!$H:$H,ПФ2026!G$5) -> -3425500 | H55: =SUMIFS(data!$G:$G,data!$C:$C,$B$31,data!$D:$D,$B$47,data!$F:$F,G$4,data!$E:$E,$B55,data!$H:$H,ПФ2026!H$5) -> -4329665.4 | I55: =SUMIFS(data!$G:$G,data!$C:$C,$B$31,data!$D:$D,$B$47,data!$F:$F,I$4,data!$E:$E,$B55,data!$H:$H,ПФ2026!I$5) -> -3425500 | J55: =SUMIFS(data!$G:$G,data!$C:$C,$B$31,data!$D:$D,$B$47,data!$F:$F,I$4,data!$E:$E,$B55,data!$H:$H,ПФ2026!J$5) -> -4202813 | K55: =SUMIFS(data!$G:$G,data!$C:$C,$B$31,data!$D:$D,$B$47,data!$F:$F,K$4,data!$E:$E,$B55,data!$H:$H,ПФ2026!K$5) -> -3425500 | L55: =SUMIFS(data!$G:$G,data!$C:$C,$B$31,data!$D:$D,$B$47,data!$F:$F,K$4,data!$E:$E,$B55,data!$H:$H,ПФ2026!L$5) -> -4500123.4 | M55: =SUMIFS(data!$G:$G,data!$C:$C,$B$31,data!$D:$D,$B$47,data!$F:$F,M$4,data!$E:$E,$B55,data!$H:$H,ПФ2026!M$5) -> -3425500 | N55: =SUMIFS(data!$G:$G,data!$C:$C,$B$31,data!$D:$D,$B$47,data!$F:$F,M$4,data!$E:$E,$B55,data!$H:$H,ПФ2026!N$5) -> -4314728 | O55: =SUMIFS(data!$G:$G,data!$C:$C,$B$31,data!$D:$D,$B$47,data!$F:$F,O$4,data!$E:$E,$B55,data!$H:$H,ПФ2026!O$5) -> -3425500 | P55: =SUMIFS(data!$G:$G,data!$C:$C,$B$31,data!$D:$D,$B$47,data!$F:$F,O$4,data!$E:$E,$B55,data!$H:$H,ПФ2026!P$5) -> 0 | Q55: =SUMIFS(data!$G:$G,data!$C:$C,$B$31,data!$D:$D,$B$47,data!$F:$F,Q$4,data!$E:$E,$B55,data!$H:$H,ПФ2026!Q$5) -> -3425500 | R55: =SUMIFS(data!$G:$G,data!$C:$C,$B$31,data!$D:$D,$B$47,data!$F:$F,Q$4,data!$E:$E,$B55,data!$H:$H,ПФ2026!R$5) -> 0 | S55: =SUMIFS(data!$G:$G,data!$C:$C,$B$31,data!$D:$D,$B$47,data!$F:$F,S$4,data!$E:$E,$B55,data!$H:$H,ПФ2026!S$5) -> -3425500 | T55: =SUMIFS(data!$G:$G,data!$C:$C,$B$31,data!$D:$D,$B$47,data!$F:$F,S$4,data!$E:$E,$B55,data!$H:$H,ПФ2026!T$5) -> 0 | U55: =SUMIFS(data!$G:$G,data!$C:$C,$B$31,data!$D:$D,$B$47,data!$F:$F,U$4,data!$E:$E,$B55,data!$H:$H,ПФ2026!U$5) -> -3425500 | V55: =SUMIFS(data!$G:$G,data!$C:$C,$B$31,data!$D:$D,$B$47,data!$F:$F,U$4,data!$E:$E,$B55,data!$H:$H,ПФ2026!V$5) -> 0 | W55: =SUMIFS(data!$G:$G,data!$C:$C,$B$31,data!$D:$D,$B$47,data!$F:$F,W$4,data!$E:$E,$B55,data!$H:$H,ПФ2026!W$5) -> -3425500 | X55: =SUMIFS(data!$G:$G,data!$C:$C,$B$31,data!$D:$D,$B$47,data!$F:$F,W$4,data!$E:$E,$B55,data!$H:$H,ПФ2026!X$5) -> 0 | Y55: =SUMIFS(data!$G:$G,data!$C:$C,$B$31,data!$D:$D,$B$47,data!$F:$F,Y$4,data!$E:$E,$B55,data!$H:$H,ПФ2026!Y$5) -> -3425500 | Z55: =SUMIFS(data!$G:$G,data!$C:$C,$B$31,data!$D:$D,$B$47,data!$F:$F,Y$4,data!$E:$E,$B55,data!$H:$H,ПФ2026!Z$5) -> 0 | AA55: =SUM(C55,E55,G55,I55,K55,M55,O116,O55,Q55,S55,Y55,W55,U55) -> -41106000 | AB55: =D55+F55+H55+J55+L55+N55+P55+R55+T55+V55+X55+Z55 -> -25389169 | AC55: =IFERROR(AB55/AA55,0) -> 0.61765117
B56: Шоро-Ош | C56: =SUMIFS(data!$G:$G,data!$C:$C,$B$31,data!$D:$D,$B$47,data!$F:$F,C$4,data!$E:$E,$B56,data!$H:$H,ПФ2026!C$5) -> -610528 | D56: =SUMIFS(data!$G:$G,data!$C:$C,$B$31,data!$D:$D,$B$47,data!$F:$F,C$4,data!$E:$E,$B56,data!$H:$H,ПФ2026!D$5) -> -361103.91 | E56: =SUMIFS(data!$G:$G,data!$C:$C,$B$31,data!$D:$D,$B$47,data!$F:$F,E$4,data!$E:$E,$B56,data!$H:$H,ПФ2026!E$5) -> -652878 | F56: =SUMIFS(data!$G:$G,data!$C:$C,$B$31,data!$D:$D,$B$47,data!$F:$F,E$4,data!$E:$E,$B56,data!$H:$H,ПФ2026!F$5) -> -407738 | G56: =SUMIFS(data!$G:$G,data!$C:$C,$B$31,data!$D:$D,$B$47,data!$F:$F,G$4,data!$E:$E,$B56,data!$H:$H,ПФ2026!G$5) -> -3344590 | H56: =SUMIFS(data!$G:$G,data!$C:$C,$B$31,data!$D:$D,$B$47,data!$F:$F,G$4,data!$E:$E,$B56,data!$H:$H,ПФ2026!H$5) -> -1928739.6 | I56: =SUMIFS(data!$G:$G,data!$C:$C,$B$31,data!$D:$D,$B$47,data!$F:$F,I$4,data!$E:$E,$B56,data!$H:$H,ПФ2026!I$5) -> -5655940 | J56: =SUMIFS(data!$G:$G,data!$C:$C,$B$31,data!$D:$D,$B$47,data!$F:$F,I$4,data!$E:$E,$B56,data!$H:$H,ПФ2026!J$5) -> -4149467.2 | K56: =SUMIFS(data!$G:$G,data!$C:$C,$B$31,data!$D:$D,$B$47,data!$F:$F,K$4,data!$E:$E,$B56,data!$H:$H,ПФ2026!K$5) -> -6795940 | L56: =SUMIFS(data!$G:$G,data!$C:$C,$B$31,data!$D:$D,$B$47,data!$F:$F,K$4,data!$E:$E,$B56,data!$H:$H,ПФ2026!L$5) -> -5139291.5 | M56: =SUMIFS(data!$G:$G,data!$C:$C,$B$31,data!$D:$D,$B$47,data!$F:$F,M$4,data!$E:$E,$B56,data!$H:$H,ПФ2026!M$5) -> -6795940 | N56: =SUMIFS(data!$G:$G,data!$C:$C,$B$31,data!$D:$D,$B$47,data!$F:$F,M$4,data!$E:$E,$B56,data!$H:$H,ПФ2026!N$5) -> -5470152.8 | O56: =SUMIFS(data!$G:$G,data!$C:$C,$B$31,data!$D:$D,$B$47,data!$F:$F,O$4,data!$E:$E,$B56,data!$H:$H,ПФ2026!O$5) -> -6795940 | P56: =SUMIFS(data!$G:$G,data!$C:$C,$B$31,data!$D:$D,$B$47,data!$F:$F,O$4,data!$E:$E,$B56,data!$H:$H,ПФ2026!P$5) -> 0 | Q56: =SUMIFS(data!$G:$G,data!$C:$C,$B$31,data!$D:$D,$B$47,data!$F:$F,Q$4,data!$E:$E,$B56,data!$H:$H,ПФ2026!Q$5) -> -6795940 | R56: =SUMIFS(data!$G:$G,data!$C:$C,$B$31,data!$D:$D,$B$47,data!$F:$F,Q$4,data!$E:$E,$B56,data!$H:$H,ПФ2026!R$5) -> 0 | S56: =SUMIFS(data!$G:$G,data!$C:$C,$B$31,data!$D:$D,$B$47,data!$F:$F,S$4,data!$E:$E,$B56,data!$H:$H,ПФ2026!S$5) -> -3881940 | T56: =SUMIFS(data!$G:$G,data!$C:$C,$B$31,data!$D:$D,$B$47,data!$F:$F,S$4,data!$E:$E,$B56,data!$H:$H,ПФ2026!T$5) -> 0 | U56: =SUMIFS(data!$G:$G,data!$C:$C,$B$31,data!$D:$D,$B$47,data!$F:$F,U$4,data!$E:$E,$B56,data!$H:$H,ПФ2026!U$5) -> -1343574 | V56: =SUMIFS(data!$G:$G,data!$C:$C,$B$31,data!$D:$D,$B$47,data!$F:$F,U$4,data!$E:$E,$B56,data!$H:$H,ПФ2026!V$5) -> 0 | W56: =SUMIFS(data!$G:$G,data!$C:$C,$B$31,data!$D:$D,$B$47,data!$F:$F,W$4,data!$E:$E,$B56,data!$H:$H,ПФ2026!W$5) -> -614378 | X56: =SUMIFS(data!$G:$G,data!$C:$C,$B$31,data!$D:$D,$B$47,data!$F:$F,W$4,data!$E:$E,$B56,data!$H:$H,ПФ2026!X$5) -> 0 | Y56: =SUMIFS(data!$G:$G,data!$C:$C,$B$31,data!$D:$D,$B$47,data!$F:$F,Y$4,data!$E:$E,$B56,data!$H:$H,ПФ2026!Y$5) -> -610528 | Z56: =SUMIFS(data!$G:$G,data!$C:$C,$B$31,data!$D:$D,$B$47,data!$F:$F,Y$4,data!$E:$E,$B56,data!$H:$H,ПФ2026!Z$5) -> 0 | AA56: =SUM(C56,E56,G56,I56,K56,M56,O118,O56,Q56,S56,Y56,W56,U56) -> -43898116 | AB56: =D56+F56+H56+J56+L56+N56+P56+R56+T56+V56+X56+Z56 -> -17456493 | AC56: =IFERROR(AB56/AA56,0) -> 0.39765927
B57: Юридический отдел | C57: =SUMIFS(data!$G:$G,data!$C:$C,$B$31,data!$D:$D,$B$47,data!$F:$F,C$4,data!$E:$E,$B57,data!$H:$H,ПФ2026!C$5) -> -190000 | D57: =SUMIFS(data!$G:$G,data!$C:$C,$B$31,data!$D:$D,$B$47,data!$F:$F,C$4,data!$E:$E,$B57,data!$H:$H,ПФ2026!D$5) -> -215888.89 | E57: =SUMIFS(data!$G:$G,data!$C:$C,$B$31,data!$D:$D,$B$47,data!$F:$F,E$4,data!$E:$E,$B57,data!$H:$H,ПФ2026!E$5) -> -190000 | F57: =SUMIFS(data!$G:$G,data!$C:$C,$B$31,data!$D:$D,$B$47,data!$F:$F,E$4,data!$E:$E,$B57,data!$H:$H,ПФ2026!F$5) -> -246833.33 | G57: =SUMIFS(data!$G:$G,data!$C:$C,$B$31,data!$D:$D,$B$47,data!$F:$F,G$4,data!$E:$E,$B57,data!$H:$H,ПФ2026!G$5) -> -190000 | H57: =SUMIFS(data!$G:$G,data!$C:$C,$B$31,data!$D:$D,$B$47,data!$F:$F,G$4,data!$E:$E,$B57,data!$H:$H,ПФ2026!H$5) -> -246833.33 | I57: =SUMIFS(data!$G:$G,data!$C:$C,$B$31,data!$D:$D,$B$47,data!$F:$F,I$4,data!$E:$E,$B57,data!$H:$H,ПФ2026!I$5) -> -190000 | J57: =SUMIFS(data!$G:$G,data!$C:$C,$B$31,data!$D:$D,$B$47,data!$F:$F,I$4,data!$E:$E,$B57,data!$H:$H,ПФ2026!J$5) -> -246833.33 | K57: =SUMIFS(data!$G:$G,data!$C:$C,$B$31,data!$D:$D,$B$47,data!$F:$F,K$4,data!$E:$E,$B57,data!$H:$H,ПФ2026!K$5) -> -190000 | L57: =SUMIFS(data!$G:$G,data!$C:$C,$B$31,data!$D:$D,$B$47,data!$F:$F,K$4,data!$E:$E,$B57,data!$H:$H,ПФ2026!L$5) -> -246833.33 | M57: =SUMIFS(data!$G:$G,data!$C:$C,$B$31,data!$D:$D,$B$47,data!$F:$F,M$4,data!$E:$E,$B57,data!$H:$H,ПФ2026!M$5) -> -190000 | N57: =SUMIFS(data!$G:$G,data!$C:$C,$B$31,data!$D:$D,$B$47,data!$F:$F,M$4,data!$E:$E,$B57,data!$H:$H,ПФ2026!N$5) -> -246833.33 | O57: =SUMIFS(data!$G:$G,data!$C:$C,$B$31,data!$D:$D,$B$47,data!$F:$F,O$4,data!$E:$E,$B57,data!$H:$H,ПФ2026!O$5) -> -190000 | P57: =SUMIFS(data!$G:$G,data!$C:$C,$B$31,data!$D:$D,$B$47,data!$F:$F,O$4,data!$E:$E,$B57,data!$H:$H,ПФ2026!P$5) -> 0 | Q57: =SUMIFS(data!$G:$G,data!$C:$C,$B$31,data!$D:$D,$B$47,data!$F:$F,Q$4,data!$E:$E,$B57,data!$H:$H,ПФ2026!Q$5) -> -190000 | R57: =SUMIFS(data!$G:$G,data!$C:$C,$B$31,data!$D:$D,$B$47,data!$F:$F,Q$4,data!$E:$E,$B57,data!$H:$H,ПФ2026!R$5) -> 0 | S57: =SUMIFS(data!$G:$G,data!$C:$C,$B$31,data!$D:$D,$B$47,data!$F:$F,S$4,data!$E:$E,$B57,data!$H:$H,ПФ2026!S$5) -> -190000 | T57: =SUMIFS(data!$G:$G,data!$C:$C,$B$31,data!$D:$D,$B$47,data!$F:$F,S$4,data!$E:$E,$B57,data!$H:$H,ПФ2026!T$5) -> 0 | U57: =SUMIFS(data!$G:$G,data!$C:$C,$B$31,data!$D:$D,$B$47,data!$F:$F,U$4,data!$E:$E,$B57,data!$H:$H,ПФ2026!U$5) -> -190000 | V57: =SUMIFS(data!$G:$G,data!$C:$C,$B$31,data!$D:$D,$B$47,data!$F:$F,U$4,data!$E:$E,$B57,data!$H:$H,ПФ2026!V$5) -> 0 | W57: =SUMIFS(data!$G:$G,data!$C:$C,$B$31,data!$D:$D,$B$47,data!$F:$F,W$4,data!$E:$E,$B57,data!$H:$H,ПФ2026!W$5) -> -190000 | X57: =SUMIFS(data!$G:$G,data!$C:$C,$B$31,data!$D:$D,$B$47,data!$F:$F,W$4,data!$E:$E,$B57,data!$H:$H,ПФ2026!X$5) -> 0 | Y57: =SUMIFS(data!$G:$G,data!$C:$C,$B$31,data!$D:$D,$B$47,data!$F:$F,Y$4,data!$E:$E,$B57,data!$H:$H,ПФ2026!Y$5) -> -190000 | Z57: =SUMIFS(data!$G:$G,data!$C:$C,$B$31,data!$D:$D,$B$47,data!$F:$F,Y$4,data!$E:$E,$B57,data!$H:$H,ПФ2026!Z$5) -> 0 | AA57: =SUM(C57,E57,G57,I57,K57,M57,O119,O57,Q57,S57,Y57,W57,U57) -> -2360000 | AB57: =D57+F57+H57+J57+L57+N57+P57+R57+T57+V57+X57+Z57 -> -1450055.5 | AC57: =IFERROR(AB57/AA57,0) -> 0.61443031
B58: Расходы по сотовой связи | C58: =SUM(C59:C60) -> -46114.954 | D58: =SUM(D59:D60) -> -25789.29 | E58: =SUM(E59:E60) -> -43905.775 | F58: =SUM(F59:F60) -> -4754.28 | G58: =SUM(G59:G60) -> -46904.322 | H58: =SUM(H59:H60) -> -4972.42 | I58: =SUM(I59:I60) -> -45736.504 | J58: =SUM(J59:J60) -> -15895.41 | ... Z58: =SUM(Z59:Z60) -> 0 | AA58: =SUM(C58,E58,G58,I58,K58,M58,O120,O58,Q58,S58,Y58,W58,U58) -> -641598.44 | AB58: =D58+F58+H58+J58+L58+N58+P58+R58+T58+V58+X58+Z58 -> -87449 | AC58: =IFERROR(AB58/AA58,0) -> 0.13629865
B59: Сотовая связь | C59: =SUMIFS(data!$G:$G,data!$C:$C,$B$31,data!$D:$D,$B$58,data!$F:$F,C$4,data!$E:$E,$B59,data!$H:$H,ПФ2026!C$5) -> -24114.954 | D59: =SUMIFS(data!$G:$G,data!$C:$C,$B$31,data!$D:$D,$B$58,data!$F:$F,C$4,data!$E:$E,$B59,data!$H:$H,ПФ2026!D$5) -> -25789.29 | E59: =SUMIFS(data!$G:$G,data!$C:$C,$B$31,data!$D:$D,$B$58,data!$F:$F,E$4,data!$E:$E,$B59,data!$H:$H,ПФ2026!E$5) -> -21905.775 | F59: =SUMIFS(data!$G:$G,data!$C:$C,$B$31,data!$D:$D,$B$58,data!$F:$F,E$4,data!$E:$E,$B59,data!$H:$H,ПФ2026!F$5) -> -4754.28 | G59: =SUMIFS(data!$G:$G,data!$C:$C,$B$31,data!$D:$D,$B$58,data!$F:$F,G$4,data!$E:$E,$B59,data!$H:$H,ПФ2026!G$5) -> -24904.322 | H59: =SUMIFS(data!$G:$G,data!$C:$C,$B$31,data!$D:$D,$B$58,data!$F:$F,G$4,data!$E:$E,$B59,data!$H:$H,ПФ2026!H$5) -> -4972.42 | I59: =SUMIFS(data!$G:$G,data!$C:$C,$B$31,data!$D:$D,$B$58,data!$F:$F,I$4,data!$E:$E,$B59,data!$H:$H,ПФ2026!I$5) -> -23736.504 | J59: =SUMIFS(data!$G:$G,data!$C:$C,$B$31,data!$D:$D,$B$58,data!$F:$F,I$4,data!$E:$E,$B59,data!$H:$H,ПФ2026!J$5) -> -15895.41 | K59: =SUMIFS(data!$G:$G,data!$C:$C,$B$31,data!$D:$D,$B$58,data!$F:$F,K$4,data!$E:$E,$B59,data!$H:$H,ПФ2026!K$5) -> -23223.47 | L59: =SUMIFS(data!$G:$G,data!$C:$C,$B$31,data!$D:$D,$B$58,data!$F:$F,K$4,data!$E:$E,$B59,data!$H:$H,ПФ2026!L$5) -> -20366.88 | M59: =SUMIFS(data!$G:$G,data!$C:$C,$B$31,data!$D:$D,$B$58,data!$F:$F,M$4,data!$E:$E,$B59,data!$H:$H,ПФ2026!M$5) -> -22789.899 | N59: =SUMIFS(data!$G:$G,data!$C:$C,$B$31,data!$D:$D,$B$58,data!$F:$F,M$4,data!$E:$E,$B59,data!$H:$H,ПФ2026!N$5) -> -15670.72 | O59: =SUMIFS(data!$G:$G,data!$C:$C,$B$31,data!$D:$D,$B$58,data!$F:$F,O$4,data!$E:$E,$B59,data!$H:$H,ПФ2026!O$5) -> -25958.84 | P59: =SUMIFS(data!$G:$G,data!$C:$C,$B$31,data!$D:$D,$B$58,data!$F:$F,O$4,data!$E:$E,$B59,data!$H:$H,ПФ2026!P$5) -> 0 | Q59: =SUMIFS(data!$G:$G,data!$C:$C,$B$31,data!$D:$D,$B$58,data!$F:$F,Q$4,data!$E:$E,$B59,data!$H:$H,ПФ2026!Q$5) -> -24454.588 | R59: =SUMIFS(data!$G:$G,data!$C:$C,$B$31,data!$D:$D,$B$58,data!$F:$F,Q$4,data!$E:$E,$B59,data!$H:$H,ПФ2026!R$5) -> 0 | S59: =SUMIFS(data!$G:$G,data!$C:$C,$B$31,data!$D:$D,$B$58,data!$F:$F,S$4,data!$E:$E,$B59,data!$H:$H,ПФ2026!S$5) -> -52390.237 | T59: =SUMIFS(data!$G:$G,data!$C:$C,$B$31,data!$D:$D,$B$58,data!$F:$F,S$4,data!$E:$E,$B59,data!$H:$H,ПФ2026!T$5) -> 0 | U59: =SUMIFS(data!$G:$G,data!$C:$C,$B$31,data!$D:$D,$B$58,data!$F:$F,U$4,data!$E:$E,$B59,data!$H:$H,ПФ2026!U$5) -> -44066.202 | V59: =SUMIFS(data!$G:$G,data!$C:$C,$B$31,data!$D:$D,$B$58,data!$F:$F,U$4,data!$E:$E,$B59,data!$H:$H,ПФ2026!V$5) -> 0 | W59: =SUMIFS(data!$G:$G,data!$C:$C,$B$31,data!$D:$D,$B$58,data!$F:$F,W$4,data!$E:$E,$B59,data!$H:$H,ПФ2026!W$5) -> -46357.598 | X59: =SUMIFS(data!$G:$G,data!$C:$C,$B$31,data!$D:$D,$B$58,data!$F:$F,W$4,data!$E:$E,$B59,data!$H:$H,ПФ2026!X$5) -> 0 | Y59: =SUMIFS(data!$G:$G,data!$C:$C,$B$31,data!$D:$D,$B$58,data!$F:$F,Y$4,data!$E:$E,$B59,data!$H:$H,ПФ2026!Y$5) -> -43696.052 | Z59: =SUMIFS(data!$G:$G,data!$C:$C,$B$31,data!$D:$D,$B$58,data!$F:$F,Y$4,data!$E:$E,$B59,data!$H:$H,ПФ2026!Z$5) -> 0 | AA59: =SUM(C59,E59,G59,I59,K59,M59,O121,O59,Q59,S59,Y59,W59,U59) -> -377598.44 | AB59: =D59+F59+H59+J59+L59+N59+P59+R59+T59+V59+X59+Z59 -> -87449 | AC59: =IFERROR(AB59/AA59,0) -> 0.23159259
B60: Расходы по сотовой связи | C60: =SUMIFS(data!$G:$G,data!$C:$C,$B$31,data!$D:$D,$B$58,data!$F:$F,C$4,data!$E:$E,$B60,data!$H:$H,ПФ2026!C$5) -> -22000 | D60: =SUMIFS(data!$G:$G,data!$C:$C,$B$31,data!$D:$D,$B$58,data!$F:$F,C$4,data!$E:$E,$B60,data!$H:$H,ПФ2026!D$5) -> 0 | E60: =SUMIFS(data!$G:$G,data!$C:$C,$B$31,data!$D:$D,$B$58,data!$F:$F,E$4,data!$E:$E,$B60,data!$H:$H,ПФ2026!E$5) -> -22000 | F60: =SUMIFS(data!$G:$G,data!$C:$C,$B$31,data!$D:$D,$B$58,data!$F:$F,E$4,data!$E:$E,$B60,data!$H:$H,ПФ2026!F$5) -> 0 | G60: =SUMIFS(data!$G:$G,data!$C:$C,$B$31,data!$D:$D,$B$58,data!$F:$F,G$4,data!$E:$E,$B60,data!$H:$H,ПФ2026!G$5) -> -22000 | H60: =SUMIFS(data!$G:$G,data!$C:$C,$B$31,data!$D:$D,$B$58,data!$F:$F,G$4,data!$E:$E,$B60,data!$H:$H,ПФ2026!H$5) -> 0 | I60: =SUMIFS(data!$G:$G,data!$C:$C,$B$31,data!$D:$D,$B$58,data!$F:$F,I$4,data!$E:$E,$B60,data!$H:$H,ПФ2026!I$5) -> -22000 | J60: =SUMIFS(data!$G:$G,data!$C:$C,$B$31,data!$D:$D,$B$58,data!$F:$F,I$4,data!$E:$E,$B60,data!$H:$H,ПФ2026!J$5) -> 0 | K60: =SUMIFS(data!$G:$G,data!$C:$C,$B$31,data!$D:$D,$B$58,data!$F:$F,K$4,data!$E:$E,$B60,data!$H:$H,ПФ2026!K$5) -> -22000 | L60: =SUMIFS(data!$G:$G,data!$C:$C,$B$31,data!$D:$D,$B$58,data!$F:$F,K$4,data!$E:$E,$B60,data!$H:$H,ПФ2026!L$5) -> 0 | M60: =SUMIFS(data!$G:$G,data!$C:$C,$B$31,data!$D:$D,$B$58,data!$F:$F,M$4,data!$E:$E,$B60,data!$H:$H,ПФ2026!M$5) -> -22000 | N60: =SUMIFS(data!$G:$G,data!$C:$C,$B$31,data!$D:$D,$B$58,data!$F:$F,M$4,data!$E:$E,$B60,data!$H:$H,ПФ2026!N$5) -> 0 | O60: =SUMIFS(data!$G:$G,data!$C:$C,$B$31,data!$D:$D,$B$58,data!$F:$F,O$4,data!$E:$E,$B60,data!$H:$H,ПФ2026!O$5) -> -22000 | P60: =SUMIFS(data!$G:$G,data!$C:$C,$B$31,data!$D:$D,$B$58,data!$F:$F,O$4,data!$E:$E,$B60,data!$H:$H,ПФ2026!P$5) -> 0 | Q60: =SUMIFS(data!$G:$G,data!$C:$C,$B$31,data!$D:$D,$B$58,data!$F:$F,Q$4,data!$E:$E,$B60,data!$H:$H,ПФ2026!Q$5) -> -22000 | R60: =SUMIFS(data!$G:$G,data!$C:$C,$B$31,data!$D:$D,$B$58,data!$F:$F,Q$4,data!$E:$E,$B60,data!$H:$H,ПФ2026!R$5) -> 0 | S60: =SUMIFS(data!$G:$G,data!$C:$C,$B$31,data!$D:$D,$B$58,data!$F:$F,S$4,data!$E:$E,$B60,data!$H:$H,ПФ2026!S$5) -> -22000 | T60: =SUMIFS(data!$G:$G,data!$C:$C,$B$31,data!$D:$D,$B$58,data!$F:$F,S$4,data!$E:$E,$B60,data!$H:$H,ПФ2026!T$5) -> 0 | U60: =SUMIFS(data!$G:$G,data!$C:$C,$B$31,data!$D:$D,$B$58,data!$F:$F,U$4,data!$E:$E,$B60,data!$H:$H,ПФ2026!U$5) -> -22000 | V60: =SUMIFS(data!$G:$G,data!$C:$C,$B$31,data!$D:$D,$B$58,data!$F:$F,U$4,data!$E:$E,$B60,data!$H:$H,ПФ2026!V$5) -> 0 | W60: =SUMIFS(data!$G:$G,data!$C:$C,$B$31,data!$D:$D,$B$58,data!$F:$F,W$4,data!$E:$E,$B60,data!$H:$H,ПФ2026!W$5) -> -22000 | X60: =SUMIFS(data!$G:$G,data!$C:$C,$B$31,data!$D:$D,$B$58,data!$F:$F,W$4,data!$E:$E,$B60,data!$H:$H,ПФ2026!X$5) -> 0 | Y60: =SUMIFS(data!$G:$G,data!$C:$C,$B$31,data!$D:$D,$B$58,data!$F:$F,Y$4,data!$E:$E,$B60,data!$H:$H,ПФ2026!Y$5) -> -22000 | Z60: =SUMIFS(data!$G:$G,data!$C:$C,$B$31,data!$D:$D,$B$58,data!$F:$F,Y$4,data!$E:$E,$B60,data!$H:$H,ПФ2026!Z$5) -> 0 | AA60: =SUM(C60,E60,G60,I60,K60,M60,O122,O60,Q60,S60,Y60,W60,U60) -> -264000 | AB60: =D60+F60+H60+J60+L60+N60+P60+R60+T60+V60+X60+Z60 -> 0 | AC60: =IFERROR(AB60/AA60,0) -> 0
B61: Столовая | C61: =SUM(C62:C77) -> -2410382.4 | D61: =SUM(D62:D77) -> -1704124 | E61: =SUM(E62:E77) -> -1958620.5 | F61: =SUM(F62:F77) -> -1676646.6 | G61: =SUM(G62:G77) -> -4212215 | H61: =SUM(H62:H77) -> -3349551.7 | I61: =SUM(I62:I77) -> -4972579.1 | J61: =SUM(J62:J77) -> -4586794.5 | ... Z61: =SUM(Z62:Z77) -> 0 | AA61: =SUM(C61,E61,G61,I61,K61,M61,O122,O61,Q61,S61,Y61,W61,U61) -> -43573130 | AB61: =D61+F61+H61+J61+L61+N61+P61+R61+T61+V61+X61+Z61 -> -22303905 | AC61: =IFERROR(AB61/AA61,0) -> 0.51187292
B62: Доход от столовой | C62: =SUMIFS(data!$G:$G,data!$C:$C,$B$31,data!$D:$D,$B$61,data!$F:$F,C$4,data!$E:$E,$B62,data!$H:$H,ПФ2026!C$5) -> 1169640 | D62: =SUMIFS(data!$G:$G,data!$C:$C,$B$31,data!$D:$D,$B$61,data!$F:$F,C$4,data!$E:$E,$B62,data!$H:$H,ПФ2026!D$5) -> 792076 | E62: =SUMIFS(data!$G:$G,data!$C:$C,$B$31,data!$D:$D,$B$61,data!$F:$F,E$4,data!$E:$E,$B62,data!$H:$H,ПФ2026!E$5) -> 720800 | F62: =SUMIFS(data!$G:$G,data!$C:$C,$B$31,data!$D:$D,$B$61,data!$F:$F,E$4,data!$E:$E,$B62,data!$H:$H,ПФ2026!F$5) -> 698179 | G62: =SUMIFS(data!$G:$G,data!$C:$C,$B$31,data!$D:$D,$B$61,data!$F:$F,G$4,data!$E:$E,$B62,data!$H:$H,ПФ2026!G$5) -> 751275 | H62: =SUMIFS(data!$G:$G,data!$C:$C,$B$31,data!$D:$D,$B$61,data!$F:$F,G$4,data!$E:$E,$B62,data!$H:$H,ПФ2026!H$5) -> 596408 | I62: =SUMIFS(data!$G:$G,data!$C:$C,$B$31,data!$D:$D,$B$61,data!$F:$F,I$4,data!$E:$E,$B62,data!$H:$H,ПФ2026!I$5) -> 1012000 | J62: =SUMIFS(data!$G:$G,data!$C:$C,$B$31,data!$D:$D,$B$61,data!$F:$F,I$4,data!$E:$E,$B62,data!$H:$H,ПФ2026!J$5) -> 1391492.8 | K62: =SUMIFS(data!$G:$G,data!$C:$C,$B$31,data!$D:$D,$B$61,data!$F:$F,K$4,data!$E:$E,$B62,data!$H:$H,ПФ2026!K$5) -> 1650480 | L62: =SUMIFS(data!$G:$G,data!$C:$C,$B$31,data!$D:$D,$B$61,data!$F:$F,K$4,data!$E:$E,$B62,data!$H:$H,ПФ2026!L$5) -> 1191581.2 | M62: =SUMIFS(data!$G:$G,data!$C:$C,$B$31,data!$D:$D,$B$61,data!$F:$F,M$4,data!$E:$E,$B62,data!$H:$H,ПФ2026!M$5) -> 1719250 | N62: =SUMIFS(data!$G:$G,data!$C:$C,$B$31,data!$D:$D,$B$61,data!$F:$F,M$4,data!$E:$E,$B62,data!$H:$H,ПФ2026!N$5) -> 1469060.4 | O62: =SUMIFS(data!$G:$G,data!$C:$C,$B$31,data!$D:$D,$B$61,data!$F:$F,O$4,data!$E:$E,$B62,data!$H:$H,ПФ2026!O$5) -> 1703380 | P62: =SUMIFS(data!$G:$G,data!$C:$C,$B$31,data!$D:$D,$B$61,data!$F:$F,O$4,data!$E:$E,$B62,data!$H:$H,ПФ2026!P$5) -> 0 | Q62: =SUMIFS(data!$G:$G,data!$C:$C,$B$31,data!$D:$D,$B$61,data!$F:$F,Q$4,data!$E:$E,$B62,data!$H:$H,ПФ2026!Q$5) -> 1634610 | R62: =SUMIFS(data!$G:$G,data!$C:$C,$B$31,data!$D:$D,$B$61,data!$F:$F,Q$4,data!$E:$E,$B62,data!$H:$H,ПФ2026!R$5) -> 0 | S62: =SUMIFS(data!$G:$G,data!$C:$C,$B$31,data!$D:$D,$B$61,data!$F:$F,S$4,data!$E:$E,$B62,data!$H:$H,ПФ2026!S$5) -> 1526004 | T62: =SUMIFS(data!$G:$G,data!$C:$C,$B$31,data!$D:$D,$B$61,data!$F:$F,S$4,data!$E:$E,$B62,data!$H:$H,ПФ2026!T$5) -> 0 | U62: =SUMIFS(data!$G:$G,data!$C:$C,$B$31,data!$D:$D,$B$61,data!$F:$F,U$4,data!$E:$E,$B62,data!$H:$H,ПФ2026!U$5) -> 1077384 | V62: =SUMIFS(data!$G:$G,data!$C:$C,$B$31,data!$D:$D,$B$61,data!$F:$F,U$4,data!$E:$E,$B62,data!$H:$H,ПФ2026!V$5) -> 0 | W62: =SUMIFS(data!$G:$G,data!$C:$C,$B$31,data!$D:$D,$B$61,data!$F:$F,W$4,data!$E:$E,$B62,data!$H:$H,ПФ2026!W$5) -> 922320 | X62: =SUMIFS(data!$G:$G,data!$C:$C,$B$31,data!$D:$D,$B$61,data!$F:$F,W$4,data!$E:$E,$B62,data!$H:$H,ПФ2026!X$5) -> 0 | Y62: =SUMIFS(data!$G:$G,data!$C:$C,$B$31,data!$D:$D,$B$61,data!$F:$F,Y$4,data!$E:$E,$B62,data!$H:$H,ПФ2026!Y$5) -> 905004 | Z62: =SUMIFS(data!$G:$G,data!$C:$C,$B$31,data!$D:$D,$B$61,data!$F:$F,Y$4,data!$E:$E,$B62,data!$H:$H,ПФ2026!Z$5) -> 0 | AA62: =SUM(C62,E62,G62,I62,K62,M62,O125,O62,Q62,S62) -> 11886439 | AB62: =SUM(D62,F62,H62,J62,L62,N62,P125,P62,R62,T62) -> 6138797.5 | AC62: =IFERROR(AB62/AA62,0) -> 0.51645388
B63: Основное сырье и материалы | C63: =SUMIFS(data!$G:$G,data!$C:$C,$B$31,data!$D:$D,$B$61,data!$F:$F,C$4,data!$E:$E,$B63,data!$H:$H,ПФ2026!C$5) -> 0 | D63: =SUMIFS(data!$G:$G,data!$C:$C,$B$31,data!$D:$D,$B$61,data!$F:$F,C$4,data!$E:$E,$B63,data!$H:$H,ПФ2026!D$5) -> 0 | E63: =SUMIFS(data!$G:$G,data!$C:$C,$B$31,data!$D:$D,$B$61,data!$F:$F,E$4,data!$E:$E,$B63,data!$H:$H,ПФ2026!E$5) -> 0 | F63: =SUMIFS(data!$G:$G,data!$C:$C,$B$31,data!$D:$D,$B$61,data!$F:$F,E$4,data!$E:$E,$B63,data!$H:$H,ПФ2026!F$5) -> 0 | G63: =SUMIFS(data!$G:$G,data!$C:$C,$B$31,data!$D:$D,$B$61,data!$F:$F,G$4,data!$E:$E,$B63,data!$H:$H,ПФ2026!G$5) -> 0 | H63: =SUMIFS(data!$G:$G,data!$C:$C,$B$31,data!$D:$D,$B$61,data!$F:$F,G$4,data!$E:$E,$B63,data!$H:$H,ПФ2026!H$5) -> 0 | I63: =SUMIFS(data!$G:$G,data!$C:$C,$B$31,data!$D:$D,$B$61,data!$F:$F,I$4,data!$E:$E,$B63,data!$H:$H,ПФ2026!I$5) -> 0 | J63: =SUMIFS(data!$G:$G,data!$C:$C,$B$31,data!$D:$D,$B$61,data!$F:$F,I$4,data!$E:$E,$B63,data!$H:$H,ПФ2026!J$5) -> 0 | K63: =SUMIFS(data!$G:$G,data!$C:$C,$B$31,data!$D:$D,$B$61,data!$F:$F,K$4,data!$E:$E,$B63,data!$H:$H,ПФ2026!K$5) -> 0 | L63: =SUMIFS(data!$G:$G,data!$C:$C,$B$31,data!$D:$D,$B$61,data!$F:$F,K$4,data!$E:$E,$B63,data!$H:$H,ПФ2026!L$5) -> 0 | M63: =SUMIFS(data!$G:$G,data!$C:$C,$B$31,data!$D:$D,$B$61,data!$F:$F,M$4,data!$E:$E,$B63,data!$H:$H,ПФ2026!M$5) -> 0 | N63: =SUMIFS(data!$G:$G,data!$C:$C,$B$31,data!$D:$D,$B$61,data!$F:$F,M$4,data!$E:$E,$B63,data!$H:$H,ПФ2026!N$5) -> 0 | O63: =SUMIFS(data!$G:$G,data!$C:$C,$B$31,data!$D:$D,$B$61,data!$F:$F,O$4,data!$E:$E,$B63,data!$H:$H,ПФ2026!O$5) -> 0 | P63: =SUMIFS(data!$G:$G,data!$C:$C,$B$31,data!$D:$D,$B$61,data!$F:$F,O$4,data!$E:$E,$B63,data!$H:$H,ПФ2026!P$5) -> 0 | Q63: =SUMIFS(data!$G:$G,data!$C:$C,$B$31,data!$D:$D,$B$61,data!$F:$F,Q$4,data!$E:$E,$B63,data!$H:$H,ПФ2026!Q$5) -> 0 | R63: =SUMIFS(data!$G:$G,data!$C:$C,$B$31,data!$D:$D,$B$61,data!$F:$F,Q$4,data!$E:$E,$B63,data!$H:$H,ПФ2026!R$5) -> 0 | S63: =SUMIFS(data!$G:$G,data!$C:$C,$B$31,data!$D:$D,$B$61,data!$F:$F,S$4,data!$E:$E,$B63,data!$H:$H,ПФ2026!S$5) -> 0 | T63: =SUMIFS(data!$G:$G,data!$C:$C,$B$31,data!$D:$D,$B$61,data!$F:$F,S$4,data!$E:$E,$B63,data!$H:$H,ПФ2026!T$5) -> 0 | U63: =SUMIFS(data!$G:$G,data!$C:$C,$B$31,data!$D:$D,$B$61,data!$F:$F,U$4,data!$E:$E,$B63,data!$H:$H,ПФ2026!U$5) -> 0 | V63: =SUMIFS(data!$G:$G,data!$C:$C,$B$31,data!$D:$D,$B$61,data!$F:$F,U$4,data!$E:$E,$B63,data!$H:$H,ПФ2026!V$5) -> 0 | W63: =SUMIFS(data!$G:$G,data!$C:$C,$B$31,data!$D:$D,$B$61,data!$F:$F,W$4,data!$E:$E,$B63,data!$H:$H,ПФ2026!W$5) -> 0 | X63: =SUMIFS(data!$G:$G,data!$C:$C,$B$31,data!$D:$D,$B$61,data!$F:$F,W$4,data!$E:$E,$B63,data!$H:$H,ПФ2026!X$5) -> 0 | Y63: =SUMIFS(data!$G:$G,data!$C:$C,$B$31,data!$D:$D,$B$61,data!$F:$F,Y$4,data!$E:$E,$B63,data!$H:$H,ПФ2026!Y$5) -> 0 | Z63: =SUMIFS(data!$G:$G,data!$C:$C,$B$31,data!$D:$D,$B$61,data!$F:$F,Y$4,data!$E:$E,$B63,data!$H:$H,ПФ2026!Z$5) -> 0 | AA63: =SUM(C63,E63,G63,I63,K63,M63,O126,O63,Q63,S63) -> -75000 | AB63: =SUM(D63,F63,H63,J63,L63,N63,P126,P63,R63,T63) -> 0 | AC63: =IFERROR(AB63/AA63,0) -> 0
B64: Наем разнорабочих | C64: =SUMIFS(data!$G:$G,data!$C:$C,$B$31,data!$D:$D,$B$61,data!$F:$F,C$4,data!$E:$E,$B64,data!$H:$H,ПФ2026!C$5) -> 0 | D64: =SUMIFS(data!$G:$G,data!$C:$C,$B$31,data!$D:$D,$B$61,data!$F:$F,C$4,data!$E:$E,$B64,data!$H:$H,ПФ2026!D$5) -> 0 | E64: =SUMIFS(data!$G:$G,data!$C:$C,$B$31,data!$D:$D,$B$61,data!$F:$F,E$4,data!$E:$E,$B64,data!$H:$H,ПФ2026!E$5) -> 0 | F64: =SUMIFS(data!$G:$G,data!$C:$C,$B$31,data!$D:$D,$B$61,data!$F:$F,E$4,data!$E:$E,$B64,data!$H:$H,ПФ2026!F$5) -> 0 | G64: =SUMIFS(data!$G:$G,data!$C:$C,$B$31,data!$D:$D,$B$61,data!$F:$F,G$4,data!$E:$E,$B64,data!$H:$H,ПФ2026!G$5) -> 0 | H64: =SUMIFS(data!$G:$G,data!$C:$C,$B$31,data!$D:$D,$B$61,data!$F:$F,G$4,data!$E:$E,$B64,data!$H:$H,ПФ2026!H$5) -> 0 | I64: =SUMIFS(data!$G:$G,data!$C:$C,$B$31,data!$D:$D,$B$61,data!$F:$F,I$4,data!$E:$E,$B64,data!$H:$H,ПФ2026!I$5) -> 0 | J64: =SUMIFS(data!$G:$G,data!$C:$C,$B$31,data!$D:$D,$B$61,data!$F:$F,I$4,data!$E:$E,$B64,data!$H:$H,ПФ2026!J$5) -> 0 | K64: =SUMIFS(data!$G:$G,data!$C:$C,$B$31,data!$D:$D,$B$61,data!$F:$F,K$4,data!$E:$E,$B64,data!$H:$H,ПФ2026!K$5) -> 0 | L64: =SUMIFS(data!$G:$G,data!$C:$C,$B$31,data!$D:$D,$B$61,data!$F:$F,K$4,data!$E:$E,$B64,data!$H:$H,ПФ2026!L$5) -> 0 | M64: =SUMIFS(data!$G:$G,data!$C:$C,$B$31,data!$D:$D,$B$61,data!$F:$F,M$4,data!$E:$E,$B64,data!$H:$H,ПФ2026!M$5) -> 0 | N64: =SUMIFS(data!$G:$G,data!$C:$C,$B$31,data!$D:$D,$B$61,data!$F:$F,M$4,data!$E:$E,$B64,data!$H:$H,ПФ2026!N$5) -> 0 | O64: =SUMIFS(data!$G:$G,data!$C:$C,$B$31,data!$D:$D,$B$61,data!$F:$F,O$4,data!$E:$E,$B64,data!$H:$H,ПФ2026!O$5) -> 0 | P64: =SUMIFS(data!$G:$G,data!$C:$C,$B$31,data!$D:$D,$B$61,data!$F:$F,O$4,data!$E:$E,$B64,data!$H:$H,ПФ2026!P$5) -> 0 | Q64: =SUMIFS(data!$G:$G,data!$C:$C,$B$31,data!$D:$D,$B$61,data!$F:$F,Q$4,data!$E:$E,$B64,data!$H:$H,ПФ2026!Q$5) -> 0 | R64: =SUMIFS(data!$G:$G,data!$C:$C,$B$31,data!$D:$D,$B$61,data!$F:$F,Q$4,data!$E:$E,$B64,data!$H:$H,ПФ2026!R$5) -> 0 | S64: =SUMIFS(data!$G:$G,data!$C:$C,$B$31,data!$D:$D,$B$61,data!$F:$F,S$4,data!$E:$E,$B64,data!$H:$H,ПФ2026!S$5) -> 0 | T64: =SUMIFS(data!$G:$G,data!$C:$C,$B$31,data!$D:$D,$B$61,data!$F:$F,S$4,data!$E:$E,$B64,data!$H:$H,ПФ2026!T$5) -> 0 | U64: =SUMIFS(data!$G:$G,data!$C:$C,$B$31,data!$D:$D,$B$61,data!$F:$F,U$4,data!$E:$E,$B64,data!$H:$H,ПФ2026!U$5) -> 0 | V64: =SUMIFS(data!$G:$G,data!$C:$C,$B$31,data!$D:$D,$B$61,data!$F:$F,U$4,data!$E:$E,$B64,data!$H:$H,ПФ2026!V$5) -> 0 | W64: =SUMIFS(data!$G:$G,data!$C:$C,$B$31,data!$D:$D,$B$61,data!$F:$F,W$4,data!$E:$E,$B64,data!$H:$H,ПФ2026!W$5) -> 0 | X64: =SUMIFS(data!$G:$G,data!$C:$C,$B$31,data!$D:$D,$B$61,data!$F:$F,W$4,data!$E:$E,$B64,data!$H:$H,ПФ2026!X$5) -> 0 | Y64: =SUMIFS(data!$G:$G,data!$C:$C,$B$31,data!$D:$D,$B$61,data!$F:$F,Y$4,data!$E:$E,$B64,data!$H:$H,ПФ2026!Y$5) -> 0 | Z64: =SUMIFS(data!$G:$G,data!$C:$C,$B$31,data!$D:$D,$B$61,data!$F:$F,Y$4,data!$E:$E,$B64,data!$H:$H,ПФ2026!Z$5) -> 0 | AA64: =SUM(C64,E64,G64,I64,K64,M64,O128,O64,Q64,S64) -> -5000 | AB64: =SUM(D64,F64,H64,J64,L64,N64,P128,P64,R64,T64) -> 0 | AC64: =IFERROR(AB64/AA64,0) -> 0
B65: Недостача | C65: =SUMIFS(data!$G:$G,data!$C:$C,$B$31,data!$D:$D,$B$61,data!$F:$F,C$4,data!$E:$E,$B65,data!$H:$H,ПФ2026!C$5) -> 0 | D65: =SUMIFS(data!$G:$G,data!$C:$C,$B$31,data!$D:$D,$B$61,data!$F:$F,C$4,data!$E:$E,$B65,data!$H:$H,ПФ2026!D$5) -> 0 | E65: =SUMIFS(data!$G:$G,data!$C:$C,$B$31,data!$D:$D,$B$61,data!$F:$F,E$4,data!$E:$E,$B65,data!$H:$H,ПФ2026!E$5) -> 0 | F65: =SUMIFS(data!$G:$G,data!$C:$C,$B$31,data!$D:$D,$B$61,data!$F:$F,E$4,data!$E:$E,$B65,data!$H:$H,ПФ2026!F$5) -> 0 | G65: =SUMIFS(data!$G:$G,data!$C:$C,$B$31,data!$D:$D,$B$61,data!$F:$F,G$4,data!$E:$E,$B65,data!$H:$H,ПФ2026!G$5) -> 0 | H65: =SUMIFS(data!$G:$G,data!$C:$C,$B$31,data!$D:$D,$B$61,data!$F:$F,G$4,data!$E:$E,$B65,data!$H:$H,ПФ2026!H$5) -> 0 | I65: =SUMIFS(data!$G:$G,data!$C:$C,$B$31,data!$D:$D,$B$61,data!$F:$F,I$4,data!$E:$E,$B65,data!$H:$H,ПФ2026!I$5) -> 0 | J65: =SUMIFS(data!$G:$G,data!$C:$C,$B$31,data!$D:$D,$B$61,data!$F:$F,I$4,data!$E:$E,$B65,data!$H:$H,ПФ2026!J$5) -> 0 | K65: =SUMIFS(data!$G:$G,data!$C:$C,$B$31,data!$D:$D,$B$61,data!$F:$F,K$4,data!$E:$E,$B65,data!$H:$H,ПФ2026!K$5) -> 0 | L65: =SUMIFS(data!$G:$G,data!$C:$C,$B$31,data!$D:$D,$B$61,data!$F:$F,K$4,data!$E:$E,$B65,data!$H:$H,ПФ2026!L$5) -> 0 | M65: =SUMIFS(data!$G:$G,data!$C:$C,$B$31,data!$D:$D,$B$61,data!$F:$F,M$4,data!$E:$E,$B65,data!$H:$H,ПФ2026!M$5) -> 0 | N65: =SUMIFS(data!$G:$G,data!$C:$C,$B$31,data!$D:$D,$B$61,data!$F:$F,M$4,data!$E:$E,$B65,data!$H:$H,ПФ2026!N$5) -> 0 | O65: =SUMIFS(data!$G:$G,data!$C:$C,$B$31,data!$D:$D,$B$61,data!$F:$F,O$4,data!$E:$E,$B65,data!$H:$H,ПФ2026!O$5) -> 0 | P65: =SUMIFS(data!$G:$G,data!$C:$C,$B$31,data!$D:$D,$B$61,data!$F:$F,O$4,data!$E:$E,$B65,data!$H:$H,ПФ2026!P$5) -> 0 | Q65: =SUMIFS(data!$G:$G,data!$C:$C,$B$31,data!$D:$D,$B$61,data!$F:$F,Q$4,data!$E:$E,$B65,data!$H:$H,ПФ2026!Q$5) -> 0 | R65: =SUMIFS(data!$G:$G,data!$C:$C,$B$31,data!$D:$D,$B$61,data!$F:$F,Q$4,data!$E:$E,$B65,data!$H:$H,ПФ2026!R$5) -> 0 | S65: =SUMIFS(data!$G:$G,data!$C:$C,$B$31,data!$D:$D,$B$61,data!$F:$F,S$4,data!$E:$E,$B65,data!$H:$H,ПФ2026!S$5) -> 0 | T65: =SUMIFS(data!$G:$G,data!$C:$C,$B$31,data!$D:$D,$B$61,data!$F:$F,S$4,data!$E:$E,$B65,data!$H:$H,ПФ2026!T$5) -> 0 | U65: =SUMIFS(data!$G:$G,data!$C:$C,$B$31,data!$D:$D,$B$61,data!$F:$F,U$4,data!$E:$E,$B65,data!$H:$H,ПФ2026!U$5) -> 0 | V65: =SUMIFS(data!$G:$G,data!$C:$C,$B$31,data!$D:$D,$B$61,data!$F:$F,U$4,data!$E:$E,$B65,data!$H:$H,ПФ2026!V$5) -> 0 | W65: =SUMIFS(data!$G:$G,data!$C:$C,$B$31,data!$D:$D,$B$61,data!$F:$F,W$4,data!$E:$E,$B65,data!$H:$H,ПФ2026!W$5) -> 0 | X65: =SUMIFS(data!$G:$G,data!$C:$C,$B$31,data!$D:$D,$B$61,data!$F:$F,W$4,data!$E:$E,$B65,data!$H:$H,ПФ2026!X$5) -> 0 | Y65: =SUMIFS(data!$G:$G,data!$C:$C,$B$31,data!$D:$D,$B$61,data!$F:$F,Y$4,data!$E:$E,$B65,data!$H:$H,ПФ2026!Y$5) -> 0 | Z65: =SUMIFS(data!$G:$G,data!$C:$C,$B$31,data!$D:$D,$B$61,data!$F:$F,Y$4,data!$E:$E,$B65,data!$H:$H,ПФ2026!Z$5) -> 0 | AA65: =SUM(C65,E65,G65,I65,K65,M65,O129,O65,Q65,S65) -> 0 | AB65: =SUM(D65,F65,H65,J65,L65,N65,P129,P65,R65,T65) -> 0 | AC65: =IFERROR(AB65/AA65,0) -> 0
B66: Оформление документов | C66: =SUMIFS(data!$G:$G,data!$C:$C,$B$31,data!$D:$D,$B$61,data!$F:$F,C$4,data!$E:$E,$B66,data!$H:$H,ПФ2026!C$5) -> 0 | D66: =SUMIFS(data!$G:$G,data!$C:$C,$B$31,data!$D:$D,$B$61,data!$F:$F,C$4,data!$E:$E,$B66,data!$H:$H,ПФ2026!D$5) -> 0 | E66: =SUMIFS(data!$G:$G,data!$C:$C,$B$31,data!$D:$D,$B$61,data!$F:$F,E$4,data!$E:$E,$B66,data!$H:$H,ПФ2026!E$5) -> 0 | F66: =SUMIFS(data!$G:$G,data!$C:$C,$B$31,data!$D:$D,$B$61,data!$F:$F,E$4,data!$E:$E,$B66,data!$H:$H,ПФ2026!F$5) -> 0 | G66: =SUMIFS(data!$G:$G,data!$C:$C,$B$31,data!$D:$D,$B$61,data!$F:$F,G$4,data!$E:$E,$B66,data!$H:$H,ПФ2026!G$5) -> 0 | H66: =SUMIFS(data!$G:$G,data!$C:$C,$B$31,data!$D:$D,$B$61,data!$F:$F,G$4,data!$E:$E,$B66,data!$H:$H,ПФ2026!H$5) -> 0 | I66: =SUMIFS(data!$G:$G,data!$C:$C,$B$31,data!$D:$D,$B$61,data!$F:$F,I$4,data!$E:$E,$B66,data!$H:$H,ПФ2026!I$5) -> 0 | J66: =SUMIFS(data!$G:$G,data!$C:$C,$B$31,data!$D:$D,$B$61,data!$F:$F,I$4,data!$E:$E,$B66,data!$H:$H,ПФ2026!J$5) -> 0 | K66: =SUMIFS(data!$G:$G,data!$C:$C,$B$31,data!$D:$D,$B$61,data!$F:$F,K$4,data!$E:$E,$B66,data!$H:$H,ПФ2026!K$5) -> 0 | L66: =SUMIFS(data!$G:$G,data!$C:$C,$B$31,data!$D:$D,$B$61,data!$F:$F,K$4,data!$E:$E,$B66,data!$H:$H,ПФ2026!L$5) -> 0 | M66: =SUMIFS(data!$G:$G,data!$C:$C,$B$31,data!$D:$D,$B$61,data!$F:$F,M$4,data!$E:$E,$B66,data!$H:$H,ПФ2026!M$5) -> 0 | N66: =SUMIFS(data!$G:$G,data!$C:$C,$B$31,data!$D:$D,$B$61,data!$F:$F,M$4,data!$E:$E,$B66,data!$H:$H,ПФ2026!N$5) -> 0 | O66: =SUMIFS(data!$G:$G,data!$C:$C,$B$31,data!$D:$D,$B$61,data!$F:$F,O$4,data!$E:$E,$B66,data!$H:$H,ПФ2026!O$5) -> 0 | P66: =SUMIFS(data!$G:$G,data!$C:$C,$B$31,data!$D:$D,$B$61,data!$F:$F,O$4,data!$E:$E,$B66,data!$H:$H,ПФ2026!P$5) -> 0 | Q66: =SUMIFS(data!$G:$G,data!$C:$C,$B$31,data!$D:$D,$B$61,data!$F:$F,Q$4,data!$E:$E,$B66,data!$H:$H,ПФ2026!Q$5) -> 0 | R66: =SUMIFS(data!$G:$G,data!$C:$C,$B$31,data!$D:$D,$B$61,data!$F:$F,Q$4,data!$E:$E,$B66,data!$H:$H,ПФ2026!R$5) -> 0 | S66: =SUMIFS(data!$G:$G,data!$C:$C,$B$31,data!$D:$D,$B$61,data!$F:$F,S$4,data!$E:$E,$B66,data!$H:$H,ПФ2026!S$5) -> 0 | T66: =SUMIFS(data!$G:$G,data!$C:$C,$B$31,data!$D:$D,$B$61,data!$F:$F,S$4,data!$E:$E,$B66,data!$H:$H,ПФ2026!T$5) -> 0 | U66: =SUMIFS(data!$G:$G,data!$C:$C,$B$31,data!$D:$D,$B$61,data!$F:$F,U$4,data!$E:$E,$B66,data!$H:$H,ПФ2026!U$5) -> 0 | V66: =SUMIFS(data!$G:$G,data!$C:$C,$B$31,data!$D:$D,$B$61,data!$F:$F,U$4,data!$E:$E,$B66,data!$H:$H,ПФ2026!V$5) -> 0 | W66: =SUMIFS(data!$G:$G,data!$C:$C,$B$31,data!$D:$D,$B$61,data!$F:$F,W$4,data!$E:$E,$B66,data!$H:$H,ПФ2026!W$5) -> 0 | X66: =SUMIFS(data!$G:$G,data!$C:$C,$B$31,data!$D:$D,$B$61,data!$F:$F,W$4,data!$E:$E,$B66,data!$H:$H,ПФ2026!X$5) -> 0 | Y66: =SUMIFS(data!$G:$G,data!$C:$C,$B$31,data!$D:$D,$B$61,data!$F:$F,Y$4,data!$E:$E,$B66,data!$H:$H,ПФ2026!Y$5) -> 0 | Z66: =SUMIFS(data!$G:$G,data!$C:$C,$B$31,data!$D:$D,$B$61,data!$F:$F,Y$4,data!$E:$E,$B66,data!$H:$H,ПФ2026!Z$5) -> 0 | AA66: =SUM(C66,E66,G66,I66,K66,M66,O129,O66,Q66,S66) -> 0 | AB66: =SUM(D66,F66,H66,J66,L66,N66,P129,P66,R66,T66) -> 0 | AC66: =IFERROR(AB66/AA66,0) -> 0
B67: Патенты | C67: =SUMIFS(data!$G:$G,data!$C:$C,$B$31,data!$D:$D,$B$61,data!$F:$F,C$4,data!$E:$E,$B67,data!$H:$H,ПФ2026!C$5) -> 0 | D67: =SUMIFS(data!$G:$G,data!$C:$C,$B$31,data!$D:$D,$B$61,data!$F:$F,C$4,data!$E:$E,$B67,data!$H:$H,ПФ2026!D$5) -> -11036 | E67: =SUMIFS(data!$G:$G,data!$C:$C,$B$31,data!$D:$D,$B$61,data!$F:$F,E$4,data!$E:$E,$B67,data!$H:$H,ПФ2026!E$5) -> 0 | F67: =SUMIFS(data!$G:$G,data!$C:$C,$B$31,data!$D:$D,$B$61,data!$F:$F,E$4,data!$E:$E,$B67,data!$H:$H,ПФ2026!F$5) -> 0 | G67: =SUMIFS(data!$G:$G,data!$C:$C,$B$31,data!$D:$D,$B$61,data!$F:$F,G$4,data!$E:$E,$B67,data!$H:$H,ПФ2026!G$5) -> -100000 | H67: =SUMIFS(data!$G:$G,data!$C:$C,$B$31,data!$D:$D,$B$61,data!$F:$F,G$4,data!$E:$E,$B67,data!$H:$H,ПФ2026!H$5) -> 0 | I67: =SUMIFS(data!$G:$G,data!$C:$C,$B$31,data!$D:$D,$B$61,data!$F:$F,I$4,data!$E:$E,$B67,data!$H:$H,ПФ2026!I$5) -> 0 | J67: =SUMIFS(data!$G:$G,data!$C:$C,$B$31,data!$D:$D,$B$61,data!$F:$F,I$4,data!$E:$E,$B67,data!$H:$H,ПФ2026!J$5) -> 0 | K67: =SUMIFS(data!$G:$G,data!$C:$C,$B$31,data!$D:$D,$B$61,data!$F:$F,K$4,data!$E:$E,$B67,data!$H:$H,ПФ2026!K$5) -> 0 | L67: =SUMIFS(data!$G:$G,data!$C:$C,$B$31,data!$D:$D,$B$61,data!$F:$F,K$4,data!$E:$E,$B67,data!$H:$H,ПФ2026!L$5) -> -32206 | M67: =SUMIFS(data!$G:$G,data!$C:$C,$B$31,data!$D:$D,$B$61,data!$F:$F,M$4,data!$E:$E,$B67,data!$H:$H,ПФ2026!M$5) -> -100000 | N67: =SUMIFS(data!$G:$G,data!$C:$C,$B$31,data!$D:$D,$B$61,data!$F:$F,M$4,data!$E:$E,$B67,data!$H:$H,ПФ2026!N$5) -> -2700 | O67: =SUMIFS(data!$G:$G,data!$C:$C,$B$31,data!$D:$D,$B$61,data!$F:$F,O$4,data!$E:$E,$B67,data!$H:$H,ПФ2026!O$5) -> 0 | P67: =SUMIFS(data!$G:$G,data!$C:$C,$B$31,data!$D:$D,$B$61,data!$F:$F,O$4,data!$E:$E,$B67,data!$H:$H,ПФ2026!P$5) -> 0 | Q67: =SUMIFS(data!$G:$G,data!$C:$C,$B$31,data!$D:$D,$B$61,data!$F:$F,Q$4,data!$E:$E,$B67,data!$H:$H,ПФ2026!Q$5) -> 0 | R67: =SUMIFS(data!$G:$G,data!$C:$C,$B$31,data!$D:$D,$B$61,data!$F:$F,Q$4,data!$E:$E,$B67,data!$H:$H,ПФ2026!R$5) -> 0 | S67: =SUMIFS(data!$G:$G,data!$C:$C,$B$31,data!$D:$D,$B$61,data!$F:$F,S$4,data!$E:$E,$B67,data!$H:$H,ПФ2026!S$5) -> -100000 | T67: =SUMIFS(data!$G:$G,data!$C:$C,$B$31,data!$D:$D,$B$61,data!$F:$F,S$4,data!$E:$E,$B67,data!$H:$H,ПФ2026!T$5) -> 0 | U67: =SUMIFS(data!$G:$G,data!$C:$C,$B$31,data!$D:$D,$B$61,data!$F:$F,U$4,data!$E:$E,$B67,data!$H:$H,ПФ2026!U$5) -> 0 | V67: =SUMIFS(data!$G:$G,data!$C:$C,$B$31,data!$D:$D,$B$61,data!$F:$F,U$4,data!$E:$E,$B67,data!$H:$H,ПФ2026!V$5) -> 0 | W67: =SUMIFS(data!$G:$G,data!$C:$C,$B$31,data!$D:$D,$B$61,data!$F:$F,W$4,data!$E:$E,$B67,data!$H:$H,ПФ2026!W$5) -> 0 | X67: =SUMIFS(data!$G:$G,data!$C:$C,$B$31,data!$D:$D,$B$61,data!$F:$F,W$4,data!$E:$E,$B67,data!$H:$H,ПФ2026!X$5) -> 0 | Y67: =SUMIFS(data!$G:$G,data!$C:$C,$B$31,data!$D:$D,$B$61,data!$F:$F,Y$4,data!$E:$E,$B67,data!$H:$H,ПФ2026!Y$5) -> -100000 | Z67: =SUMIFS(data!$G:$G,data!$C:$C,$B$31,data!$D:$D,$B$61,data!$F:$F,Y$4,data!$E:$E,$B67,data!$H:$H,ПФ2026!Z$5) -> 0 | AA67: =SUM(C67,E67,G67,I67,K67,M67,O130,O67,Q67,S67) -> -300000 | AB67: =SUM(D67,F67,H67,J67,L67,N67,P130,P67,R67,T67) -> -45942 | AC67: =IFERROR(AB67/AA67,0) -> 0.15314
B68: Продукция для сотрудников | C68: =SUMIFS(data!$G:$G,data!$C:$C,$B$31,data!$D:$D,$B$61,data!$F:$F,C$4,data!$E:$E,$B68,data!$H:$H,ПФ2026!C$5) -> -1000 | D68: =SUMIFS(data!$G:$G,data!$C:$C,$B$31,data!$D:$D,$B$61,data!$F:$F,C$4,data!$E:$E,$B68,data!$H:$H,ПФ2026!D$5) -> 0 | E68: =SUMIFS(data!$G:$G,data!$C:$C,$B$31,data!$D:$D,$B$61,data!$F:$F,E$4,data!$E:$E,$B68,data!$H:$H,ПФ2026!E$5) -> -1000 | F68: =SUMIFS(data!$G:$G,data!$C:$C,$B$31,data!$D:$D,$B$61,data!$F:$F,E$4,data!$E:$E,$B68,data!$H:$H,ПФ2026!F$5) -> 0 | G68: =SUMIFS(data!$G:$G,data!$C:$C,$B$31,data!$D:$D,$B$61,data!$F:$F,G$4,data!$E:$E,$B68,data!$H:$H,ПФ2026!G$5) -> -1000 | H68: =SUMIFS(data!$G:$G,data!$C:$C,$B$31,data!$D:$D,$B$61,data!$F:$F,G$4,data!$E:$E,$B68,data!$H:$H,ПФ2026!H$5) -> 0 | I68: =SUMIFS(data!$G:$G,data!$C:$C,$B$31,data!$D:$D,$B$61,data!$F:$F,I$4,data!$E:$E,$B68,data!$H:$H,ПФ2026!I$5) -> -1000 | J68: =SUMIFS(data!$G:$G,data!$C:$C,$B$31,data!$D:$D,$B$61,data!$F:$F,I$4,data!$E:$E,$B68,data!$H:$H,ПФ2026!J$5) -> 0 | K68: =SUMIFS(data!$G:$G,data!$C:$C,$B$31,data!$D:$D,$B$61,data!$F:$F,K$4,data!$E:$E,$B68,data!$H:$H,ПФ2026!K$5) -> -1000 | L68: =SUMIFS(data!$G:$G,data!$C:$C,$B$31,data!$D:$D,$B$61,data!$F:$F,K$4,data!$E:$E,$B68,data!$H:$H,ПФ2026!L$5) -> -66.6 | M68: =SUMIFS(data!$G:$G,data!$C:$C,$B$31,data!$D:$D,$B$61,data!$F:$F,M$4,data!$E:$E,$B68,data!$H:$H,ПФ2026!M$5) -> -1000 | N68: =SUMIFS(data!$G:$G,data!$C:$C,$B$31,data!$D:$D,$B$61,data!$F:$F,M$4,data!$E:$E,$B68,data!$H:$H,ПФ2026!N$5) -> -45.6 | O68: =SUMIFS(data!$G:$G,data!$C:$C,$B$31,data!$D:$D,$B$61,data!$F:$F,O$4,data!$E:$E,$B68,data!$H:$H,ПФ2026!O$5) -> -1000 | P68: =SUMIFS(data!$G:$G,data!$C:$C,$B$31,data!$D:$D,$B$61,data!$F:$F,O$4,data!$E:$E,$B68,data!$H:$H,ПФ2026!P$5) -> 0 | Q68: =SUMIFS(data!$G:$G,data!$C:$C,$B$31,data!$D:$D,$B$61,data!$F:$F,Q$4,data!$E:$E,$B68,data!$H:$H,ПФ2026!Q$5) -> -1000 | R68: =SUMIFS(data!$G:$G,data!$C:$C,$B$31,data!$D:$D,$B$61,data!$F:$F,Q$4,data!$E:$E,$B68,data!$H:$H,ПФ2026!R$5) -> 0 | S68: =SUMIFS(data!$G:$G,data!$C:$C,$B$31,data!$D:$D,$B$61,data!$F:$F,S$4,data!$E:$E,$B68,data!$H:$H,ПФ2026!S$5) -> -1000 | T68: =SUMIFS(data!$G:$G,data!$C:$C,$B$31,data!$D:$D,$B$61,data!$F:$F,S$4,data!$E:$E,$B68,data!$H:$H,ПФ2026!T$5) -> 0 | U68: =SUMIFS(data!$G:$G,data!$C:$C,$B$31,data!$D:$D,$B$61,data!$F:$F,U$4,data!$E:$E,$B68,data!$H:$H,ПФ2026!U$5) -> -1000 | V68: =SUMIFS(data!$G:$G,data!$C:$C,$B$31,data!$D:$D,$B$61,data!$F:$F,U$4,data!$E:$E,$B68,data!$H:$H,ПФ2026!V$5) -> 0 | W68: =SUMIFS(data!$G:$G,data!$C:$C,$B$31,data!$D:$D,$B$61,data!$F:$F,W$4,data!$E:$E,$B68,data!$H:$H,ПФ2026!W$5) -> -1000 | X68: =SUMIFS(data!$G:$G,data!$C:$C,$B$31,data!$D:$D,$B$61,data!$F:$F,W$4,data!$E:$E,$B68,data!$H:$H,ПФ2026!X$5) -> 0 | Y68: =SUMIFS(data!$G:$G,data!$C:$C,$B$31,data!$D:$D,$B$61,data!$F:$F,Y$4,data!$E:$E,$B68,data!$H:$H,ПФ2026!Y$5) -> -1000 | Z68: =SUMIFS(data!$G:$G,data!$C:$C,$B$31,data!$D:$D,$B$61,data!$F:$F,Y$4,data!$E:$E,$B68,data!$H:$H,ПФ2026!Z$5) -> 0 | AA68: =SUM(C68,E68,G68,I68,K68,M68,O131,O68,Q68,S68) -> -9000 | AB68: =SUM(D68,F68,H68,J68,L68,N68,P131,P68,R68,T68) -> -112.2 | AC68: =IFERROR(AB68/AA68,0) -> 0.012466667
B69: Прочие материалы и МБП | C69: =SUMIFS(data!$G:$G,data!$C:$C,$B$31,data!$D:$D,$B$61,data!$F:$F,C$4,data!$E:$E,$B69,data!$H:$H,ПФ2026!C$5) -> -920000 | D69: =SUMIFS(data!$G:$G,data!$C:$C,$B$31,data!$D:$D,$B$61,data!$F:$F,C$4,data!$E:$E,$B69,data!$H:$H,ПФ2026!D$5) -> -10959.47 | E69: =SUMIFS(data!$G:$G,data!$C:$C,$B$31,data!$D:$D,$B$61,data!$F:$F,E$4,data!$E:$E,$B69,data!$H:$H,ПФ2026!E$5) -> -20000 | F69: =SUMIFS(data!$G:$G,data!$C:$C,$B$31,data!$D:$D,$B$61,data!$F:$F,E$4,data!$E:$E,$B69,data!$H:$H,ПФ2026!F$5) -> -2990 | G69: =SUMIFS(data!$G:$G,data!$C:$C,$B$31,data!$D:$D,$B$61,data!$F:$F,G$4,data!$E:$E,$B69,data!$H:$H,ПФ2026!G$5) -> -20000 | H69: =SUMIFS(data!$G:$G,data!$C:$C,$B$31,data!$D:$D,$B$61,data!$F:$F,G$4,data!$E:$E,$B69,data!$H:$H,ПФ2026!H$5) -> 0 | I69: =SUMIFS(data!$G:$G,data!$C:$C,$B$31,data!$D:$D,$B$61,data!$F:$F,I$4,data!$E:$E,$B69,data!$H:$H,ПФ2026!I$5) -> -20000 | J69: =SUMIFS(data!$G:$G,data!$C:$C,$B$31,data!$D:$D,$B$61,data!$F:$F,I$4,data!$E:$E,$B69,data!$H:$H,ПФ2026!J$5) -> 0 | K69: =SUMIFS(data!$G:$G,data!$C:$C,$B$31,data!$D:$D,$B$61,data!$F:$F,K$4,data!$E:$E,$B69,data!$H:$H,ПФ2026!K$5) -> -20000 | L69: =SUMIFS(data!$G:$G,data!$C:$C,$B$31,data!$D:$D,$B$61,data!$F:$F,K$4,data!$E:$E,$B69,data!$H:$H,ПФ2026!L$5) -> -211267.72 | M69: =SUMIFS(data!$G:$G,data!$C:$C,$B$31,data!$D:$D,$B$61,data!$F:$F,M$4,data!$E:$E,$B69,data!$H:$H,ПФ2026!M$5) -> -20000 | N69: =SUMIFS(data!$G:$G,data!$C:$C,$B$31,data!$D:$D,$B$61,data!$F:$F,M$4,data!$E:$E,$B69,data!$H:$H,ПФ2026!N$5) -> -322925.53 | O69: =SUMIFS(data!$G:$G,data!$C:$C,$B$31,data!$D:$D,$B$61,data!$F:$F,O$4,data!$E:$E,$B69,data!$H:$H,ПФ2026!O$5) -> -20000 | P69: =SUMIFS(data!$G:$G,data!$C:$C,$B$31,data!$D:$D,$B$61,data!$F:$F,O$4,data!$E:$E,$B69,data!$H:$H,ПФ2026!P$5) -> 0 | Q69: =SUMIFS(data!$G:$G,data!$C:$C,$B$31,data!$D:$D,$B$61,data!$F:$F,Q$4,data!$E:$E,$B69,data!$H:$H,ПФ2026!Q$5) -> -20000 | R69: =SUMIFS(data!$G:$G,data!$C:$C,$B$31,data!$D:$D,$B$61,data!$F:$F,Q$4,data!$E:$E,$B69,data!$H:$H,ПФ2026!R$5) -> 0 | S69: =SUMIFS(data!$G:$G,data!$C:$C,$B$31,data!$D:$D,$B$61,data!$F:$F,S$4,data!$E:$E,$B69,data!$H:$H,ПФ2026!S$5) -> -20000 | T69: =SUMIFS(data!$G:$G,data!$C:$C,$B$31,data!$D:$D,$B$61,data!$F:$F,S$4,data!$E:$E,$B69,data!$H:$H,ПФ2026!T$5) -> 0 | U69: =SUMIFS(data!$G:$G,data!$C:$C,$B$31,data!$D:$D,$B$61,data!$F:$F,U$4,data!$E:$E,$B69,data!$H:$H,ПФ2026!U$5) -> -20000 | V69: =SUMIFS(data!$G:$G,data!$C:$C,$B$31,data!$D:$D,$B$61,data!$F:$F,U$4,data!$E:$E,$B69,data!$H:$H,ПФ2026!V$5) -> 0 | W69: =SUMIFS(data!$G:$G,data!$C:$C,$B$31,data!$D:$D,$B$61,data!$F:$F,W$4,data!$E:$E,$B69,data!$H:$H,ПФ2026!W$5) -> -20000 | X69: =SUMIFS(data!$G:$G,data!$C:$C,$B$31,data!$D:$D,$B$61,data!$F:$F,W$4,data!$E:$E,$B69,data!$H:$H,ПФ2026!X$5) -> 0 | Y69: =SUMIFS(data!$G:$G,data!$C:$C,$B$31,data!$D:$D,$B$61,data!$F:$F,Y$4,data!$E:$E,$B69,data!$H:$H,ПФ2026!Y$5) -> -20000 | Z69: =SUMIFS(data!$G:$G,data!$C:$C,$B$31,data!$D:$D,$B$61,data!$F:$F,Y$4,data!$E:$E,$B69,data!$H:$H,ПФ2026!Z$5) -> 0 | AA69: =SUM(C69,E69,G69,I69,K69,M69,O133,O69,Q69,S69) -> -1080000 | AB69: =SUM(D69,F69,H69,J69,L69,N69,P133,P69,R69,T69) -> -548142.72 | AC69: =IFERROR(AB69/AA69,0) -> 0.50753956
B70: Расходы на питание | C70: =SUMIFS(data!$G:$G,data!$C:$C,$B$31,data!$D:$D,$B$61,data!$F:$F,C$4,data!$E:$E,$B70,data!$H:$H,ПФ2026!C$5) -> -1119040 | D70: =SUMIFS(data!$G:$G,data!$C:$C,$B$31,data!$D:$D,$B$61,data!$F:$F,C$4,data!$E:$E,$B70,data!$H:$H,ПФ2026!D$5) -> -957208 | E70: =SUMIFS(data!$G:$G,data!$C:$C,$B$31,data!$D:$D,$B$61,data!$F:$F,E$4,data!$E:$E,$B70,data!$H:$H,ПФ2026!E$5) -> -1119040 | F70: =SUMIFS(data!$G:$G,data!$C:$C,$B$31,data!$D:$D,$B$61,data!$F:$F,E$4,data!$E:$E,$B70,data!$H:$H,ПФ2026!F$5) -> -926070 | G70: =SUMIFS(data!$G:$G,data!$C:$C,$B$31,data!$D:$D,$B$61,data!$F:$F,G$4,data!$E:$E,$B70,data!$H:$H,ПФ2026!G$5) -> -2452240 | H70: =SUMIFS(data!$G:$G,data!$C:$C,$B$31,data!$D:$D,$B$61,data!$F:$F,G$4,data!$E:$E,$B70,data!$H:$H,ПФ2026!H$5) -> -1884620.3 | I70: =SUMIFS(data!$G:$G,data!$C:$C,$B$31,data!$D:$D,$B$61,data!$F:$F,I$4,data!$E:$E,$B70,data!$H:$H,ПФ2026!I$5) -> -3279440 | J70: =SUMIFS(data!$G:$G,data!$C:$C,$B$31,data!$D:$D,$B$61,data!$F:$F,I$4,data!$E:$E,$B70,data!$H:$H,ПФ2026!J$5) -> -3473787.5 | K70: =SUMIFS(data!$G:$G,data!$C:$C,$B$31,data!$D:$D,$B$61,data!$F:$F,K$4,data!$E:$E,$B70,data!$H:$H,ПФ2026!K$5) -> -3279440 | L70: =SUMIFS(data!$G:$G,data!$C:$C,$B$31,data!$D:$D,$B$61,data!$F:$F,K$4,data!$E:$E,$B70,data!$H:$H,ПФ2026!L$5) -> -3350351.5 | M70: =SUMIFS(data!$G:$G,data!$C:$C,$B$31,data!$D:$D,$B$61,data!$F:$F,M$4,data!$E:$E,$B70,data!$H:$H,ПФ2026!M$5) -> -3444440 | N70: =SUMIFS(data!$G:$G,data!$C:$C,$B$31,data!$D:$D,$B$61,data!$F:$F,M$4,data!$E:$E,$B70,data!$H:$H,ПФ2026!N$5) -> -3954485 | O70: =SUMIFS(data!$G:$G,data!$C:$C,$B$31,data!$D:$D,$B$61,data!$F:$F,O$4,data!$E:$E,$B70,data!$H:$H,ПФ2026!O$5) -> -3444440 | P70: =SUMIFS(data!$G:$G,data!$C:$C,$B$31,data!$D:$D,$B$61,data!$F:$F,O$4,data!$E:$E,$B70,data!$H:$H,ПФ2026!P$5) -> 0 | Q70: =SUMIFS(data!$G:$G,data!$C:$C,$B$31,data!$D:$D,$B$61,data!$F:$F,Q$4,data!$E:$E,$B70,data!$H:$H,ПФ2026!Q$5) -> -3444440 | R70: =SUMIFS(data!$G:$G,data!$C:$C,$B$31,data!$D:$D,$B$61,data!$F:$F,Q$4,data!$E:$E,$B70,data!$H:$H,ПФ2026!R$5) -> 0 | S70: =SUMIFS(data!$G:$G,data!$C:$C,$B$31,data!$D:$D,$B$61,data!$F:$F,S$4,data!$E:$E,$B70,data!$H:$H,ПФ2026!S$5) -> -3279440 | T70: =SUMIFS(data!$G:$G,data!$C:$C,$B$31,data!$D:$D,$B$61,data!$F:$F,S$4,data!$E:$E,$B70,data!$H:$H,ПФ2026!T$5) -> 0 | U70: =SUMIFS(data!$G:$G,data!$C:$C,$B$31,data!$D:$D,$B$61,data!$F:$F,U$4,data!$E:$E,$B70,data!$H:$H,ПФ2026!U$5) -> -1453440 | V70: =SUMIFS(data!$G:$G,data!$C:$C,$B$31,data!$D:$D,$B$61,data!$F:$F,U$4,data!$E:$E,$B70,data!$H:$H,ПФ2026!V$5) -> 0 | W70: =SUMIFS(data!$G:$G,data!$C:$C,$B$31,data!$D:$D,$B$61,data!$F:$F,W$4,data!$E:$E,$B70,data!$H:$H,ПФ2026!W$5) -> -1220240 | X70: =SUMIFS(data!$G:$G,data!$C:$C,$B$31,data!$D:$D,$B$61,data!$F:$F,W$4,data!$E:$E,$B70,data!$H:$H,ПФ2026!X$5) -> 0 | Y70: =SUMIFS(data!$G:$G,data!$C:$C,$B$31,data!$D:$D,$B$61,data!$F:$F,Y$4,data!$E:$E,$B70,data!$H:$H,ПФ2026!Y$5) -> -1220240 | Z70: =SUMIFS(data!$G:$G,data!$C:$C,$B$31,data!$D:$D,$B$61,data!$F:$F,Y$4,data!$E:$E,$B70,data!$H:$H,ПФ2026!Z$5) -> 0 | AA70: =SUM(C70,E70,G70,I70,K70,M70,O134,O70,Q70,S70) -> -24861960 | AB70: =SUM(D70,F70,H70,J70,L70,N70,P134,P70,R70,T70) -> -14546522 | AC70: =IFERROR(AB70/AA70,0) -> 0.58509153
B71: Расходы на продукты | C71: =SUMIFS(data!$G:$G,data!$C:$C,$B$31,data!$D:$D,$B$61,data!$F:$F,C$4,data!$E:$E,$B71,data!$H:$H,ПФ2026!C$5) -> -1500000 | D71: =SUMIFS(data!$G:$G,data!$C:$C,$B$31,data!$D:$D,$B$61,data!$F:$F,C$4,data!$E:$E,$B71,data!$H:$H,ПФ2026!D$5) -> -1451384.4 | E71: =SUMIFS(data!$G:$G,data!$C:$C,$B$31,data!$D:$D,$B$61,data!$F:$F,E$4,data!$E:$E,$B71,data!$H:$H,ПФ2026!E$5) -> -1500000 | F71: =SUMIFS(data!$G:$G,data!$C:$C,$B$31,data!$D:$D,$B$61,data!$F:$F,E$4,data!$E:$E,$B71,data!$H:$H,ПФ2026!F$5) -> -1412284 | G71: =SUMIFS(data!$G:$G,data!$C:$C,$B$31,data!$D:$D,$B$61,data!$F:$F,G$4,data!$E:$E,$B71,data!$H:$H,ПФ2026!G$5) -> -2350000 | H71: =SUMIFS(data!$G:$G,data!$C:$C,$B$31,data!$D:$D,$B$61,data!$F:$F,G$4,data!$E:$E,$B71,data!$H:$H,ПФ2026!H$5) -> -1891964.1 | I71: =SUMIFS(data!$G:$G,data!$C:$C,$B$31,data!$D:$D,$B$61,data!$F:$F,I$4,data!$E:$E,$B71,data!$H:$H,ПФ2026!I$5) -> -2350000 | J71: =SUMIFS(data!$G:$G,data!$C:$C,$B$31,data!$D:$D,$B$61,data!$F:$F,I$4,data!$E:$E,$B71,data!$H:$H,ПФ2026!J$5) -> -2355593.3 | K71: =SUMIFS(data!$G:$G,data!$C:$C,$B$31,data!$D:$D,$B$61,data!$F:$F,K$4,data!$E:$E,$B71,data!$H:$H,ПФ2026!K$5) -> -3000000 | L71: =SUMIFS(data!$G:$G,data!$C:$C,$B$31,data!$D:$D,$B$61,data!$F:$F,K$4,data!$E:$E,$B71,data!$H:$H,ПФ2026!L$5) -> -2454417.7 | M71: =SUMIFS(data!$G:$G,data!$C:$C,$B$31,data!$D:$D,$B$61,data!$F:$F,M$4,data!$E:$E,$B71,data!$H:$H,ПФ2026!M$5) -> -3000000 | N71: =SUMIFS(data!$G:$G,data!$C:$C,$B$31,data!$D:$D,$B$61,data!$F:$F,M$4,data!$E:$E,$B71,data!$H:$H,ПФ2026!N$5) -> -3192686.8 | O71: =SUMIFS(data!$G:$G,data!$C:$C,$B$31,data!$D:$D,$B$61,data!$F:$F,O$4,data!$E:$E,$B71,data!$H:$H,ПФ2026!O$5) -> -3000000 | P71: =SUMIFS(data!$G:$G,data!$C:$C,$B$31,data!$D:$D,$B$61,data!$F:$F,O$4,data!$E:$E,$B71,data!$H:$H,ПФ2026!P$5) -> 0 | Q71: =SUMIFS(data!$G:$G,data!$C:$C,$B$31,data!$D:$D,$B$61,data!$F:$F,Q$4,data!$E:$E,$B71,data!$H:$H,ПФ2026!Q$5) -> -3000000 | R71: =SUMIFS(data!$G:$G,data!$C:$C,$B$31,data!$D:$D,$B$61,data!$F:$F,Q$4,data!$E:$E,$B71,data!$H:$H,ПФ2026!R$5) -> 0 | S71: =SUMIFS(data!$G:$G,data!$C:$C,$B$31,data!$D:$D,$B$61,data!$F:$F,S$4,data!$E:$E,$B71,data!$H:$H,ПФ2026!S$5) -> -3000000 | T71: =SUMIFS(data!$G:$G,data!$C:$C,$B$31,data!$D:$D,$B$61,data!$F:$F,S$4,data!$E:$E,$B71,data!$H:$H,ПФ2026!T$5) -> 0 | U71: =SUMIFS(data!$G:$G,data!$C:$C,$B$31,data!$D:$D,$B$61,data!$F:$F,U$4,data!$E:$E,$B71,data!$H:$H,ПФ2026!U$5) -> -1500000 | V71: =SUMIFS(data!$G:$G,data!$C:$C,$B$31,data!$D:$D,$B$61,data!$F:$F,U$4,data!$E:$E,$B71,data!$H:$H,ПФ2026!V$5) -> 0 | W71: =SUMIFS(data!$G:$G,data!$C:$C,$B$31,data!$D:$D,$B$61,data!$F:$F,W$4,data!$E:$E,$B71,data!$H:$H,ПФ2026!W$5) -> -1500000 | X71: =SUMIFS(data!$G:$G,data!$C:$C,$B$31,data!$D:$D,$B$61,data!$F:$F,W$4,data!$E:$E,$B71,data!$H:$H,ПФ2026!X$5) -> 0 | Y71: =SUMIFS(data!$G:$G,data!$C:$C,$B$31,data!$D:$D,$B$61,data!$F:$F,Y$4,data!$E:$E,$B71,data!$H:$H,ПФ2026!Y$5) -> -1500000 | Z71: =SUMIFS(data!$G:$G,data!$C:$C,$B$31,data!$D:$D,$B$61,data!$F:$F,Y$4,data!$E:$E,$B71,data!$H:$H,ПФ2026!Z$5) -> 0 | AA71: =SUM(C71,E71,G71,I71,K71,M71,O136,O71,Q71,S71) -> -22700000 | AB71: =SUM(D71,F71,H71,J71,L71,N71,P136,P71,R71,T71) -> -12758330 | AC71: =IFERROR(AB71/AA71,0) -> 0.56204098
B72: Расходы на спец.питание | C72: =SUMIFS(data!$G:$G,data!$C:$C,$B$31,data!$D:$D,$B$61,data!$F:$F,C$4,data!$E:$E,$B72,data!$H:$H,ПФ2026!C$5) -> -7040 | D72: =SUMIFS(data!$G:$G,data!$C:$C,$B$31,data!$D:$D,$B$61,data!$F:$F,C$4,data!$E:$E,$B72,data!$H:$H,ПФ2026!D$5) -> -35752.6 | E72: =SUMIFS(data!$G:$G,data!$C:$C,$B$31,data!$D:$D,$B$61,data!$F:$F,E$4,data!$E:$E,$B72,data!$H:$H,ПФ2026!E$5) -> -7040 | F72: =SUMIFS(data!$G:$G,data!$C:$C,$B$31,data!$D:$D,$B$61,data!$F:$F,E$4,data!$E:$E,$B72,data!$H:$H,ПФ2026!F$5) -> -26068.35 | G72: =SUMIFS(data!$G:$G,data!$C:$C,$B$31,data!$D:$D,$B$61,data!$F:$F,G$4,data!$E:$E,$B72,data!$H:$H,ПФ2026!G$5) -> -7392 | H72: =SUMIFS(data!$G:$G,data!$C:$C,$B$31,data!$D:$D,$B$61,data!$F:$F,G$4,data!$E:$E,$B72,data!$H:$H,ПФ2026!H$5) -> -12517.01 | I72: =SUMIFS(data!$G:$G,data!$C:$C,$B$31,data!$D:$D,$B$61,data!$F:$F,I$4,data!$E:$E,$B72,data!$H:$H,ПФ2026!I$5) -> -7392 | J72: =SUMIFS(data!$G:$G,data!$C:$C,$B$31,data!$D:$D,$B$61,data!$F:$F,I$4,data!$E:$E,$B72,data!$H:$H,ПФ2026!J$5) -> -50376.54 | K72: =SUMIFS(data!$G:$G,data!$C:$C,$B$31,data!$D:$D,$B$61,data!$F:$F,K$4,data!$E:$E,$B72,data!$H:$H,ПФ2026!K$5) -> -7392 | L72: =SUMIFS(data!$G:$G,data!$C:$C,$B$31,data!$D:$D,$B$61,data!$F:$F,K$4,data!$E:$E,$B72,data!$H:$H,ПФ2026!L$5) -> -33551.59 | M72: =SUMIFS(data!$G:$G,data!$C:$C,$B$31,data!$D:$D,$B$61,data!$F:$F,M$4,data!$E:$E,$B72,data!$H:$H,ПФ2026!M$5) -> -7392 | N72: =SUMIFS(data!$G:$G,data!$C:$C,$B$31,data!$D:$D,$B$61,data!$F:$F,M$4,data!$E:$E,$B72,data!$H:$H,ПФ2026!N$5) -> -43252.94 | O72: =SUMIFS(data!$G:$G,data!$C:$C,$B$31,data!$D:$D,$B$61,data!$F:$F,O$4,data!$E:$E,$B72,data!$H:$H,ПФ2026!O$5) -> -7392 | P72: =SUMIFS(data!$G:$G,data!$C:$C,$B$31,data!$D:$D,$B$61,data!$F:$F,O$4,data!$E:$E,$B72,data!$H:$H,ПФ2026!P$5) -> 0 | Q72: =SUMIFS(data!$G:$G,data!$C:$C,$B$31,data!$D:$D,$B$61,data!$F:$F,Q$4,data!$E:$E,$B72,data!$H:$H,ПФ2026!Q$5) -> -7392 | R72: =SUMIFS(data!$G:$G,data!$C:$C,$B$31,data!$D:$D,$B$61,data!$F:$F,Q$4,data!$E:$E,$B72,data!$H:$H,ПФ2026!R$5) -> 0 | S72: =SUMIFS(data!$G:$G,data!$C:$C,$B$31,data!$D:$D,$B$61,data!$F:$F,S$4,data!$E:$E,$B72,data!$H:$H,ПФ2026!S$5) -> -7392 | T72: =SUMIFS(data!$G:$G,data!$C:$C,$B$31,data!$D:$D,$B$61,data!$F:$F,S$4,data!$E:$E,$B72,data!$H:$H,ПФ2026!T$5) -> 0 | U72: =SUMIFS(data!$G:$G,data!$C:$C,$B$31,data!$D:$D,$B$61,data!$F:$F,U$4,data!$E:$E,$B72,data!$H:$H,ПФ2026!U$5) -> -7392 | V72: =SUMIFS(data!$G:$G,data!$C:$C,$B$31,data!$D:$D,$B$61,data!$F:$F,U$4,data!$E:$E,$B72,data!$H:$H,ПФ2026!V$5) -> 0 | W72: =SUMIFS(data!$G:$G,data!$C:$C,$B$31,data!$D:$D,$B$61,data!$F:$F,W$4,data!$E:$E,$B72,data!$H:$H,ПФ2026!W$5) -> -7040 | X72: =SUMIFS(data!$G:$G,data!$C:$C,$B$31,data!$D:$D,$B$61,data!$F:$F,W$4,data!$E:$E,$B72,data!$H:$H,ПФ2026!X$5) -> 0 | Y72: =SUMIFS(data!$G:$G,data!$C:$C,$B$31,data!$D:$D,$B$61,data!$F:$F,Y$4,data!$E:$E,$B72,data!$H:$H,ПФ2026!Y$5) -> -7040 | Z72: =SUMIFS(data!$G:$G,data!$C:$C,$B$31,data!$D:$D,$B$61,data!$F:$F,Y$4,data!$E:$E,$B72,data!$H:$H,ПФ2026!Z$5) -> 0 | AA72: =SUM(C72,E72,G72,I72,K72,M72,O137,O72,Q72,S72) -> -250824 | AB72: =SUM(D72,F72,H72,J72,L72,N72,P137,P72,R72,T72) -> -201519.03 | AC72: =IFERROR(AB72/AA72,0) -> 0.80342802
B73: Санитарная обработка | C73: =SUMIFS(data!$G:$G,data!$C:$C,$B$31,data!$D:$D,$B$61,data!$F:$F,C$4,data!$E:$E,$B73,data!$H:$H,ПФ2026!C$5) -> 0 | D73: =SUMIFS(data!$G:$G,data!$C:$C,$B$31,data!$D:$D,$B$61,data!$F:$F,C$4,data!$E:$E,$B73,data!$H:$H,ПФ2026!D$5) -> 0 | E73: =SUMIFS(data!$G:$G,data!$C:$C,$B$31,data!$D:$D,$B$61,data!$F:$F,E$4,data!$E:$E,$B73,data!$H:$H,ПФ2026!E$5) -> 0 | F73: =SUMIFS(data!$G:$G,data!$C:$C,$B$31,data!$D:$D,$B$61,data!$F:$F,E$4,data!$E:$E,$B73,data!$H:$H,ПФ2026!F$5) -> 0 | G73: =SUMIFS(data!$G:$G,data!$C:$C,$B$31,data!$D:$D,$B$61,data!$F:$F,G$4,data!$E:$E,$B73,data!$H:$H,ПФ2026!G$5) -> 0 | H73: =SUMIFS(data!$G:$G,data!$C:$C,$B$31,data!$D:$D,$B$61,data!$F:$F,G$4,data!$E:$E,$B73,data!$H:$H,ПФ2026!H$5) -> 0 | I73: =SUMIFS(data!$G:$G,data!$C:$C,$B$31,data!$D:$D,$B$61,data!$F:$F,I$4,data!$E:$E,$B73,data!$H:$H,ПФ2026!I$5) -> 0 | J73: =SUMIFS(data!$G:$G,data!$C:$C,$B$31,data!$D:$D,$B$61,data!$F:$F,I$4,data!$E:$E,$B73,data!$H:$H,ПФ2026!J$5) -> 0 | K73: =SUMIFS(data!$G:$G,data!$C:$C,$B$31,data!$D:$D,$B$61,data!$F:$F,K$4,data!$E:$E,$B73,data!$H:$H,ПФ2026!K$5) -> 0 | L73: =SUMIFS(data!$G:$G,data!$C:$C,$B$31,data!$D:$D,$B$61,data!$F:$F,K$4,data!$E:$E,$B73,data!$H:$H,ПФ2026!L$5) -> 0 | M73: =SUMIFS(data!$G:$G,data!$C:$C,$B$31,data!$D:$D,$B$61,data!$F:$F,M$4,data!$E:$E,$B73,data!$H:$H,ПФ2026!M$5) -> 0 | N73: =SUMIFS(data!$G:$G,data!$C:$C,$B$31,data!$D:$D,$B$61,data!$F:$F,M$4,data!$E:$E,$B73,data!$H:$H,ПФ2026!N$5) -> 0 | O73: =SUMIFS(data!$G:$G,data!$C:$C,$B$31,data!$D:$D,$B$61,data!$F:$F,O$4,data!$E:$E,$B73,data!$H:$H,ПФ2026!O$5) -> 0 | P73: =SUMIFS(data!$G:$G,data!$C:$C,$B$31,data!$D:$D,$B$61,data!$F:$F,O$4,data!$E:$E,$B73,data!$H:$H,ПФ2026!P$5) -> 0 | Q73: =SUMIFS(data!$G:$G,data!$C:$C,$B$31,data!$D:$D,$B$61,data!$F:$F,Q$4,data!$E:$E,$B73,data!$H:$H,ПФ2026!Q$5) -> 0 | R73: =SUMIFS(data!$G:$G,data!$C:$C,$B$31,data!$D:$D,$B$61,data!$F:$F,Q$4,data!$E:$E,$B73,data!$H:$H,ПФ2026!R$5) -> 0 | S73: =SUMIFS(data!$G:$G,data!$C:$C,$B$31,data!$D:$D,$B$61,data!$F:$F,S$4,data!$E:$E,$B73,data!$H:$H,ПФ2026!S$5) -> 0 | T73: =SUMIFS(data!$G:$G,data!$C:$C,$B$31,data!$D:$D,$B$61,data!$F:$F,S$4,data!$E:$E,$B73,data!$H:$H,ПФ2026!T$5) -> 0 | U73: =SUMIFS(data!$G:$G,data!$C:$C,$B$31,data!$D:$D,$B$61,data!$F:$F,U$4,data!$E:$E,$B73,data!$H:$H,ПФ2026!U$5) -> 0 | V73: =SUMIFS(data!$G:$G,data!$C:$C,$B$31,data!$D:$D,$B$61,data!$F:$F,U$4,data!$E:$E,$B73,data!$H:$H,ПФ2026!V$5) -> 0 | W73: =SUMIFS(data!$G:$G,data!$C:$C,$B$31,data!$D:$D,$B$61,data!$F:$F,W$4,data!$E:$E,$B73,data!$H:$H,ПФ2026!W$5) -> 0 | X73: =SUMIFS(data!$G:$G,data!$C:$C,$B$31,data!$D:$D,$B$61,data!$F:$F,W$4,data!$E:$E,$B73,data!$H:$H,ПФ2026!X$5) -> 0 | Y73: =SUMIFS(data!$G:$G,data!$C:$C,$B$31,data!$D:$D,$B$61,data!$F:$F,Y$4,data!$E:$E,$B73,data!$H:$H,ПФ2026!Y$5) -> 0 | Z73: =SUMIFS(data!$G:$G,data!$C:$C,$B$31,data!$D:$D,$B$61,data!$F:$F,Y$4,data!$E:$E,$B73,data!$H:$H,ПФ2026!Z$5) -> 0 | AA73: =SUM(C73,E73,G73,I73,K73,M73,O138,O73,Q73,S73) -> 0 | AB73: =SUM(D73,F73,H73,J73,L73,N73,P138,P73,R73,T73) -> 0 | AC73: =IFERROR(AB73/AA73,0) -> 0
B74: Сервисное обслуживание,абонплата | C74: =SUMIFS(data!$G:$G,data!$C:$C,$B$31,data!$D:$D,$B$61,data!$F:$F,C$4,data!$E:$E,$B74,data!$H:$H,ПФ2026!C$5) -> 0 | D74: =SUMIFS(data!$G:$G,data!$C:$C,$B$31,data!$D:$D,$B$61,data!$F:$F,C$4,data!$E:$E,$B74,data!$H:$H,ПФ2026!D$5) -> 0 | E74: =SUMIFS(data!$G:$G,data!$C:$C,$B$31,data!$D:$D,$B$61,data!$F:$F,E$4,data!$E:$E,$B74,data!$H:$H,ПФ2026!E$5) -> 0 | F74: =SUMIFS(data!$G:$G,data!$C:$C,$B$31,data!$D:$D,$B$61,data!$F:$F,E$4,data!$E:$E,$B74,data!$H:$H,ПФ2026!F$5) -> 0 | G74: =SUMIFS(data!$G:$G,data!$C:$C,$B$31,data!$D:$D,$B$61,data!$F:$F,G$4,data!$E:$E,$B74,data!$H:$H,ПФ2026!G$5) -> 0 | H74: =SUMIFS(data!$G:$G,data!$C:$C,$B$31,data!$D:$D,$B$61,data!$F:$F,G$4,data!$E:$E,$B74,data!$H:$H,ПФ2026!H$5) -> 0 | I74: =SUMIFS(data!$G:$G,data!$C:$C,$B$31,data!$D:$D,$B$61,data!$F:$F,I$4,data!$E:$E,$B74,data!$H:$H,ПФ2026!I$5) -> -23283 | J74: =SUMIFS(data!$G:$G,data!$C:$C,$B$31,data!$D:$D,$B$61,data!$F:$F,I$4,data!$E:$E,$B74,data!$H:$H,ПФ2026!J$5) -> 0 | K74: =SUMIFS(data!$G:$G,data!$C:$C,$B$31,data!$D:$D,$B$61,data!$F:$F,K$4,data!$E:$E,$B74,data!$H:$H,ПФ2026!K$5) -> 0 | L74: =SUMIFS(data!$G:$G,data!$C:$C,$B$31,data!$D:$D,$B$61,data!$F:$F,K$4,data!$E:$E,$B74,data!$H:$H,ПФ2026!L$5) -> 0 | M74: =SUMIFS(data!$G:$G,data!$C:$C,$B$31,data!$D:$D,$B$61,data!$F:$F,M$4,data!$E:$E,$B74,data!$H:$H,ПФ2026!M$5) -> 0 | N74: =SUMIFS(data!$G:$G,data!$C:$C,$B$31,data!$D:$D,$B$61,data!$F:$F,M$4,data!$E:$E,$B74,data!$H:$H,ПФ2026!N$5) -> 0 | O74: =SUMIFS(data!$G:$G,data!$C:$C,$B$31,data!$D:$D,$B$61,data!$F:$F,O$4,data!$E:$E,$B74,data!$H:$H,ПФ2026!O$5) -> 0 | P74: =SUMIFS(data!$G:$G,data!$C:$C,$B$31,data!$D:$D,$B$61,data!$F:$F,O$4,data!$E:$E,$B74,data!$H:$H,ПФ2026!P$5) -> 0 | Q74: =SUMIFS(data!$G:$G,data!$C:$C,$B$31,data!$D:$D,$B$61,data!$F:$F,Q$4,data!$E:$E,$B74,data!$H:$H,ПФ2026!Q$5) -> -23283 | R74: =SUMIFS(data!$G:$G,data!$C:$C,$B$31,data!$D:$D,$B$61,data!$F:$F,Q$4,data!$E:$E,$B74,data!$H:$H,ПФ2026!R$5) -> 0 | S74: =SUMIFS(data!$G:$G,data!$C:$C,$B$31,data!$D:$D,$B$61,data!$F:$F,S$4,data!$E:$E,$B74,data!$H:$H,ПФ2026!S$5) -> 0 | T74: =SUMIFS(data!$G:$G,data!$C:$C,$B$31,data!$D:$D,$B$61,data!$F:$F,S$4,data!$E:$E,$B74,data!$H:$H,ПФ2026!T$5) -> 0 | U74: =SUMIFS(data!$G:$G,data!$C:$C,$B$31,data!$D:$D,$B$61,data!$F:$F,U$4,data!$E:$E,$B74,data!$H:$H,ПФ2026!U$5) -> 0 | V74: =SUMIFS(data!$G:$G,data!$C:$C,$B$31,data!$D:$D,$B$61,data!$F:$F,U$4,data!$E:$E,$B74,data!$H:$H,ПФ2026!V$5) -> 0 | W74: =SUMIFS(data!$G:$G,data!$C:$C,$B$31,data!$D:$D,$B$61,data!$F:$F,W$4,data!$E:$E,$B74,data!$H:$H,ПФ2026!W$5) -> 0 | X74: =SUMIFS(data!$G:$G,data!$C:$C,$B$31,data!$D:$D,$B$61,data!$F:$F,W$4,data!$E:$E,$B74,data!$H:$H,ПФ2026!X$5) -> 0 | Y74: =SUMIFS(data!$G:$G,data!$C:$C,$B$31,data!$D:$D,$B$61,data!$F:$F,Y$4,data!$E:$E,$B74,data!$H:$H,ПФ2026!Y$5) -> 0 | Z74: =SUMIFS(data!$G:$G,data!$C:$C,$B$31,data!$D:$D,$B$61,data!$F:$F,Y$4,data!$E:$E,$B74,data!$H:$H,ПФ2026!Z$5) -> 0 | AA74: =SUM(C74,E74,G74,I74,K74,M74,O139,O74,Q74,S74) -> -221566 | AB74: =SUM(D74,F74,H74,J74,L74,N74,P139,P74,R74,T74) -> 0 | AC74: =IFERROR(AB74/AA74,0) -> 0
B75: Текущий ремонт оборудования, ОС и МБП | C75: =SUMIFS(data!$G:$G,data!$C:$C,$B$31,data!$D:$D,$B$61,data!$F:$F,C$4,data!$E:$E,$B75,data!$H:$H,ПФ2026!C$5) -> -32942.45 | D75: =SUMIFS(data!$G:$G,data!$C:$C,$B$31,data!$D:$D,$B$61,data!$F:$F,C$4,data!$E:$E,$B75,data!$H:$H,ПФ2026!D$5) -> -2762.27 | E75: =SUMIFS(data!$G:$G,data!$C:$C,$B$31,data!$D:$D,$B$61,data!$F:$F,E$4,data!$E:$E,$B75,data!$H:$H,ПФ2026!E$5) -> -32340.49 | F75: =SUMIFS(data!$G:$G,data!$C:$C,$B$31,data!$D:$D,$B$61,data!$F:$F,E$4,data!$E:$E,$B75,data!$H:$H,ПФ2026!F$5) -> -7413.24 | G75: =SUMIFS(data!$G:$G,data!$C:$C,$B$31,data!$D:$D,$B$61,data!$F:$F,G$4,data!$E:$E,$B75,data!$H:$H,ПФ2026!G$5) -> -32857.99 | H75: =SUMIFS(data!$G:$G,data!$C:$C,$B$31,data!$D:$D,$B$61,data!$F:$F,G$4,data!$E:$E,$B75,data!$H:$H,ПФ2026!H$5) -> -156858.29 | I75: =SUMIFS(data!$G:$G,data!$C:$C,$B$31,data!$D:$D,$B$61,data!$F:$F,I$4,data!$E:$E,$B75,data!$H:$H,ПФ2026!I$5) -> -53464.15 | J75: =SUMIFS(data!$G:$G,data!$C:$C,$B$31,data!$D:$D,$B$61,data!$F:$F,I$4,data!$E:$E,$B75,data!$H:$H,ПФ2026!J$5) -> -25739.97 | K75: =SUMIFS(data!$G:$G,data!$C:$C,$B$31,data!$D:$D,$B$61,data!$F:$F,K$4,data!$E:$E,$B75,data!$H:$H,ПФ2026!K$5) -> -45368.05 | L75: =SUMIFS(data!$G:$G,data!$C:$C,$B$31,data!$D:$D,$B$61,data!$F:$F,K$4,data!$E:$E,$B75,data!$H:$H,ПФ2026!L$5) -> -7975.5 | M75: =SUMIFS(data!$G:$G,data!$C:$C,$B$31,data!$D:$D,$B$61,data!$F:$F,M$4,data!$E:$E,$B75,data!$H:$H,ПФ2026!M$5) -> -48989.25 | N75: =SUMIFS(data!$G:$G,data!$C:$C,$B$31,data!$D:$D,$B$61,data!$F:$F,M$4,data!$E:$E,$B75,data!$H:$H,ПФ2026!N$5) -> -41497.62 | O75: =SUMIFS(data!$G:$G,data!$C:$C,$B$31,data!$D:$D,$B$61,data!$F:$F,O$4,data!$E:$E,$B75,data!$H:$H,ПФ2026!O$5) -> -42968.05 | P75: =SUMIFS(data!$G:$G,data!$C:$C,$B$31,data!$D:$D,$B$61,data!$F:$F,O$4,data!$E:$E,$B75,data!$H:$H,ПФ2026!P$5) -> 0 | Q75: =SUMIFS(data!$G:$G,data!$C:$C,$B$31,data!$D:$D,$B$61,data!$F:$F,Q$4,data!$E:$E,$B75,data!$H:$H,ПФ2026!Q$5) -> -45782.65 | R75: =SUMIFS(data!$G:$G,data!$C:$C,$B$31,data!$D:$D,$B$61,data!$F:$F,Q$4,data!$E:$E,$B75,data!$H:$H,ПФ2026!R$5) -> 0 | S75: =SUMIFS(data!$G:$G,data!$C:$C,$B$31,data!$D:$D,$B$61,data!$F:$F,S$4,data!$E:$E,$B75,data!$H:$H,ПФ2026!S$5) -> -35830.75 | T75: =SUMIFS(data!$G:$G,data!$C:$C,$B$31,data!$D:$D,$B$61,data!$F:$F,S$4,data!$E:$E,$B75,data!$H:$H,ПФ2026!T$5) -> 0 | U75: =SUMIFS(data!$G:$G,data!$C:$C,$B$31,data!$D:$D,$B$61,data!$F:$F,U$4,data!$E:$E,$B75,data!$H:$H,ПФ2026!U$5) -> -33054.05 | V75: =SUMIFS(data!$G:$G,data!$C:$C,$B$31,data!$D:$D,$B$61,data!$F:$F,U$4,data!$E:$E,$B75,data!$H:$H,ПФ2026!V$5) -> 0 | W75: =SUMIFS(data!$G:$G,data!$C:$C,$B$31,data!$D:$D,$B$61,data!$F:$F,W$4,data!$E:$E,$B75,data!$H:$H,ПФ2026!W$5) -> -37212.25 | X75: =SUMIFS(data!$G:$G,data!$C:$C,$B$31,data!$D:$D,$B$61,data!$F:$F,W$4,data!$E:$E,$B75,data!$H:$H,ПФ2026!X$5) -> 0 | Y75: =SUMIFS(data!$G:$G,data!$C:$C,$B$31,data!$D:$D,$B$61,data!$F:$F,Y$4,data!$E:$E,$B75,data!$H:$H,ПФ2026!Y$5) -> -32724.65 | Z75: =SUMIFS(data!$G:$G,data!$C:$C,$B$31,data!$D:$D,$B$61,data!$F:$F,Y$4,data!$E:$E,$B75,data!$H:$H,ПФ2026!Z$5) -> 0 | AA75: =SUM(C75,E75,G75,I75,K75,M75,O140,O75,Q75,S75) -> -370543.83 | AB75: =SUM(D75,F75,H75,J75,L75,N75,P140,P75,R75,T75) -> -242246.89 | AC75: =IFERROR(AB75/AA75,0) -> 0.65376042
B76: Услуги | C76: =SUMIFS(data!$G:$G,data!$C:$C,$B$31,data!$D:$D,$B$61,data!$F:$F,C$4,data!$E:$E,$B76,data!$H:$H,ПФ2026!C$5) -> 0 | D76: =SUMIFS(data!$G:$G,data!$C:$C,$B$31,data!$D:$D,$B$61,data!$F:$F,C$4,data!$E:$E,$B76,data!$H:$H,ПФ2026!D$5) -> 0 | E76: =SUMIFS(data!$G:$G,data!$C:$C,$B$31,data!$D:$D,$B$61,data!$F:$F,E$4,data!$E:$E,$B76,data!$H:$H,ПФ2026!E$5) -> 0 | F76: =SUMIFS(data!$G:$G,data!$C:$C,$B$31,data!$D:$D,$B$61,data!$F:$F,E$4,data!$E:$E,$B76,data!$H:$H,ПФ2026!F$5) -> 0 | G76: =SUMIFS(data!$G:$G,data!$C:$C,$B$31,data!$D:$D,$B$61,data!$F:$F,G$4,data!$E:$E,$B76,data!$H:$H,ПФ2026!G$5) -> 0 | H76: =SUMIFS(data!$G:$G,data!$C:$C,$B$31,data!$D:$D,$B$61,data!$F:$F,G$4,data!$E:$E,$B76,data!$H:$H,ПФ2026!H$5) -> 0 | I76: =SUMIFS(data!$G:$G,data!$C:$C,$B$31,data!$D:$D,$B$61,data!$F:$F,I$4,data!$E:$E,$B76,data!$H:$H,ПФ2026!I$5) -> 0 | J76: =SUMIFS(data!$G:$G,data!$C:$C,$B$31,data!$D:$D,$B$61,data!$F:$F,I$4,data!$E:$E,$B76,data!$H:$H,ПФ2026!J$5) -> 0 | K76: =SUMIFS(data!$G:$G,data!$C:$C,$B$31,data!$D:$D,$B$61,data!$F:$F,K$4,data!$E:$E,$B76,data!$H:$H,ПФ2026!K$5) -> 0 | L76: =SUMIFS(data!$G:$G,data!$C:$C,$B$31,data!$D:$D,$B$61,data!$F:$F,K$4,data!$E:$E,$B76,data!$H:$H,ПФ2026!L$5) -> 0 | M76: =SUMIFS(data!$G:$G,data!$C:$C,$B$31,data!$D:$D,$B$61,data!$F:$F,M$4,data!$E:$E,$B76,data!$H:$H,ПФ2026!M$5) -> 0 | N76: =SUMIFS(data!$G:$G,data!$C:$C,$B$31,data!$D:$D,$B$61,data!$F:$F,M$4,data!$E:$E,$B76,data!$H:$H,ПФ2026!N$5) -> 0 | O76: =SUMIFS(data!$G:$G,data!$C:$C,$B$31,data!$D:$D,$B$61,data!$F:$F,O$4,data!$E:$E,$B76,data!$H:$H,ПФ2026!O$5) -> 0 | P76: =SUMIFS(data!$G:$G,data!$C:$C,$B$31,data!$D:$D,$B$61,data!$F:$F,O$4,data!$E:$E,$B76,data!$H:$H,ПФ2026!P$5) -> 0 | Q76: =SUMIFS(data!$G:$G,data!$C:$C,$B$31,data!$D:$D,$B$61,data!$F:$F,Q$4,data!$E:$E,$B76,data!$H:$H,ПФ2026!Q$5) -> 0 | R76: =SUMIFS(data!$G:$G,data!$C:$C,$B$31,data!$D:$D,$B$61,data!$F:$F,Q$4,data!$E:$E,$B76,data!$H:$H,ПФ2026!R$5) -> 0 | S76: =SUMIFS(data!$G:$G,data!$C:$C,$B$31,data!$D:$D,$B$61,data!$F:$F,S$4,data!$E:$E,$B76,data!$H:$H,ПФ2026!S$5) -> 0 | T76: =SUMIFS(data!$G:$G,data!$C:$C,$B$31,data!$D:$D,$B$61,data!$F:$F,S$4,data!$E:$E,$B76,data!$H:$H,ПФ2026!T$5) -> 0 | U76: =SUMIFS(data!$G:$G,data!$C:$C,$B$31,data!$D:$D,$B$61,data!$F:$F,U$4,data!$E:$E,$B76,data!$H:$H,ПФ2026!U$5) -> 0 | V76: =SUMIFS(data!$G:$G,data!$C:$C,$B$31,data!$D:$D,$B$61,data!$F:$F,U$4,data!$E:$E,$B76,data!$H:$H,ПФ2026!V$5) -> 0 | W76: =SUMIFS(data!$G:$G,data!$C:$C,$B$31,data!$D:$D,$B$61,data!$F:$F,W$4,data!$E:$E,$B76,data!$H:$H,ПФ2026!W$5) -> 0 | X76: =SUMIFS(data!$G:$G,data!$C:$C,$B$31,data!$D:$D,$B$61,data!$F:$F,W$4,data!$E:$E,$B76,data!$H:$H,ПФ2026!X$5) -> 0 | Y76: =SUMIFS(data!$G:$G,data!$C:$C,$B$31,data!$D:$D,$B$61,data!$F:$F,Y$4,data!$E:$E,$B76,data!$H:$H,ПФ2026!Y$5) -> 0 | Z76: =SUMIFS(data!$G:$G,data!$C:$C,$B$31,data!$D:$D,$B$61,data!$F:$F,Y$4,data!$E:$E,$B76,data!$H:$H,ПФ2026!Z$5) -> 0 | AA76: =SUM(C76,E76,G76,I76,K76,M76,O141,O76,Q76,S76) -> -10000 | AB76: =SUM(D76,F76,H76,J76,L76,N76,P141,P76,R76,T76) -> 0 | AC76: =IFERROR(AB76/AA76,0) -> 0
B77: Текущий ремонт помещений | C77: =SUMIFS(data!$G:$G,data!$C:$C,$B$31,data!$D:$D,$B$61,data!$F:$F,C$4,data!$E:$E,$B77,data!$H:$H,ПФ2026!C$5) -> 0 | D77: =SUMIFS(data!$G:$G,data!$C:$C,$B$31,data!$D:$D,$B$61,data!$F:$F,C$4,data!$E:$E,$B77,data!$H:$H,ПФ2026!D$5) -> -27097.31 | E77: =SUMIFS(data!$G:$G,data!$C:$C,$B$31,data!$D:$D,$B$61,data!$F:$F,E$4,data!$E:$E,$B77,data!$H:$H,ПФ2026!E$5) -> 0 | F77: =SUMIFS(data!$G:$G,data!$C:$C,$B$31,data!$D:$D,$B$61,data!$F:$F,E$4,data!$E:$E,$B77,data!$H:$H,ПФ2026!F$5) -> 0 | G77: =SUMIFS(data!$G:$G,data!$C:$C,$B$31,data!$D:$D,$B$61,data!$F:$F,G$4,data!$E:$E,$B77,data!$H:$H,ПФ2026!G$5) -> 0 | H77: =SUMIFS(data!$G:$G,data!$C:$C,$B$31,data!$D:$D,$B$61,data!$F:$F,G$4,data!$E:$E,$B77,data!$H:$H,ПФ2026!H$5) -> 0 | I77: =SUMIFS(data!$G:$G,data!$C:$C,$B$31,data!$D:$D,$B$61,data!$F:$F,I$4,data!$E:$E,$B77,data!$H:$H,ПФ2026!I$5) -> -250000 | J77: =SUMIFS(data!$G:$G,data!$C:$C,$B$31,data!$D:$D,$B$61,data!$F:$F,I$4,data!$E:$E,$B77,data!$H:$H,ПФ2026!J$5) -> -72790 | K77: =SUMIFS(data!$G:$G,data!$C:$C,$B$31,data!$D:$D,$B$61,data!$F:$F,K$4,data!$E:$E,$B77,data!$H:$H,ПФ2026!K$5) -> 0 | L77: =SUMIFS(data!$G:$G,data!$C:$C,$B$31,data!$D:$D,$B$61,data!$F:$F,K$4,data!$E:$E,$B77,data!$H:$H,ПФ2026!L$5) -> 0 | M77: =SUMIFS(data!$G:$G,data!$C:$C,$B$31,data!$D:$D,$B$61,data!$F:$F,M$4,data!$E:$E,$B77,data!$H:$H,ПФ2026!M$5) -> 0 | N77: =SUMIFS(data!$G:$G,data!$C:$C,$B$31,data!$D:$D,$B$61,data!$F:$F,M$4,data!$E:$E,$B77,data!$H:$H,ПФ2026!N$5) -> 0 | O77: =SUMIFS(data!$G:$G,data!$C:$C,$B$31,data!$D:$D,$B$61,data!$F:$F,O$4,data!$E:$E,$B77,data!$H:$H,ПФ2026!O$5) -> 0 | P77: =SUMIFS(data!$G:$G,data!$C:$C,$B$31,data!$D:$D,$B$61,data!$F:$F,O$4,data!$E:$E,$B77,data!$H:$H,ПФ2026!P$5) -> 0 | Q77: =SUMIFS(data!$G:$G,data!$C:$C,$B$31,data!$D:$D,$B$61,data!$F:$F,Q$4,data!$E:$E,$B77,data!$H:$H,ПФ2026!Q$5) -> 0 | R77: =SUMIFS(data!$G:$G,data!$C:$C,$B$31,data!$D:$D,$B$61,data!$F:$F,Q$4,data!$E:$E,$B77,data!$H:$H,ПФ2026!R$5) -> 0 | S77: =SUMIFS(data!$G:$G,data!$C:$C,$B$31,data!$D:$D,$B$61,data!$F:$F,S$4,data!$E:$E,$B77,data!$H:$H,ПФ2026!S$5) -> 0 | T77: =SUMIFS(data!$G:$G,data!$C:$C,$B$31,data!$D:$D,$B$61,data!$F:$F,S$4,data!$E:$E,$B77,data!$H:$H,ПФ2026!T$5) -> 0 | U77: =SUMIFS(data!$G:$G,data!$C:$C,$B$31,data!$D:$D,$B$61,data!$F:$F,U$4,data!$E:$E,$B77,data!$H:$H,ПФ2026!U$5) -> 0 | V77: =SUMIFS(data!$G:$G,data!$C:$C,$B$31,data!$D:$D,$B$61,data!$F:$F,U$4,data!$E:$E,$B77,data!$H:$H,ПФ2026!V$5) -> 0 | W77: =SUMIFS(data!$G:$G,data!$C:$C,$B$31,data!$D:$D,$B$61,data!$F:$F,W$4,data!$E:$E,$B77,data!$H:$H,ПФ2026!W$5) -> 0 | X77: =SUMIFS(data!$G:$G,data!$C:$C,$B$31,data!$D:$D,$B$61,data!$F:$F,W$4,data!$E:$E,$B77,data!$H:$H,ПФ2026!X$5) -> 0 | Y77: =SUMIFS(data!$G:$G,data!$C:$C,$B$31,data!$D:$D,$B$61,data!$F:$F,Y$4,data!$E:$E,$B77,data!$H:$H,ПФ2026!Y$5) -> 0 | Z77: =SUMIFS(data!$G:$G,data!$C:$C,$B$31,data!$D:$D,$B$61,data!$F:$F,Y$4,data!$E:$E,$B77,data!$H:$H,ПФ2026!Z$5) -> 0 | AA77: =SUM(C77,E77,G77,I77,K77,M77,O142,O77,Q77,S77) -> -250000 | AB77: =SUM(D77,F77,H77,J77,L77,N77,P142,P77,R77,T77) -> -99887.31 | AC77: =IFERROR(AB77/AA77,0) -> 0.39954924
B78: Административные расходы | C78: =SUM(C79,C113,C137,C143,C107) -> -4086225 | D78: =SUM(D79,D113,D137,D143,D107) -> -3117842.1 | E78: =SUM(E79,E113,E137,E143,E107) -> -2273925 | F78: =SUM(F79,F113,F137,F143,F107) -> -2278386 | G78: =SUM(G79,G113,G137,G143,G107) -> -3280689 | H78: =SUM(H79,H113,H137,H143,H107) -> -7057384.7 | I78: =SUM(I79,I113,I137,I143,I107) -> -1155345 | J78: =SUM(J79,J113,J137,J143,J107) -> -1487207.8 | ... Z78: =SUM(Z79,Z113,Z137,Z143,Z107) -> 0 | AA78: =C78+E78+G78+I78+K78+M78+O78+Q78+S78+U78+W78+Y78 -> -63514885 | AB78: =D78+F78+H78+J78+L78+N78+P78+R78+T78+V78+X78+Z78 -> -37998497 | AC78: =IFERROR(AB78/AA78,0) -> 0.5982613
B79: Департамент УЧР | C79: =SUM(C80:C106) -> -2938760 | D79: =SUM(D80:D106) -> -311580.48 | E79: =SUM(E80:E106) -> -840640 | F79: =SUM(F80:F106) -> -934895.09 | G79: =SUM(G80:G106) -> -1960224 | H79: =SUM(H80:H106) -> -4108079.3 | I79: =SUM(I80:I106) -> -287880 | J79: =SUM(J80:J106) -> -381457.98 | ... Z79: =SUM(Z80:Z106) -> 0 | AA79: =SUM(C79,E79,G79,I79,K79,M79,O142,O79,Q79,S79,Y79,W79,U79) -> -50693304 | AB79: =D79+F79+H79+J79+L79+N79+P79+R79+T79+V79+X79+Z79 -> -7977964.1 | AC79: =IFERROR(AB79/AA79,0) -> 0.15737708
B80: Вознаграждение, поощрение и поздравление сотрудник | C80: =SUMIFS(data!$G:$G,data!$C:$C,$B$78,data!$D:$D,$B$79,data!$F:$F,C$4,data!$E:$E,$B80,data!$H:$H,ПФ2026!C$5) -> -2252560 | D80: =SUMIFS(data!$G:$G,data!$C:$C,$B$78,data!$D:$D,$B$79,data!$F:$F,C$4,data!$E:$E,$B80,data!$H:$H,ПФ2026!D$5) -> -161094.07 | E80: =SUMIFS(data!$G:$G,data!$C:$C,$B$78,data!$D:$D,$B$79,data!$F:$F,E$4,data!$E:$E,$B80,data!$H:$H,ПФ2026!E$5) -> -5000 | F80: =SUMIFS(data!$G:$G,data!$C:$C,$B$78,data!$D:$D,$B$79,data!$F:$F,E$4,data!$E:$E,$B80,data!$H:$H,ПФ2026!F$5) -> -450000 | G80: =SUMIFS(data!$G:$G,data!$C:$C,$B$78,data!$D:$D,$B$79,data!$F:$F,G$4,data!$E:$E,$B80,data!$H:$H,ПФ2026!G$5) -> -5000 | H80: =SUMIFS(data!$G:$G,data!$C:$C,$B$78,data!$D:$D,$B$79,data!$F:$F,G$4,data!$E:$E,$B80,data!$H:$H,ПФ2026!H$5) -> -2106555.9 | I80: =SUMIFS(data!$G:$G,data!$C:$C,$B$78,data!$D:$D,$B$79,data!$F:$F,I$4,data!$E:$E,$B80,data!$H:$H,ПФ2026!I$5) -> -5000 | J80: =SUMIFS(data!$G:$G,data!$C:$C,$B$78,data!$D:$D,$B$79,data!$F:$F,I$4,data!$E:$E,$B80,data!$H:$H,ПФ2026!J$5) -> -2000 | K80: =SUMIFS(data!$G:$G,data!$C:$C,$B$78,data!$D:$D,$B$79,data!$F:$F,K$4,data!$E:$E,$B80,data!$H:$H,ПФ2026!K$5) -> -5000 | L80: =SUMIFS(data!$G:$G,data!$C:$C,$B$78,data!$D:$D,$B$79,data!$F:$F,K$4,data!$E:$E,$B80,data!$H:$H,ПФ2026!L$5) -> 0 | M80: =SUMIFS(data!$G:$G,data!$C:$C,$B$78,data!$D:$D,$B$79,data!$F:$F,M$4,data!$E:$E,$B80,data!$H:$H,ПФ2026!M$5) -> -5000 | N80: =SUMIFS(data!$G:$G,data!$C:$C,$B$78,data!$D:$D,$B$79,data!$F:$F,M$4,data!$E:$E,$B80,data!$H:$H,ПФ2026!N$5) -> -8950 | O80: =SUMIFS(data!$G:$G,data!$C:$C,$B$78,data!$D:$D,$B$79,data!$F:$F,O$4,data!$E:$E,$B80,data!$H:$H,ПФ2026!O$5) -> -5000 | P80: =SUMIFS(data!$G:$G,data!$C:$C,$B$78,data!$D:$D,$B$79,data!$F:$F,O$4,data!$E:$E,$B80,data!$H:$H,ПФ2026!P$5) -> 0 | Q80: =SUMIFS(data!$G:$G,data!$C:$C,$B$78,data!$D:$D,$B$79,data!$F:$F,Q$4,data!$E:$E,$B80,data!$H:$H,ПФ2026!Q$5) -> -5000 | R80: =SUMIFS(data!$G:$G,data!$C:$C,$B$78,data!$D:$D,$B$79,data!$F:$F,Q$4,data!$E:$E,$B80,data!$H:$H,ПФ2026!R$5) -> 0 | S80: =SUMIFS(data!$G:$G,data!$C:$C,$B$78,data!$D:$D,$B$79,data!$F:$F,S$4,data!$E:$E,$B80,data!$H:$H,ПФ2026!S$5) -> -5000 | T80: =SUMIFS(data!$G:$G,data!$C:$C,$B$78,data!$D:$D,$B$79,data!$F:$F,S$4,data!$E:$E,$B80,data!$H:$H,ПФ2026!T$5) -> 0 | U80: =SUMIFS(data!$G:$G,data!$C:$C,$B$78,data!$D:$D,$B$79,data!$F:$F,U$4,data!$E:$E,$B80,data!$H:$H,ПФ2026!U$5) -> -5005000 | V80: =SUMIFS(data!$G:$G,data!$C:$C,$B$78,data!$D:$D,$B$79,data!$F:$F,U$4,data!$E:$E,$B80,data!$H:$H,ПФ2026!V$5) -> 0 | W80: =SUMIFS(data!$G:$G,data!$C:$C,$B$78,data!$D:$D,$B$79,data!$F:$F,W$4,data!$E:$E,$B80,data!$H:$H,ПФ2026!W$5) -> -5000 | X80: =SUMIFS(data!$G:$G,data!$C:$C,$B$78,data!$D:$D,$B$79,data!$F:$F,W$4,data!$E:$E,$B80,data!$H:$H,ПФ2026!X$5) -> 0 | Y80: =SUMIFS(data!$G:$G,data!$C:$C,$B$78,data!$D:$D,$B$79,data!$F:$F,Y$4,data!$E:$E,$B80,data!$H:$H,ПФ2026!Y$5) -> -30005000 | Z80: =SUMIFS(data!$G:$G,data!$C:$C,$B$78,data!$D:$D,$B$79,data!$F:$F,Y$4,data!$E:$E,$B80,data!$H:$H,ПФ2026!Z$5) -> 0 | AA80: =SUM(C80,E80,G80,I80,K80,M80,O143,O80,Q80,S80,Y80,W80,U80) -> -38022025 | AB80: =D80+F80+H80+J80+L80+N80+P80+R80+T80+V80+X80+Z80 -> -2728600 | AC80: =IFERROR(AB80/AA80,0) -> 0.071763668
B81: Аренда футбольного поля | C81: =SUMIFS(data!$G:$G,data!$C:$C,$B$78,data!$D:$D,$B$79,data!$F:$F,C$4,data!$E:$E,$B81,data!$H:$H,ПФ2026!C$5) -> 0 | D81: =SUMIFS(data!$G:$G,data!$C:$C,$B$78,data!$D:$D,$B$79,data!$F:$F,C$4,data!$E:$E,$B81,data!$H:$H,ПФ2026!D$5) -> 0 | E81: =SUMIFS(data!$G:$G,data!$C:$C,$B$78,data!$D:$D,$B$79,data!$F:$F,E$4,data!$E:$E,$B81,data!$H:$H,ПФ2026!E$5) -> 0 | F81: =SUMIFS(data!$G:$G,data!$C:$C,$B$78,data!$D:$D,$B$79,data!$F:$F,E$4,data!$E:$E,$B81,data!$H:$H,ПФ2026!F$5) -> 0 | G81: =SUMIFS(data!$G:$G,data!$C:$C,$B$78,data!$D:$D,$B$79,data!$F:$F,G$4,data!$E:$E,$B81,data!$H:$H,ПФ2026!G$5) -> 0 | H81: =SUMIFS(data!$G:$G,data!$C:$C,$B$78,data!$D:$D,$B$79,data!$F:$F,G$4,data!$E:$E,$B81,data!$H:$H,ПФ2026!H$5) -> 0 | I81: =SUMIFS(data!$G:$G,data!$C:$C,$B$78,data!$D:$D,$B$79,data!$F:$F,I$4,data!$E:$E,$B81,data!$H:$H,ПФ2026!I$5) -> 0 | J81: =SUMIFS(data!$G:$G,data!$C:$C,$B$78,data!$D:$D,$B$79,data!$F:$F,I$4,data!$E:$E,$B81,data!$H:$H,ПФ2026!J$5) -> -36000 | K81: =SUMIFS(data!$G:$G,data!$C:$C,$B$78,data!$D:$D,$B$79,data!$F:$F,K$4,data!$E:$E,$B81,data!$H:$H,ПФ2026!K$5) -> 0 | L81: =SUMIFS(data!$G:$G,data!$C:$C,$B$78,data!$D:$D,$B$79,data!$F:$F,K$4,data!$E:$E,$B81,data!$H:$H,ПФ2026!L$5) -> 0 | M81: =SUMIFS(data!$G:$G,data!$C:$C,$B$78,data!$D:$D,$B$79,data!$F:$F,M$4,data!$E:$E,$B81,data!$H:$H,ПФ2026!M$5) -> 0 | N81: =SUMIFS(data!$G:$G,data!$C:$C,$B$78,data!$D:$D,$B$79,data!$F:$F,M$4,data!$E:$E,$B81,data!$H:$H,ПФ2026!N$5) -> 0 | O81: =SUMIFS(data!$G:$G,data!$C:$C,$B$78,data!$D:$D,$B$79,data!$F:$F,O$4,data!$E:$E,$B81,data!$H:$H,ПФ2026!O$5) -> 0 | P81: =SUMIFS(data!$G:$G,data!$C:$C,$B$78,data!$D:$D,$B$79,data!$F:$F,O$4,data!$E:$E,$B81,data!$H:$H,ПФ2026!P$5) -> 0 | Q81: =SUMIFS(data!$G:$G,data!$C:$C,$B$78,data!$D:$D,$B$79,data!$F:$F,Q$4,data!$E:$E,$B81,data!$H:$H,ПФ2026!Q$5) -> 0 | R81: =SUMIFS(data!$G:$G,data!$C:$C,$B$78,data!$D:$D,$B$79,data!$F:$F,Q$4,data!$E:$E,$B81,data!$H:$H,ПФ2026!R$5) -> 0 | S81: =SUMIFS(data!$G:$G,data!$C:$C,$B$78,data!$D:$D,$B$79,data!$F:$F,S$4,data!$E:$E,$B81,data!$H:$H,ПФ2026!S$5) -> 0 | T81: =SUMIFS(data!$G:$G,data!$C:$C,$B$78,data!$D:$D,$B$79,data!$F:$F,S$4,data!$E:$E,$B81,data!$H:$H,ПФ2026!T$5) -> 0 | U81: =SUMIFS(data!$G:$G,data!$C:$C,$B$78,data!$D:$D,$B$79,data!$F:$F,U$4,data!$E:$E,$B81,data!$H:$H,ПФ2026!U$5) -> 0 | V81: =SUMIFS(data!$G:$G,data!$C:$C,$B$78,data!$D:$D,$B$79,data!$F:$F,U$4,data!$E:$E,$B81,data!$H:$H,ПФ2026!V$5) -> 0 | W81: =SUMIFS(data!$G:$G,data!$C:$C,$B$78,data!$D:$D,$B$79,data!$F:$F,W$4,data!$E:$E,$B81,data!$H:$H,ПФ2026!W$5) -> 0 | X81: =SUMIFS(data!$G:$G,data!$C:$C,$B$78,data!$D:$D,$B$79,data!$F:$F,W$4,data!$E:$E,$B81,data!$H:$H,ПФ2026!X$5) -> 0 | Y81: =SUMIFS(data!$G:$G,data!$C:$C,$B$78,data!$D:$D,$B$79,data!$F:$F,Y$4,data!$E:$E,$B81,data!$H:$H,ПФ2026!Y$5) -> 0 | Z81: =SUMIFS(data!$G:$G,data!$C:$C,$B$78,data!$D:$D,$B$79,data!$F:$F,Y$4,data!$E:$E,$B81,data!$H:$H,ПФ2026!Z$5) -> 0 | AA81: =SUM(C81,E81,G81,I81,K81,M81,O144,O81,Q81,S81,Y81,W81,U81) -> -15000 | AB81: =D81+F81+H81+J81+L81+N81+P81+R81+T81+V81+X81+Z81 -> -36000 | AC81: =IFERROR(AB81/AA81,0) -> 2.4
B82: Командировочные расходы | C82: =SUMIFS(data!$G:$G,data!$C:$C,$B$78,data!$D:$D,$B$79,data!$F:$F,C$4,data!$E:$E,$B82,data!$H:$H,ПФ2026!C$5) -> 0 | D82: =SUMIFS(data!$G:$G,data!$C:$C,$B$78,data!$D:$D,$B$79,data!$F:$F,C$4,data!$E:$E,$B82,data!$H:$H,ПФ2026!D$5) -> 0 | E82: =SUMIFS(data!$G:$G,data!$C:$C,$B$78,data!$D:$D,$B$79,data!$F:$F,E$4,data!$E:$E,$B82,data!$H:$H,ПФ2026!E$5) -> 0 | F82: =SUMIFS(data!$G:$G,data!$C:$C,$B$78,data!$D:$D,$B$79,data!$F:$F,E$4,data!$E:$E,$B82,data!$H:$H,ПФ2026!F$5) -> 0 | G82: =SUMIFS(data!$G:$G,data!$C:$C,$B$78,data!$D:$D,$B$79,data!$F:$F,G$4,data!$E:$E,$B82,data!$H:$H,ПФ2026!G$5) -> 0 | H82: =SUMIFS(data!$G:$G,data!$C:$C,$B$78,data!$D:$D,$B$79,data!$F:$F,G$4,data!$E:$E,$B82,data!$H:$H,ПФ2026!H$5) -> 0 | I82: =SUMIFS(data!$G:$G,data!$C:$C,$B$78,data!$D:$D,$B$79,data!$F:$F,I$4,data!$E:$E,$B82,data!$H:$H,ПФ2026!I$5) -> 0 | J82: =SUMIFS(data!$G:$G,data!$C:$C,$B$78,data!$D:$D,$B$79,data!$F:$F,I$4,data!$E:$E,$B82,data!$H:$H,ПФ2026!J$5) -> 0 | K82: =SUMIFS(data!$G:$G,data!$C:$C,$B$78,data!$D:$D,$B$79,data!$F:$F,K$4,data!$E:$E,$B82,data!$H:$H,ПФ2026!K$5) -> 0 | L82: =SUMIFS(data!$G:$G,data!$C:$C,$B$78,data!$D:$D,$B$79,data!$F:$F,K$4,data!$E:$E,$B82,data!$H:$H,ПФ2026!L$5) -> 0 | M82: =SUMIFS(data!$G:$G,data!$C:$C,$B$78,data!$D:$D,$B$79,data!$F:$F,M$4,data!$E:$E,$B82,data!$H:$H,ПФ2026!M$5) -> 0 | N82: =SUMIFS(data!$G:$G,data!$C:$C,$B$78,data!$D:$D,$B$79,data!$F:$F,M$4,data!$E:$E,$B82,data!$H:$H,ПФ2026!N$5) -> 0 | O82: =SUMIFS(data!$G:$G,data!$C:$C,$B$78,data!$D:$D,$B$79,data!$F:$F,O$4,data!$E:$E,$B82,data!$H:$H,ПФ2026!O$5) -> 0 | P82: =SUMIFS(data!$G:$G,data!$C:$C,$B$78,data!$D:$D,$B$79,data!$F:$F,O$4,data!$E:$E,$B82,data!$H:$H,ПФ2026!P$5) -> 0 | Q82: =SUMIFS(data!$G:$G,data!$C:$C,$B$78,data!$D:$D,$B$79,data!$F:$F,Q$4,data!$E:$E,$B82,data!$H:$H,ПФ2026!Q$5) -> 0 | R82: =SUMIFS(data!$G:$G,data!$C:$C,$B$78,data!$D:$D,$B$79,data!$F:$F,Q$4,data!$E:$E,$B82,data!$H:$H,ПФ2026!R$5) -> 0 | S82: =SUMIFS(data!$G:$G,data!$C:$C,$B$78,data!$D:$D,$B$79,data!$F:$F,S$4,data!$E:$E,$B82,data!$H:$H,ПФ2026!S$5) -> 0 | T82: =SUMIFS(data!$G:$G,data!$C:$C,$B$78,data!$D:$D,$B$79,data!$F:$F,S$4,data!$E:$E,$B82,data!$H:$H,ПФ2026!T$5) -> 0 | U82: =SUMIFS(data!$G:$G,data!$C:$C,$B$78,data!$D:$D,$B$79,data!$F:$F,U$4,data!$E:$E,$B82,data!$H:$H,ПФ2026!U$5) -> 0 | V82: =SUMIFS(data!$G:$G,data!$C:$C,$B$78,data!$D:$D,$B$79,data!$F:$F,U$4,data!$E:$E,$B82,data!$H:$H,ПФ2026!V$5) -> 0 | W82: =SUMIFS(data!$G:$G,data!$C:$C,$B$78,data!$D:$D,$B$79,data!$F:$F,W$4,data!$E:$E,$B82,data!$H:$H,ПФ2026!W$5) -> 0 | X82: =SUMIFS(data!$G:$G,data!$C:$C,$B$78,data!$D:$D,$B$79,data!$F:$F,W$4,data!$E:$E,$B82,data!$H:$H,ПФ2026!X$5) -> 0 | Y82: =SUMIFS(data!$G:$G,data!$C:$C,$B$78,data!$D:$D,$B$79,data!$F:$F,Y$4,data!$E:$E,$B82,data!$H:$H,ПФ2026!Y$5) -> 0 | Z82: =SUMIFS(data!$G:$G,data!$C:$C,$B$78,data!$D:$D,$B$79,data!$F:$F,Y$4,data!$E:$E,$B82,data!$H:$H,ПФ2026!Z$5) -> 0 | AA82: =SUM(C82,E82,G82,I82,K82,M82,O146,O82,Q82,S82,Y82,W82,U82) -> -10000 | AB82: =D82+F82+H82+J82+L82+N82+P82+R82+T82+V82+X82+Z82 -> 0 | AC82: =IFERROR(AB82/AA82,0) -> 0
B83: Консультации, оценка, юридич., аудиторские услуги | C83: =SUMIFS(data!$G:$G,data!$C:$C,$B$78,data!$D:$D,$B$79,data!$F:$F,C$4,data!$E:$E,$B83,data!$H:$H,ПФ2026!C$5) -> 0 | D83: =SUMIFS(data!$G:$G,data!$C:$C,$B$78,data!$D:$D,$B$79,data!$F:$F,C$4,data!$E:$E,$B83,data!$H:$H,ПФ2026!D$5) -> 0 | E83: =SUMIFS(data!$G:$G,data!$C:$C,$B$78,data!$D:$D,$B$79,data!$F:$F,E$4,data!$E:$E,$B83,data!$H:$H,ПФ2026!E$5) -> 0 | F83: =SUMIFS(data!$G:$G,data!$C:$C,$B$78,data!$D:$D,$B$79,data!$F:$F,E$4,data!$E:$E,$B83,data!$H:$H,ПФ2026!F$5) -> 0 | G83: =SUMIFS(data!$G:$G,data!$C:$C,$B$78,data!$D:$D,$B$79,data!$F:$F,G$4,data!$E:$E,$B83,data!$H:$H,ПФ2026!G$5) -> 0 | H83: =SUMIFS(data!$G:$G,data!$C:$C,$B$78,data!$D:$D,$B$79,data!$F:$F,G$4,data!$E:$E,$B83,data!$H:$H,ПФ2026!H$5) -> 0 | I83: =SUMIFS(data!$G:$G,data!$C:$C,$B$78,data!$D:$D,$B$79,data!$F:$F,I$4,data!$E:$E,$B83,data!$H:$H,ПФ2026!I$5) -> 0 | J83: =SUMIFS(data!$G:$G,data!$C:$C,$B$78,data!$D:$D,$B$79,data!$F:$F,I$4,data!$E:$E,$B83,data!$H:$H,ПФ2026!J$5) -> 0 | K83: =SUMIFS(data!$G:$G,data!$C:$C,$B$78,data!$D:$D,$B$79,data!$F:$F,K$4,data!$E:$E,$B83,data!$H:$H,ПФ2026!K$5) -> 0 | L83: =SUMIFS(data!$G:$G,data!$C:$C,$B$78,data!$D:$D,$B$79,data!$F:$F,K$4,data!$E:$E,$B83,data!$H:$H,ПФ2026!L$5) -> 0 | M83: =SUMIFS(data!$G:$G,data!$C:$C,$B$78,data!$D:$D,$B$79,data!$F:$F,M$4,data!$E:$E,$B83,data!$H:$H,ПФ2026!M$5) -> 0 | N83: =SUMIFS(data!$G:$G,data!$C:$C,$B$78,data!$D:$D,$B$79,data!$F:$F,M$4,data!$E:$E,$B83,data!$H:$H,ПФ2026!N$5) -> 0 | O83: =SUMIFS(data!$G:$G,data!$C:$C,$B$78,data!$D:$D,$B$79,data!$F:$F,O$4,data!$E:$E,$B83,data!$H:$H,ПФ2026!O$5) -> 0 | P83: =SUMIFS(data!$G:$G,data!$C:$C,$B$78,data!$D:$D,$B$79,data!$F:$F,O$4,data!$E:$E,$B83,data!$H:$H,ПФ2026!P$5) -> 0 | Q83: =SUMIFS(data!$G:$G,data!$C:$C,$B$78,data!$D:$D,$B$79,data!$F:$F,Q$4,data!$E:$E,$B83,data!$H:$H,ПФ2026!Q$5) -> 0 | R83: =SUMIFS(data!$G:$G,data!$C:$C,$B$78,data!$D:$D,$B$79,data!$F:$F,Q$4,data!$E:$E,$B83,data!$H:$H,ПФ2026!R$5) -> 0 | S83: =SUMIFS(data!$G:$G,data!$C:$C,$B$78,data!$D:$D,$B$79,data!$F:$F,S$4,data!$E:$E,$B83,data!$H:$H,ПФ2026!S$5) -> 0 | T83: =SUMIFS(data!$G:$G,data!$C:$C,$B$78,data!$D:$D,$B$79,data!$F:$F,S$4,data!$E:$E,$B83,data!$H:$H,ПФ2026!T$5) -> 0 | U83: =SUMIFS(data!$G:$G,data!$C:$C,$B$78,data!$D:$D,$B$79,data!$F:$F,U$4,data!$E:$E,$B83,data!$H:$H,ПФ2026!U$5) -> 0 | V83: =SUMIFS(data!$G:$G,data!$C:$C,$B$78,data!$D:$D,$B$79,data!$F:$F,U$4,data!$E:$E,$B83,data!$H:$H,ПФ2026!V$5) -> 0 | W83: =SUMIFS(data!$G:$G,data!$C:$C,$B$78,data!$D:$D,$B$79,data!$F:$F,W$4,data!$E:$E,$B83,data!$H:$H,ПФ2026!W$5) -> 0 | X83: =SUMIFS(data!$G:$G,data!$C:$C,$B$78,data!$D:$D,$B$79,data!$F:$F,W$4,data!$E:$E,$B83,data!$H:$H,ПФ2026!X$5) -> 0 | Y83: =SUMIFS(data!$G:$G,data!$C:$C,$B$78,data!$D:$D,$B$79,data!$F:$F,Y$4,data!$E:$E,$B83,data!$H:$H,ПФ2026!Y$5) -> 0 | Z83: =SUMIFS(data!$G:$G,data!$C:$C,$B$78,data!$D:$D,$B$79,data!$F:$F,Y$4,data!$E:$E,$B83,data!$H:$H,ПФ2026!Z$5) -> 0 | AA83: =SUM(C83,E83,G83,I83,K83,M83,O147,O83,Q83,S83,Y83,W83,U83) -> -563770 | AB83: =D83+F83+H83+J83+L83+N83+P83+R83+T83+V83+X83+Z83 -> 0 | AC83: =IFERROR(AB83/AA83,0) -> 0
B84: Конференции, презентации, участие на выставках | C84: =SUMIFS(data!$G:$G,data!$C:$C,$B$78,data!$D:$D,$B$79,data!$F:$F,C$4,data!$E:$E,$B84,data!$H:$H,ПФ2026!C$5) -> 0 | D84: =SUMIFS(data!$G:$G,data!$C:$C,$B$78,data!$D:$D,$B$79,data!$F:$F,C$4,data!$E:$E,$B84,data!$H:$H,ПФ2026!D$5) -> 0 | E84: =SUMIFS(data!$G:$G,data!$C:$C,$B$78,data!$D:$D,$B$79,data!$F:$F,E$4,data!$E:$E,$B84,data!$H:$H,ПФ2026!E$5) -> 0 | F84: =SUMIFS(data!$G:$G,data!$C:$C,$B$78,data!$D:$D,$B$79,data!$F:$F,E$4,data!$E:$E,$B84,data!$H:$H,ПФ2026!F$5) -> 0 | G84: =SUMIFS(data!$G:$G,data!$C:$C,$B$78,data!$D:$D,$B$79,data!$F:$F,G$4,data!$E:$E,$B84,data!$H:$H,ПФ2026!G$5) -> 0 | H84: =SUMIFS(data!$G:$G,data!$C:$C,$B$78,data!$D:$D,$B$79,data!$F:$F,G$4,data!$E:$E,$B84,data!$H:$H,ПФ2026!H$5) -> 0 | I84: =SUMIFS(data!$G:$G,data!$C:$C,$B$78,data!$D:$D,$B$79,data!$F:$F,I$4,data!$E:$E,$B84,data!$H:$H,ПФ2026!I$5) -> 0 | J84: =SUMIFS(data!$G:$G,data!$C:$C,$B$78,data!$D:$D,$B$79,data!$F:$F,I$4,data!$E:$E,$B84,data!$H:$H,ПФ2026!J$5) -> -37900 | K84: =SUMIFS(data!$G:$G,data!$C:$C,$B$78,data!$D:$D,$B$79,data!$F:$F,K$4,data!$E:$E,$B84,data!$H:$H,ПФ2026!K$5) -> 0 | L84: =SUMIFS(data!$G:$G,data!$C:$C,$B$78,data!$D:$D,$B$79,data!$F:$F,K$4,data!$E:$E,$B84,data!$H:$H,ПФ2026!L$5) -> 0 | M84: =SUMIFS(data!$G:$G,data!$C:$C,$B$78,data!$D:$D,$B$79,data!$F:$F,M$4,data!$E:$E,$B84,data!$H:$H,ПФ2026!M$5) -> 0 | N84: =SUMIFS(data!$G:$G,data!$C:$C,$B$78,data!$D:$D,$B$79,data!$F:$F,M$4,data!$E:$E,$B84,data!$H:$H,ПФ2026!N$5) -> 0 | O84: =SUMIFS(data!$G:$G,data!$C:$C,$B$78,data!$D:$D,$B$79,data!$F:$F,O$4,data!$E:$E,$B84,data!$H:$H,ПФ2026!O$5) -> 0 | P84: =SUMIFS(data!$G:$G,data!$C:$C,$B$78,data!$D:$D,$B$79,data!$F:$F,O$4,data!$E:$E,$B84,data!$H:$H,ПФ2026!P$5) -> 0 | Q84: =SUMIFS(data!$G:$G,data!$C:$C,$B$78,data!$D:$D,$B$79,data!$F:$F,Q$4,data!$E:$E,$B84,data!$H:$H,ПФ2026!Q$5) -> 0 | R84: =SUMIFS(data!$G:$G,data!$C:$C,$B$78,data!$D:$D,$B$79,data!$F:$F,Q$4,data!$E:$E,$B84,data!$H:$H,ПФ2026!R$5) -> 0 | S84: =SUMIFS(data!$G:$G,data!$C:$C,$B$78,data!$D:$D,$B$79,data!$F:$F,S$4,data!$E:$E,$B84,data!$H:$H,ПФ2026!S$5) -> 0 | T84: =SUMIFS(data!$G:$G,data!$C:$C,$B$78,data!$D:$D,$B$79,data!$F:$F,S$4,data!$E:$E,$B84,data!$H:$H,ПФ2026!T$5) -> 0 | U84: =SUMIFS(data!$G:$G,data!$C:$C,$B$78,data!$D:$D,$B$79,data!$F:$F,U$4,data!$E:$E,$B84,data!$H:$H,ПФ2026!U$5) -> 0 | V84: =SUMIFS(data!$G:$G,data!$C:$C,$B$78,data!$D:$D,$B$79,data!$F:$F,U$4,data!$E:$E,$B84,data!$H:$H,ПФ2026!V$5) -> 0 | W84: =SUMIFS(data!$G:$G,data!$C:$C,$B$78,data!$D:$D,$B$79,data!$F:$F,W$4,data!$E:$E,$B84,data!$H:$H,ПФ2026!W$5) -> 0 | X84: =SUMIFS(data!$G:$G,data!$C:$C,$B$78,data!$D:$D,$B$79,data!$F:$F,W$4,data!$E:$E,$B84,data!$H:$H,ПФ2026!X$5) -> 0 | Y84: =SUMIFS(data!$G:$G,data!$C:$C,$B$78,data!$D:$D,$B$79,data!$F:$F,Y$4,data!$E:$E,$B84,data!$H:$H,ПФ2026!Y$5) -> 0 | Z84: =SUMIFS(data!$G:$G,data!$C:$C,$B$78,data!$D:$D,$B$79,data!$F:$F,Y$4,data!$E:$E,$B84,data!$H:$H,ПФ2026!Z$5) -> 0 | AA84: =SUM(C84,E84,G84,I84,K84,M84,O148,O84,Q84,S84,Y84,W84,U84) -> 0 | AB84: =D84+F84+H84+J84+L84+N84+P84+R84+T84+V84+X84+Z84 -> -37900 | AC84: =IFERROR(AB84/AA84,0) -> 0
B85: Корпоративное мероприятие | C85: =SUMIFS(data!$G:$G,data!$C:$C,$B$78,data!$D:$D,$B$79,data!$F:$F,C$4,data!$E:$E,$B85,data!$H:$H,ПФ2026!C$5) -> -115000 | D85: =SUMIFS(data!$G:$G,data!$C:$C,$B$78,data!$D:$D,$B$79,data!$F:$F,C$4,data!$E:$E,$B85,data!$H:$H,ПФ2026!D$5) -> -107780 | E85: =SUMIFS(data!$G:$G,data!$C:$C,$B$78,data!$D:$D,$B$79,data!$F:$F,E$4,data!$E:$E,$B85,data!$H:$H,ПФ2026!E$5) -> -210000 | F85: =SUMIFS(data!$G:$G,data!$C:$C,$B$78,data!$D:$D,$B$79,data!$F:$F,E$4,data!$E:$E,$B85,data!$H:$H,ПФ2026!F$5) -> -261621 | G85: =SUMIFS(data!$G:$G,data!$C:$C,$B$78,data!$D:$D,$B$79,data!$F:$F,G$4,data!$E:$E,$B85,data!$H:$H,ПФ2026!G$5) -> -795000 | H85: =SUMIFS(data!$G:$G,data!$C:$C,$B$78,data!$D:$D,$B$79,data!$F:$F,G$4,data!$E:$E,$B85,data!$H:$H,ПФ2026!H$5) -> -842729.82 | I85: =SUMIFS(data!$G:$G,data!$C:$C,$B$78,data!$D:$D,$B$79,data!$F:$F,I$4,data!$E:$E,$B85,data!$H:$H,ПФ2026!I$5) -> -45000 | J85: =SUMIFS(data!$G:$G,data!$C:$C,$B$78,data!$D:$D,$B$79,data!$F:$F,I$4,data!$E:$E,$B85,data!$H:$H,ПФ2026!J$5) -> -32344.07 | K85: =SUMIFS(data!$G:$G,data!$C:$C,$B$78,data!$D:$D,$B$79,data!$F:$F,K$4,data!$E:$E,$B85,data!$H:$H,ПФ2026!K$5) -> -315000 | L85: =SUMIFS(data!$G:$G,data!$C:$C,$B$78,data!$D:$D,$B$79,data!$F:$F,K$4,data!$E:$E,$B85,data!$H:$H,ПФ2026!L$5) -> -1154474.4 | M85: =SUMIFS(data!$G:$G,data!$C:$C,$B$78,data!$D:$D,$B$79,data!$F:$F,M$4,data!$E:$E,$B85,data!$H:$H,ПФ2026!M$5) -> -90000 | N85: =SUMIFS(data!$G:$G,data!$C:$C,$B$78,data!$D:$D,$B$79,data!$F:$F,M$4,data!$E:$E,$B85,data!$H:$H,ПФ2026!N$5) -> -381560.33 | O85: =SUMIFS(data!$G:$G,data!$C:$C,$B$78,data!$D:$D,$B$79,data!$F:$F,O$4,data!$E:$E,$B85,data!$H:$H,ПФ2026!O$5) -> -515000 | P85: =SUMIFS(data!$G:$G,data!$C:$C,$B$78,data!$D:$D,$B$79,data!$F:$F,O$4,data!$E:$E,$B85,data!$H:$H,ПФ2026!P$5) -> 0 | Q85: =SUMIFS(data!$G:$G,data!$C:$C,$B$78,data!$D:$D,$B$79,data!$F:$F,Q$4,data!$E:$E,$B85,data!$H:$H,ПФ2026!Q$5) -> -15000 | R85: =SUMIFS(data!$G:$G,data!$C:$C,$B$78,data!$D:$D,$B$79,data!$F:$F,Q$4,data!$E:$E,$B85,data!$H:$H,ПФ2026!R$5) -> 0 | S85: =SUMIFS(data!$G:$G,data!$C:$C,$B$78,data!$D:$D,$B$79,data!$F:$F,S$4,data!$E:$E,$B85,data!$H:$H,ПФ2026!S$5) -> -315000 | T85: =SUMIFS(data!$G:$G,data!$C:$C,$B$78,data!$D:$D,$B$79,data!$F:$F,S$4,data!$E:$E,$B85,data!$H:$H,ПФ2026!T$5) -> 0 | U85: =SUMIFS(data!$G:$G,data!$C:$C,$B$78,data!$D:$D,$B$79,data!$F:$F,U$4,data!$E:$E,$B85,data!$H:$H,ПФ2026!U$5) -> -2015000 | V85: =SUMIFS(data!$G:$G,data!$C:$C,$B$78,data!$D:$D,$B$79,data!$F:$F,U$4,data!$E:$E,$B85,data!$H:$H,ПФ2026!V$5) -> 0 | W85: =SUMIFS(data!$G:$G,data!$C:$C,$B$78,data!$D:$D,$B$79,data!$F:$F,W$4,data!$E:$E,$B85,data!$H:$H,ПФ2026!W$5) -> -220000 | X85: =SUMIFS(data!$G:$G,data!$C:$C,$B$78,data!$D:$D,$B$79,data!$F:$F,W$4,data!$E:$E,$B85,data!$H:$H,ПФ2026!X$5) -> 0 | Y85: =SUMIFS(data!$G:$G,data!$C:$C,$B$78,data!$D:$D,$B$79,data!$F:$F,Y$4,data!$E:$E,$B85,data!$H:$H,ПФ2026!Y$5) -> -2115000 | Z85: =SUMIFS(data!$G:$G,data!$C:$C,$B$78,data!$D:$D,$B$79,data!$F:$F,Y$4,data!$E:$E,$B85,data!$H:$H,ПФ2026!Z$5) -> 0 | AA85: =SUM(C85,E85,G85,I85,K85,M85,O149,O85,Q85,S85,Y85,W85,U85) -> -6875000 | AB85: =D85+F85+H85+J85+L85+N85+P85+R85+T85+V85+X85+Z85 -> -2780509.7 | AC85: =IFERROR(AB85/AA85,0) -> 0.40443777
B86: Материальная помощь (рождение,похороны,болезни) | C86: =SUMIFS(data!$G:$G,data!$C:$C,$B$78,data!$D:$D,$B$79,data!$F:$F,C$4,data!$E:$E,$B86,data!$H:$H,ПФ2026!C$5) -> -60000 | D86: =SUMIFS(data!$G:$G,data!$C:$C,$B$78,data!$D:$D,$B$79,data!$F:$F,C$4,data!$E:$E,$B86,data!$H:$H,ПФ2026!D$5) -> -25100 | E86: =SUMIFS(data!$G:$G,data!$C:$C,$B$78,data!$D:$D,$B$79,data!$F:$F,E$4,data!$E:$E,$B86,data!$H:$H,ПФ2026!E$5) -> -60000 | F86: =SUMIFS(data!$G:$G,data!$C:$C,$B$78,data!$D:$D,$B$79,data!$F:$F,E$4,data!$E:$E,$B86,data!$H:$H,ПФ2026!F$5) -> -50000 | G86: =SUMIFS(data!$G:$G,data!$C:$C,$B$78,data!$D:$D,$B$79,data!$F:$F,G$4,data!$E:$E,$B86,data!$H:$H,ПФ2026!G$5) -> -60000 | H86: =SUMIFS(data!$G:$G,data!$C:$C,$B$78,data!$D:$D,$B$79,data!$F:$F,G$4,data!$E:$E,$B86,data!$H:$H,ПФ2026!H$5) -> -25000 | I86: =SUMIFS(data!$G:$G,data!$C:$C,$B$78,data!$D:$D,$B$79,data!$F:$F,I$4,data!$E:$E,$B86,data!$H:$H,ПФ2026!I$5) -> -60000 | J86: =SUMIFS(data!$G:$G,data!$C:$C,$B$78,data!$D:$D,$B$79,data!$F:$F,I$4,data!$E:$E,$B86,data!$H:$H,ПФ2026!J$5) -> -55000 | K86: =SUMIFS(data!$G:$G,data!$C:$C,$B$78,data!$D:$D,$B$79,data!$F:$F,K$4,data!$E:$E,$B86,data!$H:$H,ПФ2026!K$5) -> -60000 | L86: =SUMIFS(data!$G:$G,data!$C:$C,$B$78,data!$D:$D,$B$79,data!$F:$F,K$4,data!$E:$E,$B86,data!$H:$H,ПФ2026!L$5) -> -25000 | M86: =SUMIFS(data!$G:$G,data!$C:$C,$B$78,data!$D:$D,$B$79,data!$F:$F,M$4,data!$E:$E,$B86,data!$H:$H,ПФ2026!M$5) -> -60000 | N86: =SUMIFS(data!$G:$G,data!$C:$C,$B$78,data!$D:$D,$B$79,data!$F:$F,M$4,data!$E:$E,$B86,data!$H:$H,ПФ2026!N$5) -> -25000 | O86: =SUMIFS(data!$G:$G,data!$C:$C,$B$78,data!$D:$D,$B$79,data!$F:$F,O$4,data!$E:$E,$B86,data!$H:$H,ПФ2026!O$5) -> -60000 | P86: =SUMIFS(data!$G:$G,data!$C:$C,$B$78,data!$D:$D,$B$79,data!$F:$F,O$4,data!$E:$E,$B86,data!$H:$H,ПФ2026!P$5) -> 0 | Q86: =SUMIFS(data!$G:$G,data!$C:$C,$B$78,data!$D:$D,$B$79,data!$F:$F,Q$4,data!$E:$E,$B86,data!$H:$H,ПФ2026!Q$5) -> -60000 | R86: =SUMIFS(data!$G:$G,data!$C:$C,$B$78,data!$D:$D,$B$79,data!$F:$F,Q$4,data!$E:$E,$B86,data!$H:$H,ПФ2026!R$5) -> 0 | S86: =SUMIFS(data!$G:$G,data!$C:$C,$B$78,data!$D:$D,$B$79,data!$F:$F,S$4,data!$E:$E,$B86,data!$H:$H,ПФ2026!S$5) -> -60000 | T86: =SUMIFS(data!$G:$G,data!$C:$C,$B$78,data!$D:$D,$B$79,data!$F:$F,S$4,data!$E:$E,$B86,data!$H:$H,ПФ2026!T$5) -> 0 | U86: =SUMIFS(data!$G:$G,data!$C:$C,$B$78,data!$D:$D,$B$79,data!$F:$F,U$4,data!$E:$E,$B86,data!$H:$H,ПФ2026!U$5) -> -60000 | V86: =SUMIFS(data!$G:$G,data!$C:$C,$B$78,data!$D:$D,$B$79,data!$F:$F,U$4,data!$E:$E,$B86,data!$H:$H,ПФ2026!V$5) -> 0 | W86: =SUMIFS(data!$G:$G,data!$C:$C,$B$78,data!$D:$D,$B$79,data!$F:$F,W$4,data!$E:$E,$B86,data!$H:$H,ПФ2026!W$5) -> -60000 | X86: =SUMIFS(data!$G:$G,data!$C:$C,$B$78,data!$D:$D,$B$79,data!$F:$F,W$4,data!$E:$E,$B86,data!$H:$H,ПФ2026!X$5) -> 0 | Y86: =SUMIFS(data!$G:$G,data!$C:$C,$B$78,data!$D:$D,$B$79,data!$F:$F,Y$4,data!$E:$E,$B86,data!$H:$H,ПФ2026!Y$5) -> -60000 | Z86: =SUMIFS(data!$G:$G,data!$C:$C,$B$78,data!$D:$D,$B$79,data!$F:$F,Y$4,data!$E:$E,$B86,data!$H:$H,ПФ2026!Z$5) -> 0 | AA86: =SUM(C86,E86,G86,I86,K86,M86,O150,O86,Q86,S86,Y86,W86,U86) -> -720000 | AB86: =D86+F86+H86+J86+L86+N86+P86+R86+T86+V86+X86+Z86 -> -205100 | AC86: =IFERROR(AB86/AA86,0) -> 0.28486111
